Workbook

Sheet cover
B3: Community studied: | C3: =df_geo!B2 -> #N/A
B4: Census subdivision #: | C4: =df_geo!A2 -> 1000000
B6: Region: | C6: =df_geo!B3 -> Canada
B7: Province: | C7: =df_geo!B4 -> #N/A
B9: Effective date: | C9: =TODAY() -> 46154

Sheet priorities
B2: VULNERABILITY PROFILE — COMMUNITY SNAPSHOT TEXT | E2: PRIORITY ISSUES — TOP RANKED VULNERABILITY CONCERNS
B3: The text below is auto-generated from the index results entered on the Inputs sheet. Copy the relevant cells into the Community Snapshot as needed. Not all indices need to appear — include those most pertinent to the community's profile. | E3: Show top: | F3: 5 | G3: ← Change this number to show more or fewer issues (1–8)
B4: Index | C4: Generated narrative text | E4: Rank | F4: Issues | G4: Implication
B5: Residential instability | C5: =IFERROR(SUBSTITUTE(textlib!G2&" "&INDEX(textlib!B2:F2,MATCH(vuln!I36,{"Low","Below average","Average","Above average","High"},0)),"[COMPARATOR]",vuln!K36),"Information unavailable") -> Information unavailable | E5: =IF(1<=$F$3,1,"") -> 1 | F5: =IFERROR(IF(1<=$F$3,INDEX(vuln!$G$36:$G$43,MATCH(LARGE(vuln!$M$36:$M$43,1),vuln!$M$36:$M$43,0)),""),"Information unavailable") -> Information unavailable | G5: =IFERROR(IF(1<=$F$3,SUBSTITUTE(INDEX(textlib!$G$2:$G$9,MATCH(LARGE(vuln!$M$36:$M$43,1),vuln!$M$36:$M$43,0))&" "&INDEX(textlib!$B$2:$F$9,MATCH(LARGE(vuln!$M$36:$M$43,1),vuln!$M$36:$M$43,0),MATCH(INDEX(vuln!$I$36:$I$43,MATCH(LARGE(vuln!$M$36:$M$43,1),vuln!$M$36:$M$43,0)),{"Low","Below average","Average","Above average","High"},0)),"[COMPARATOR]",INDEX(vuln!$K$36:$K$43,MATCH(LARGE(vuln!$M$36:$M$43,1),vuln!$M$36:$M$43,0))),"" ),"Information unavailable") -> Information unavailable
B6: Economic dependency | C6: =IFERROR(SUBSTITUTE(textlib!G3&" "&INDEX(textlib!B3:F3,MATCH(vuln!I37,{"Low","Below average","Average","Above average","High"},0)),"[COMPARATOR]",vuln!K37),"Information unavailable") -> Information unavailable | E6: =IF(2<=$F$3,2,"") -> 2 | F6: =IFERROR(IF(2<=$F$3,INDEX(vuln!$G$36:$G$43,MATCH(LARGE(vuln!$M$36:$M$43,2),vuln!$M$36:$M$43,0)),""),"Information unavailable") -> Information unavailable | G6: =IFERROR(IF(2<=$F$3,SUBSTITUTE(INDEX(textlib!$G$2:$G$9,MATCH(LARGE(vuln!$M$36:$M$43,2),vuln!$M$36:$M$43,0))&" "&INDEX(textlib!$B$2:$F$9,MATCH(LARGE(vuln!$M$36:$M$43,2),vuln!$M$36:$M$43,0),MATCH(INDEX(vuln!$I$36:$I$43,MATCH(LARGE(vuln!$M$36:$M$43,2),vuln!$M$36:$M$43,0)),{"Low","Below average","Average","Above average","High"},0)),"[COMPARATOR]",INDEX(vuln!$K$36:$K$43,MATCH(LARGE(vuln!$M$36:$M$43,2),vuln!$M$36:$M$43,0))),"" ),"Information unavailable") -> Information unavailable
B7: Ethno-cultural composition | C7: =IFERROR(SUBSTITUTE(textlib!G4&" "&INDEX(textlib!B4:F4,MATCH(vuln!I38,{"Low","Below average","Average","Above average","High"},0)),"[COMPARATOR]",vuln!K38),"Information unavailable") -> Information unavailable | E7: =IF(3<=$F$3,3,"") -> 3 | F7: =IFERROR(IF(3<=$F$3,INDEX(vuln!$G$36:$G$43,MATCH(LARGE(vuln!$M$36:$M$43,3),vuln!$M$36:$M$43,0)),""),"Information unavailable") -> Information unavailable | G7: =IFERROR(IF(3<=$F$3,SUBSTITUTE(INDEX(textlib!$G$2:$G$9,MATCH(LARGE(vuln!$M$36:$M$43,3),vuln!$M$36:$M$43,0))&" "&INDEX(textlib!$B$2:$F$9,MATCH(LARGE(vuln!$M$36:$M$43,3),vuln!$M$36:$M$43,0),MATCH(INDEX(vuln!$I$36:$I$43,MATCH(LARGE(vuln!$M$36:$M$43,3),vuln!$M$36:$M$43,0)),{"Low","Below average","Average","Above average","High"},0)),"[COMPARATOR]",INDEX(vuln!$K$36:$K$43,MATCH(LARGE(vuln!$M$36:$M$43,3),vuln!$M$36:$M$43,0))),"" ),"Information unavailable") -> Information unavailable
B8: Situational vulnerability | C8: =IFERROR(SUBSTITUTE(textlib!G5&" "&INDEX(textlib!B5:F5,MATCH(vuln!I39,{"Low","Below average","Average","Above average","High"},0)),"[COMPARATOR]",vuln!K39),"Information unavailable") -> Information unavailable | E8: =IF(4<=$F$3,4,"") -> 4 | F8: =IFERROR(IF(4<=$F$3,INDEX(vuln!$G$36:$G$43,MATCH(LARGE(vuln!$M$36:$M$43,4),vuln!$M$36:$M$43,0)),""),"Information unavailable") -> Information unavailable | G8: =IFERROR(IF(4<=$F$3,SUBSTITUTE(INDEX(textlib!$G$2:$G$9,MATCH(LARGE(vuln!$M$36:$M$43,4),vuln!$M$36:$M$43,0))&" "&INDEX(textlib!$B$2:$F$9,MATCH(LARGE(vuln!$M$36:$M$43,4),vuln!$M$36:$M$43,0),MATCH(INDEX(vuln!$I$36:$I$43,MATCH(LARGE(vuln!$M$36:$M$43,4),vuln!$M$36:$M$43,0)),{"Low","Below average","Average","Above average","High"},0)),"[COMPARATOR]",INDEX(vuln!$K$36:$K$43,MATCH(LARGE(vuln!$M$36:$M$43,4),vuln!$M$36:$M$43,0))),"" ),"Information unavailable") -> Information unavailable
B9: Social resilience | C9: =IFERROR(SUBSTITUTE(textlib!G6&" "&INDEX(textlib!B6:F6,MATCH(vuln!I40,{"Low","Below average","Average","Above average","High"},0)),"[COMPARATOR]",vuln!K40),"Information unavailable") -> Information unavailable | E9: =IF(5<=$F$3,5,"") -> 5 | F9: =IFERROR(IF(5<=$F$3,INDEX(vuln!$G$36:$G$43,MATCH(LARGE(vuln!$M$36:$M$43,5),vuln!$M$36:$M$43,0)),""),"Information unavailable") -> Information unavailable | G9: =IFERROR(IF(5<=$F$3,SUBSTITUTE(INDEX(textlib!$G$2:$G$9,MATCH(LARGE(vuln!$M$36:$M$43,5),vuln!$M$36:$M$43,0))&" "&INDEX(textlib!$B$2:$F$9,MATCH(LARGE(vuln!$M$36:$M$43,5),vuln!$M$36:$M$43,0),MATCH(INDEX(vuln!$I$36:$I$43,MATCH(LARGE(vuln!$M$36:$M$43,5),vuln!$M$36:$M$43,0)),{"Low","Below average","Average","Above average","High"},0)),"[COMPARATOR]",INDEX(vuln!$K$36:$K$43,MATCH(LARGE(vuln!$M$36:$M$43,5),vuln!$M$36:$M$43,0))),"" ),"Information unavailable") -> Information unavailable
B10: Social vulnerability | C10: =IFERROR(SUBSTITUTE(textlib!G7&" "&INDEX(textlib!B7:F7,MATCH(vuln!I41,{"Low","Below average","Average","Above average","High"},0)),"[COMPARATOR]",vuln!K41),"Information unavailable") -> Information unavailable | E10: =IF(6<=$F$3,6,"") | F10: =IF(6<=$F$3,INDEX(vuln!$G$36:$G$43,MATCH(LARGE(vuln!$M$36:$M$43,6),vuln!$M$36:$M$43,0)),"") | G10: =IFERROR(IF(6<=$F$3,SUBSTITUTE(INDEX(textlib!$G$2:$G$9,MATCH(LARGE(vuln!$M$36:$M$43,6),vuln!$M$36:$M$43,0))&" "&INDEX(textlib!$B$2:$F$9,MATCH(LARGE(vuln!$M$36:$M$43,6),vuln!$M$36:$M$43,0),MATCH(INDEX(vuln!$I$36:$I$43,MATCH(LARGE(vuln!$M$36:$M$43,6),vuln!$M$36:$M$43,0)),{"Low","Below average","Average","Above average","High"},0)),"[COMPARATOR]",INDEX(vuln!$K$36:$K$43,MATCH(LARGE(vuln!$M$36:$M$43,6),vuln!$M$36:$M$43,0))),"" ),"Information unavailable")
B11: Material deprivation | C11: =IFERROR(SUBSTITUTE(textlib!G8&" "&INDEX(textlib!B8:F8,MATCH(vuln!I42,{"Low","Below average","Average","Above average","High"},0)),"[COMPARATOR]",vuln!K42),"Information unavailable") -> Information unavailable | E11: =IF(7<=$F$3,7,"") | F11: =IF(7<=$F$3,INDEX(vuln!$G$36:$G$43,MATCH(LARGE(vuln!$M$36:$M$43,7),vuln!$M$36:$M$43,0)),"") | G11: =IFERROR(IF(7<=$F$3,SUBSTITUTE(INDEX(textlib!$G$2:$G$9,MATCH(LARGE(vuln!$M$36:$M$43,7),vuln!$M$36:$M$43,0))&" "&INDEX(textlib!$B$2:$F$9,MATCH(LARGE(vuln!$M$36:$M$43,7),vuln!$M$36:$M$43,0),MATCH(INDEX(vuln!$I$36:$I$43,MATCH(LARGE(vuln!$M$36:$M$43,7),vuln!$M$36:$M$43,0)),{"Low","Below average","Average","Above average","High"},0)),"[COMPARATOR]",INDEX(vuln!$K$36:$K$43,MATCH(LARGE(vuln!$M$36:$M$43,7),vuln!$M$36:$M$43,0))),"" ),"Information unavailable")
B12: Social deprivation | C12: =IFERROR(SUBSTITUTE(textlib!G9&" "&INDEX(textlib!B9:F9,MATCH(vuln!I43,{"Low","Below average","Average","Above average","High"},0)),"[COMPARATOR]",vuln!K43),"Information unavailable") -> Information unavailable | E12: =IF(8<=$F$3,8,"") | F12: =IF(8<=$F$3,INDEX(vuln!$G$36:$G$43,MATCH(LARGE(vuln!$M$36:$M$43,8),vuln!$M$36:$M$43,0)),"") | G12: =IFERROR(IF(8<=$F$3,SUBSTITUTE(INDEX(textlib!$G$2:$G$9,MATCH(LARGE(vuln!$M$36:$M$43,8),vuln!$M$36:$M$43,0))&" "&INDEX(textlib!$B$2:$F$9,MATCH(LARGE(vuln!$M$36:$M$43,8),vuln!$M$36:$M$43,0),MATCH(INDEX(vuln!$I$36:$I$43,MATCH(LARGE(vuln!$M$36:$M$43,8),vuln!$M$36:$M$43,0)),{"Low","Below average","Average","Above average","High"},0)),"[COMPARATOR]",INDEX(vuln!$K$36:$K$43,MATCH(LARGE(vuln!$M$36:$M$43,8),vuln!$M$36:$M$43,0))),"" ),"Information unavailable")
B14: Source: Canadian Index of Multiple Deprivation (CIMD), Canadian Index of Social Resilience (CISR), Canadian Index of Social Vulnerability (CISV), Material and Social Deprivation Index (MSDI). Results derived from 2021 Census dissemination area data. Note: Social resilience is inverted — high resilience is a favourable outcome. | E14: Ranking is based on the provincial quintile result. Social resilience is inverted (low resilience ranks as high severity). Where two indices share the same quintile result, the index appearing earlier in the table ranks first. All eight indices are available on the Generated Text sheet.

Sheet summary
B4: DEMOGRAPHIC PROFILE | F4: ECONOMIC PROFILE
B5: =IFERROR(popn_fut!$M$35,"x") -> x | C5: =IFERROR(popn_now!F36,"x") -> x | D5: =IFERROR(popn_now!F37,"x") -> 0 | F5: {=IFERROR(income!$C$40,"x")} -> x | G5: =IFERROR(income!$C$45,"x") -> x | H5: =IFERROR(econ!$C$63,"x") -> x
B6: Total population (2025) | C6: Population change (2021-2025) | D6: Change to 0 to 14 year olds (2021-2025) | F6: Median before-tax household income (2020) | G6: Before-tax single person income (2020) | H6: ="Largest employer: " & econ!N38 -> Largest employer:
B7: =IFERROR(popn_now!F45,"x") -> x | C7: =IFERROR(popn_now!F46,"x") -> x | D7: =IFERROR(popn_now!J152,"x") -> x | F7: {=IFERROR(ABS(econ!J93),"x")} -> 0 | G7: =IFERROR(econ!$C$24,"x") -> x | H7: =IFERROR(IF(econ!C26 = 0, "x", econ!C26),0) -> x
B8: Change to 15 to 34 year olds (2021-2025) | C8: Change to 65+ year olds (2021-2025) | D8: Share of population that moved to the community between 2016-2021 | F8: ="Net " & IF(econ!J93<0,"outflow","inflow") & " of commuters (2021)" -> Net inflow of commuters (2021) | G8: Persons 15+ in the labour force (2021) | H8: Persons 15+ unemployed (2021)
B9: =popn_now!C195 -> x | C9: =popn_now!C196 -> x | D9: =popn_now!C194 -> x | F9: =income!$C$142 -> x | G9: =IFERROR(IF(SUM(income!D99:E99) = 0, "x", SUM(income!D99:E99)),"x") -> x | H9: =sales!C44 -> x
B10: Visible minority identifying persons (2021) | C10: Immigrants (2021) | D10: Indigenous identifying persons (2021) | F10: Persons living below the poverty line (2021) | G10: Households with very-low or low incomes | H10: Change in province-wide wage/salaries (2019-2024)
B11: {=IFERROR(hh!C39,"x")} -> x | C11: =hh!D39 -> x | D11: {=IF(hh!E39=0,"x",hh!E39)} -> x
B12: Total households (2021) | C12: Owner households (2021) | D12: Renter households (2021)
B13: =IFERROR(hh!F56,"x") -> x | C13: =hh!F52 -> x | D13: =IF(hh!G90>0,hh!G90,"x") -> x
B14: Single person households (2021) | C14: Lone parent households (2021) | D14: Suppressed 25 to 34 year old led households (2021)
B17: HOUSING PROFILE | F17: HOUSING NEED
B18: =IFERROR(dwell!N17,"x") -> x | C18: =IFERROR(1-dwell!C50/dwell!N17,"x") -> x | D18: =dwell!F103 -> x | F18: =need!C107 -> x | G18: =need!C108 -> x | H18: =need!C109 -> x
B19: Total dwellings (2021) | C19: Not occupied by usual residents (e.g., vacant, STRs, second homes - 2021) | D19: Single-detached dwellings (2021) | F19: Overcrowded households (2021) | G19: Dwellings needing major repair (2021) | H19: Dwellings deemed unaffordable (2021)
B20: =IFERROR(IF(AVERAGE(dwell!C17:H17) = 0, "x", AVERAGE(dwell!C17:H17)),"x") -> x | C20: =IFERROR(SUM(dwell!F51:F52),"x") -> x | D20: =IFERROR(SUM(dwell!C287:D287),"x") -> 0 | F20: =need!C111 -> x | G20: =need!D111 -> x | H20: =need!E111 -> x
B21: Average annual permit totals (2018-2023) | C21: Dwellings built pre-1980 | D21: Estimated dwellings with moderate to high flood susceptibility | F21: Total households in core housing need (2021) | G21: Owner households in core housing need (2021) | H21: Renter households in core housing need (2021)
B22: =rental!C34 -> x | C22: =IF(rental!D34="x",rental!F34,rental!D34) -> x | D22: =dwell!C181 -> x | F22: =IFERROR(need!E199/need!D199,"x") -> x | G22: =IFERROR(SUM(need!D200:D201)/need!D199,"x") -> x | H22: =need!C112 -> x
B23: Change in average rents (2020-2025) | C23: =IF(rental!D34="x","Provincial","Local") & " rental vacancy rate" -> Provincial rental vacancy rate | D23: Rentals considered affordable (2021) | F23: Households in core need that are single persons (2021) | G23: Households in core need that are very low or low income earning (2021) | H23: Total households in extreme core housing need (2021)
B24: =IFERROR(IF(dwell!H189 = 0, "x", dwell!H189),"x") -> x | C24: =sales!D34 -> x | D24: =IFERROR(dwell!D256,"x") -> x
B25: Change in affordable rentals (2016-2021) | C25: Change in average sale prices (2020-2025) | D25: Estimated short-term rentals that are potentially long-term housing (2025)
B26: =dwell!C145 -> x | C26: =SUM(dwell!C374:D374) -> 0 | D26: =SUM(dwell!C377:D377) -> 0
B27: Renters living in subsidized housing (2021) | C27: Non-market housing inventory (beds and units) | D27: Shelter spaces for various population groups
B30: UNIT DEMAND / PROJECTED NEEDS
B31: =IFERROR(popn_fut!D81,"x") -> x | C31: =IFERROR(popn_fut!S81,"x") -> 0 | D31: =IFERROR(popn_fut!S82,"x") -> 0
B32: Projected population (2035) | C32: Projected population change (2025-2035) | D32: Change to 0 to 14 year olds (2025-2035)
B33: =IFERROR(popn_fut!S90,"x") -> x | C33: =IFERROR(popn_fut!S91,"x") -> x | D33: =IFERROR(projection!D72,"x") -> x
B34: Change to 15 to 34 year olds (2021-2025) | C34: Change to 65+ year olds (2021-2025) | D34: Estimated 2025 dwelling deficit
B35: =IFERROR(projection!E354,"x") -> x | C35: =IFERROR(1-projection!E362/projection!E365,"x") -> x | D35: {=IFERROR(SUM(projection!G273:G277)/SUM(projection!C273:C277),"x")} -> x
B36: Projected total new dwelling demand (2025-2035) | C36: Demand for affordable units (2025-2035) | D36: Demand for rental units (2025-2035)
B37: =IFERROR(ABS(projection!E460),"x") -> x | C37: =MAX(projection!D529,projection!D528) -> 0
B38: ="Potential "& IF(projection!E460<0,"outflow","inflow") & " of unit demand from employment pressures (2025)" -> Potential inflow of unit demand from employment pressures (2025) | C38: Total maximum senior housing bed/unit demand (by 2035)

Sheet projection
A1: CSD | B1: CD | C1: PR | D1: Scenario
A2: =df_geo!A2 -> 1000000 | B2: =_xlfn.NUMBERVALUE(LEFT(A2,4)) -> 1000 | C2: =_xlfn.NUMBERVALUE(LEFT(B2,2)) -> 10 | D2: =popn_fut!D2 -> #N/A
B5: DEMOGRAPHIC PROJECTIONS
B7: ESTIMATED POPULATION
C8: 2015 | D8: 2016 | E8: 2017 | F8: 2018 | G8: 2019 | H8: 2020 | I8: 2021 | J8: 2022 | K8: 2023 | L8: 2024 | M8: 2025 | N8: 2026 | O8: 2027 | P8: 2028 | Q8: 2029 | R8: 2030 | S8: 2031 | T8: 2032 | U8: 2033 | V8: 2034 | W8: 2035 | X8: 2036 | Y8: 2037 | Z8: 2038 | AA8: 2039 | AB8: 2040 | AC8: 2041 | AD8: 2042 | AE8: 2043 | AF8: 2044 | AG8: 2045 | AH8: 2046 | AI8: 2047 | AJ8: 2048 | AK8: 2049 | AL8: 2050
B9: Total | C9: {=INDEX(df_est_csd!$C$2:$BA$10, MATCH($A$2, df_est_csd!$B$2:$B$10, 0), MATCH(TEXT(C$8, "####"), df_est_csd!$C$1:$BA$1, 0))} -> #N/A | D9: {=INDEX(df_est_csd!$C$2:$BA$10, MATCH($A$2, df_est_csd!$B$2:$B$10, 0), MATCH(TEXT(D$8, "####"), df_est_csd!$C$1:$BA$1, 0))} -> #N/A | E9: {=INDEX(df_est_csd!$C$2:$BA$10, MATCH($A$2, df_est_csd!$B$2:$B$10, 0), MATCH(TEXT(E$8, "####"), df_est_csd!$C$1:$BA$1, 0))} -> #N/A | F9: {=INDEX(df_est_csd!$C$2:$BA$10, MATCH($A$2, df_est_csd!$B$2:$B$10, 0), MATCH(TEXT(F$8, "####"), df_est_csd!$C$1:$BA$1, 0))} -> #N/A | G9: {=INDEX(df_est_csd!$C$2:$BA$10, MATCH($A$2, df_est_csd!$B$2:$B$10, 0), MATCH(TEXT(G$8, "####"), df_est_csd!$C$1:$BA$1, 0))} -> #N/A | H9: {=INDEX(df_est_csd!$C$2:$BA$10, MATCH($A$2, df_est_csd!$B$2:$B$10, 0), MATCH(TEXT(H$8, "####"), df_est_csd!$C$1:$BA$1, 0))} -> #N/A | I9: {=INDEX(df_est_csd!$C$2:$BA$10, MATCH($A$2, df_est_csd!$B$2:$B$10, 0), MATCH(TEXT(I$8, "####"), df_est_csd!$C$1:$BA$1, 0))} -> #N/A | J9: {=INDEX(df_est_csd!$C$2:$BA$10, MATCH($A$2, df_est_csd!$B$2:$B$10, 0), MATCH(TEXT(J$8, "####"), df_est_csd!$C$1:$BA$1, 0))} -> #N/A | ... M9: {=INDEX(df_est_csd!$C$2:$BA$10, MATCH($A$2, df_est_csd!$B$2:$B$10, 0), MATCH(TEXT(M$8, "####"), df_est_csd!$C$1:$BA$1, 0))} -> #N/A | N9: {=IFERROR(MROUND(INDEX(df_proj!$E$2:$AD$1000, MATCH(1, ($A$2 = df_proj!$A$2:$A$1000) * (df_proj!$B$2:$B$1000 = $B9) * (df_proj!$C$2:$C$1000 = $D$2), 0), MATCH(TEXT(N$8, "####"), df_proj!$E$1:$AD$1,0)),5),MROUND(INDEX(df_proj!$E$2:$AD$1000, MATCH(1, ($B$2 = df_proj!$A$2:$A$1000) * (df_proj!$B$2:$B$1000 = $B9) * (df_proj!$C$2:$C$1000 = $D$2), 0), MATCH(TEXT(N$8, "####"), df_proj!$E$1:$AD$1,0)) * popn_fut!$C81/popn_fut!$E81,5))} -> #N/A | O9: {=IFERROR(MROUND(INDEX(df_proj!$E$2:$AD$1000, MATCH(1, ($A$2 = df_proj!$A$2:$A$1000) * (df_proj!$B$2:$B$1000 = $B9) * (df_proj!$C$2:$C$1000 = $D$2), 0), MATCH(TEXT(O$8, "####"), df_proj!$E$1:$AD$1,0)),5),MROUND(INDEX(df_proj!$E$2:$AD$1000, MATCH(1, ($B$2 = df_proj!$A$2:$A$1000) * (df_proj!$B$2:$B$1000 = $B9) * (df_proj!$C$2:$C$1000 = $D$2), 0), MATCH(TEXT(O$8, "####"), df_proj!$E$1:$AD$1,0)) * popn_fut!$C81/popn_fut!$E81,5))} -> #N/A | P9: {=IFERROR(MROUND(INDEX(df_proj!$E$2:$AD$1000, MATCH(1, ($A$2 = df_proj!$A$2:$A$1000) * (df_proj!$B$2:$B$1000 = $B9) * (df_proj!$C$2:$C$1000 = $D$2), 0), MATCH(TEXT(P$8, "####"), df_proj!$E$1:$AD$1,0)),5),MROUND(INDEX(df_proj!$E$2:$AD$1000, MATCH(1, ($B$2 = df_proj!$A$2:$A$1000) * (df_proj!$B$2:$B$1000 = $B9) * (df_proj!$C$2:$C$1000 = $D$2), 0), MATCH(TEXT(P$8, "####"), df_proj!$E$1:$AD$1,0)) * popn_fut!$C81/popn_fut!$E81,5))} -> #N/A | Q9: {=IFERROR(MROUND(INDEX(df_proj!$E$2:$AD$1000, MATCH(1, ($A$2 = df_proj!$A$2:$A$1000) * (df_proj!$B$2:$B$1000 = $B9) * (df_proj!$C$2:$C$1000 = $D$2), 0), MATCH(TEXT(Q$8, "####"), df_proj!$E$1:$AD$1,0)),5),MROUND(INDEX(df_proj!$E$2:$AD$1000, MATCH(1, ($B$2 = df_proj!$A$2:$A$1000) * (df_proj!$B$2:$B$1000 = $B9) * (df_proj!$C$2:$C$1000 = $D$2), 0), MATCH(TEXT(Q$8, "####"), df_proj!$E$1:$AD$1,0)) * popn_fut!$C81/popn_fut!$E81,5))} -> #N/A | R9: {=IFERROR(MROUND(INDEX(df_proj!$E$2:$AD$1000, MATCH(1, ($A$2 = df_proj!$A$2:$A$1000) * (df_proj!$B$2:$B$1000 = $B9) * (df_proj!$C$2:$C$1000 = $D$2), 0), MATCH(TEXT(R$8, "####"), df_proj!$E$1:$AD$1,0)),5),MROUND(INDEX(df_proj!$E$2:$AD$1000, MATCH(1, ($B$2 = df_proj!$A$2:$A$1000) * (df_proj!$B$2:$B$1000 = $B9) * (df_proj!$C$2:$C$1000 = $D$2), 0), MATCH(TEXT(R$8, "####"), df_proj!$E$1:$AD$1,0)) * popn_fut!$C81/popn_fut!$E81,5))} -> #N/A | S9: {=IFERROR(MROUND(INDEX(df_proj!$E$2:$AD$1000, MATCH(1, ($A$2 = df_proj!$A$2:$A$1000) * (df_proj!$B$2:$B$1000 = $B9) * (df_proj!$C$2:$C$1000 = $D$2), 0), MATCH(TEXT(S$8, "####"), df_proj!$E$1:$AD$1,0)),5),MROUND(INDEX(df_proj!$E$2:$AD$1000, MATCH(1, ($B$2 = df_proj!$A$2:$A$1000) * (df_proj!$B$2:$B$1000 = $B9) * (df_proj!$C$2:$C$1000 = $D$2), 0), MATCH(TEXT(S$8, "####"), df_proj!$E$1:$AD$1,0)) * popn_fut!$C81/popn_fut!$E81,5))} -> #N/A | T9: {=IFERROR(MROUND(INDEX(df_proj!$E$2:$AD$1000, MATCH(1, ($A$2 = df_proj!$A$2:$A$1000) * (df_proj!$B$2:$B$1000 = $B9) * (df_proj!$C$2:$C$1000 = $D$2), 0), MATCH(TEXT(T$8, "####"), df_proj!$E$1:$AD$1,0)),5),MROUND(INDEX(df_proj!$E$2:$AD$1000, MATCH(1, ($B$2 = df_proj!$A$2:$A$1000) * (df_proj!$B$2:$B$1000 = $B9) * (df_proj!$C$2:$C$1000 = $D$2), 0), MATCH(TEXT(T$8, "####"), df_proj!$E$1:$AD$1,0)) * popn_fut!$C81/popn_fut!$E81,5))} -> #N/A | U9: {=IFERROR(MROUND(INDEX(df_proj!$E$2:$AD$1000, MATCH(1, ($A$2 = df_proj!$A$2:$A$1000) * (df_proj!$B$2:$B$1000 = $B9) * (df_proj!$C$2:$C$1000 = $D$2), 0), MATCH(TEXT(U$8, "####"), df_proj!$E$1:$AD$1,0)),5),MROUND(INDEX(df_proj!$E$2:$AD$1000, MATCH(1, ($B$2 = df_proj!$A$2:$A$1000) * (df_proj!$B$2:$B$1000 = $B9) * (df_proj!$C$2:$C$1000 = $D$2), 0), MATCH(TEXT(U$8, "####"), df_proj!$E$1:$AD$1,0)) * popn_fut!$C81/popn_fut!$E81,5))} -> #N/A | ... AL9: {=IFERROR(MROUND(INDEX(df_proj!$E$2:$AD$1000, MATCH(1, ($A$2 = df_proj!$A$2:$A$1000) * (df_proj!$B$2:$B$1000 = $B9) * (df_proj!$C$2:$C$1000 = $D$2), 0), MATCH(TEXT(AL$8, "####"), df_proj!$E$1:$AD$1,0)),5),MROUND(INDEX(df_proj!$E$2:$AD$1000, MATCH(1, ($B$2 = df_proj!$A$2:$A$1000) * (df_proj!$B$2:$B$1000 = $B9) * (df_proj!$C$2:$C$1000 = $D$2), 0), MATCH(TEXT(AL$8, "####"), df_proj!$E$1:$AD$1,0)) * popn_fut!$C81/popn_fut!$E81,5))} -> #N/A
A10: 0 | B10: 0 to 4 | D10: {=popn_now!J13:J30} -> #N/A | I10: {=popn_now!K13:K30} -> #N/A | M10: {=IFERROR(MROUND(INDEX(df_proj!$E$2:$AD$1000, MATCH(1, ($A$2 = df_proj!$A$2:$A$1000) * (df_proj!$B$2:$B$1000 = $B10) * (df_proj!$C$2:$C$1000 = $D$2), 0), MATCH(TEXT(M$8, "####"), df_proj!$E$1:$AD$1,0)),5),MROUND(INDEX(df_proj!$E$2:$AD$1000, MATCH(1, ($B$2 = df_proj!$A$2:$A$1000) * (df_proj!$B$2:$B$1000 = $B10) * (df_proj!$C$2:$C$1000 = $D$2), 0), MATCH(TEXT(M$8, "####"), df_proj!$E$1:$AD$1,0)) * popn_fut!$C82/popn_fut!$E82,5))} -> #N/A | N10: {=IFERROR(MROUND(INDEX(df_proj!$E$2:$AD$1000, MATCH(1, ($A$2 = df_proj!$A$2:$A$1000) * (df_proj!$B$2:$B$1000 = $B10) * (df_proj!$C$2:$C$1000 = $D$2), 0), MATCH(TEXT(N$8, "####"), df_proj!$E$1:$AD$1,0)),5),MROUND(INDEX(df_proj!$E$2:$AD$1000, MATCH(1, ($B$2 = df_proj!$A$2:$A$1000) * (df_proj!$B$2:$B$1000 = $B10) * (df_proj!$C$2:$C$1000 = $D$2), 0), MATCH(TEXT(N$8, "####"), df_proj!$E$1:$AD$1,0)) * popn_fut!$C82/popn_fut!$E82,5))} -> #N/A | O10: {=IFERROR(MROUND(INDEX(df_proj!$E$2:$AD$1000, MATCH(1, ($A$2 = df_proj!$A$2:$A$1000) * (df_proj!$B$2:$B$1000 = $B10) * (df_proj!$C$2:$C$1000 = $D$2), 0), MATCH(TEXT(O$8, "####"), df_proj!$E$1:$AD$1,0)),5),MROUND(INDEX(df_proj!$E$2:$AD$1000, MATCH(1, ($B$2 = df_proj!$A$2:$A$1000) * (df_proj!$B$2:$B$1000 = $B10) * (df_proj!$C$2:$C$1000 = $D$2), 0), MATCH(TEXT(O$8, "####"), df_proj!$E$1:$AD$1,0)) * popn_fut!$C82/popn_fut!$E82,5))} -> #N/A | P10: {=IFERROR(MROUND(INDEX(df_proj!$E$2:$AD$1000, MATCH(1, ($A$2 = df_proj!$A$2:$A$1000) * (df_proj!$B$2:$B$1000 = $B10) * (df_proj!$C$2:$C$1000 = $D$2), 0), MATCH(TEXT(P$8, "####"), df_proj!$E$1:$AD$1,0)),5),MROUND(INDEX(df_proj!$E$2:$AD$1000, MATCH(1, ($B$2 = df_proj!$A$2:$A$1000) * (df_proj!$B$2:$B$1000 = $B10) * (df_proj!$C$2:$C$1000 = $D$2), 0), MATCH(TEXT(P$8, "####"), df_proj!$E$1:$AD$1,0)) * popn_fut!$C82/popn_fut!$E82,5))} -> #N/A | Q10: {=IFERROR(MROUND(INDEX(df_proj!$E$2:$AD$1000, MATCH(1, ($A$2 = df_proj!$A$2:$A$1000) * (df_proj!$B$2:$B$1000 = $B10) * (df_proj!$C$2:$C$1000 = $D$2), 0), MATCH(TEXT(Q$8, "####"), df_proj!$E$1:$AD$1,0)),5),MROUND(INDEX(df_proj!$E$2:$AD$1000, MATCH(1, ($B$2 = df_proj!$A$2:$A$1000) * (df_proj!$B$2:$B$1000 = $B10) * (df_proj!$C$2:$C$1000 = $D$2), 0), MATCH(TEXT(Q$8, "####"), df_proj!$E$1:$AD$1,0)) * popn_fut!$C82/popn_fut!$E82,5))} -> #N/A | R10: {=IFERROR(MROUND(INDEX(df_proj!$E$2:$AD$1000, MATCH(1, ($A$2 = df_proj!$A$2:$A$1000) * (df_proj!$B$2:$B$1000 = $B10) * (df_proj!$C$2:$C$1000 = $D$2), 0), MATCH(TEXT(R$8, "####"), df_proj!$E$1:$AD$1,0)),5),MROUND(INDEX(df_proj!$E$2:$AD$1000, MATCH(1, ($B$2 = df_proj!$A$2:$A$1000) * (df_proj!$B$2:$B$1000 = $B10) * (df_proj!$C$2:$C$1000 = $D$2), 0), MATCH(TEXT(R$8, "####"), df_proj!$E$1:$AD$1,0)) * popn_fut!$C82/popn_fut!$E82,5))} -> #N/A | S10: {=IFERROR(MROUND(INDEX(df_proj!$E$2:$AD$1000, MATCH(1, ($A$2 = df_proj!$A$2:$A$1000) * (df_proj!$B$2:$B$1000 = $B10) * (df_proj!$C$2:$C$1000 = $D$2), 0), MATCH(TEXT(S$8, "####"), df_proj!$E$1:$AD$1,0)),5),MROUND(INDEX(df_proj!$E$2:$AD$1000, MATCH(1, ($B$2 = df_proj!$A$2:$A$1000) * (df_proj!$B$2:$B$1000 = $B10) * (df_proj!$C$2:$C$1000 = $D$2), 0), MATCH(TEXT(S$8, "####"), df_proj!$E$1:$AD$1,0)) * popn_fut!$C82/popn_fut!$E82,5))} -> #N/A | T10: {=IFERROR(MROUND(INDEX(df_proj!$E$2:$AD$1000, MATCH(1, ($A$2 = df_proj!$A$2:$A$1000) * (df_proj!$B$2:$B$1000 = $B10) * (df_proj!$C$2:$C$1000 = $D$2), 0), MATCH(TEXT(T$8, "####"), df_proj!$E$1:$AD$1,0)),5),MROUND(INDEX(df_proj!$E$2:$AD$1000, MATCH(1, ($B$2 = df_proj!$A$2:$A$1000) * (df_proj!$B$2:$B$1000 = $B10) * (df_proj!$C$2:$C$1000 = $D$2), 0), MATCH(TEXT(T$8, "####"), df_proj!$E$1:$AD$1,0)) * popn_fut!$C82/popn_fut!$E82,5))} -> #N/A | ... AL10: {=IFERROR(MROUND(INDEX(df_proj!$E$2:$AD$1000, MATCH(1, ($A$2 = df_proj!$A$2:$A$1000) * (df_proj!$B$2:$B$1000 = $B10) * (df_proj!$C$2:$C$1000 = $D$2), 0), MATCH(TEXT(AL$8, "####"), df_proj!$E$1:$AD$1,0)),5),MROUND(INDEX(df_proj!$E$2:$AD$1000, MATCH(1, ($B$2 = df_proj!$A$2:$A$1000) * (df_proj!$B$2:$B$1000 = $B10) * (df_proj!$C$2:$C$1000 = $D$2), 0), MATCH(TEXT(AL$8, "####"), df_proj!$E$1:$AD$1,0)) * popn_fut!$C82/popn_fut!$E82,5))} -> #N/A | AM10: =I10 -> #N/A | AP10: =W10 -> #N/A
A11: 5 | B11: 5 to 9 | D11: #N/A | I11: #N/A | M11: {=IFERROR(MROUND(INDEX(df_proj!$E$2:$AD$1000, MATCH(1, ($A$2 = df_proj!$A$2:$A$1000) * (df_proj!$B$2:$B$1000 = $B11) * (df_proj!$C$2:$C$1000 = $D$2), 0), MATCH(TEXT(M$8, "####"), df_proj!$E$1:$AD$1,0)),5),MROUND(INDEX(df_proj!$E$2:$AD$1000, MATCH(1, ($B$2 = df_proj!$A$2:$A$1000) * (df_proj!$B$2:$B$1000 = $B11) * (df_proj!$C$2:$C$1000 = $D$2), 0), MATCH(TEXT(M$8, "####"), df_proj!$E$1:$AD$1,0)) * popn_fut!$C83/popn_fut!$E83,5))} -> #N/A | N11: {=IFERROR(MROUND(INDEX(df_proj!$E$2:$AD$1000, MATCH(1, ($A$2 = df_proj!$A$2:$A$1000) * (df_proj!$B$2:$B$1000 = $B11) * (df_proj!$C$2:$C$1000 = $D$2), 0), MATCH(TEXT(N$8, "####"), df_proj!$E$1:$AD$1,0)),5),MROUND(INDEX(df_proj!$E$2:$AD$1000, MATCH(1, ($B$2 = df_proj!$A$2:$A$1000) * (df_proj!$B$2:$B$1000 = $B11) * (df_proj!$C$2:$C$1000 = $D$2), 0), MATCH(TEXT(N$8, "####"), df_proj!$E$1:$AD$1,0)) * popn_fut!$C83/popn_fut!$E83,5))} -> #N/A | O11: {=IFERROR(MROUND(INDEX(df_proj!$E$2:$AD$1000, MATCH(1, ($A$2 = df_proj!$A$2:$A$1000) * (df_proj!$B$2:$B$1000 = $B11) * (df_proj!$C$2:$C$1000 = $D$2), 0), MATCH(TEXT(O$8, "####"), df_proj!$E$1:$AD$1,0)),5),MROUND(INDEX(df_proj!$E$2:$AD$1000, MATCH(1, ($B$2 = df_proj!$A$2:$A$1000) * (df_proj!$B$2:$B$1000 = $B11) * (df_proj!$C$2:$C$1000 = $D$2), 0), MATCH(TEXT(O$8, "####"), df_proj!$E$1:$AD$1,0)) * popn_fut!$C83/popn_fut!$E83,5))} -> #N/A | P11: {=IFERROR(MROUND(INDEX(df_proj!$E$2:$AD$1000, MATCH(1, ($A$2 = df_proj!$A$2:$A$1000) * (df_proj!$B$2:$B$1000 = $B11) * (df_proj!$C$2:$C$1000 = $D$2), 0), MATCH(TEXT(P$8, "####"), df_proj!$E$1:$AD$1,0)),5),MROUND(INDEX(df_proj!$E$2:$AD$1000, MATCH(1, ($B$2 = df_proj!$A$2:$A$1000) * (df_proj!$B$2:$B$1000 = $B11) * (df_proj!$C$2:$C$1000 = $D$2), 0), MATCH(TEXT(P$8, "####"), df_proj!$E$1:$AD$1,0)) * popn_fut!$C83/popn_fut!$E83,5))} -> #N/A | Q11: {=IFERROR(MROUND(INDEX(df_proj!$E$2:$AD$1000, MATCH(1, ($A$2 = df_proj!$A$2:$A$1000) * (df_proj!$B$2:$B$1000 = $B11) * (df_proj!$C$2:$C$1000 = $D$2), 0), MATCH(TEXT(Q$8, "####"), df_proj!$E$1:$AD$1,0)),5),MROUND(INDEX(df_proj!$E$2:$AD$1000, MATCH(1, ($B$2 = df_proj!$A$2:$A$1000) * (df_proj!$B$2:$B$1000 = $B11) * (df_proj!$C$2:$C$1000 = $D$2), 0), MATCH(TEXT(Q$8, "####"), df_proj!$E$1:$AD$1,0)) * popn_fut!$C83/popn_fut!$E83,5))} -> #N/A | R11: {=IFERROR(MROUND(INDEX(df_proj!$E$2:$AD$1000, MATCH(1, ($A$2 = df_proj!$A$2:$A$1000) * (df_proj!$B$2:$B$1000 = $B11) * (df_proj!$C$2:$C$1000 = $D$2), 0), MATCH(TEXT(R$8, "####"), df_proj!$E$1:$AD$1,0)),5),MROUND(INDEX(df_proj!$E$2:$AD$1000, MATCH(1, ($B$2 = df_proj!$A$2:$A$1000) * (df_proj!$B$2:$B$1000 = $B11) * (df_proj!$C$2:$C$1000 = $D$2), 0), MATCH(TEXT(R$8, "####"), df_proj!$E$1:$AD$1,0)) * popn_fut!$C83/popn_fut!$E83,5))} -> #N/A | S11: {=IFERROR(MROUND(INDEX(df_proj!$E$2:$AD$1000, MATCH(1, ($A$2 = df_proj!$A$2:$A$1000) * (df_proj!$B$2:$B$1000 = $B11) * (df_proj!$C$2:$C$1000 = $D$2), 0), MATCH(TEXT(S$8, "####"), df_proj!$E$1:$AD$1,0)),5),MROUND(INDEX(df_proj!$E$2:$AD$1000, MATCH(1, ($B$2 = df_proj!$A$2:$A$1000) * (df_proj!$B$2:$B$1000 = $B11) * (df_proj!$C$2:$C$1000 = $D$2), 0), MATCH(TEXT(S$8, "####"), df_proj!$E$1:$AD$1,0)) * popn_fut!$C83/popn_fut!$E83,5))} -> #N/A | T11: {=IFERROR(MROUND(INDEX(df_proj!$E$2:$AD$1000, MATCH(1, ($A$2 = df_proj!$A$2:$A$1000) * (df_proj!$B$2:$B$1000 = $B11) * (df_proj!$C$2:$C$1000 = $D$2), 0), MATCH(TEXT(T$8, "####"), df_proj!$E$1:$AD$1,0)),5),MROUND(INDEX(df_proj!$E$2:$AD$1000, MATCH(1, ($B$2 = df_proj!$A$2:$A$1000) * (df_proj!$B$2:$B$1000 = $B11) * (df_proj!$C$2:$C$1000 = $D$2), 0), MATCH(TEXT(T$8, "####"), df_proj!$E$1:$AD$1,0)) * popn_fut!$C83/popn_fut!$E83,5))} -> #N/A | ... AL11: {=IFERROR(MROUND(INDEX(df_proj!$E$2:$AD$1000, MATCH(1, ($A$2 = df_proj!$A$2:$A$1000) * (df_proj!$B$2:$B$1000 = $B11) * (df_proj!$C$2:$C$1000 = $D$2), 0), MATCH(TEXT(AL$8, "####"), df_proj!$E$1:$AD$1,0)),5),MROUND(INDEX(df_proj!$E$2:$AD$1000, MATCH(1, ($B$2 = df_proj!$A$2:$A$1000) * (df_proj!$B$2:$B$1000 = $B11) * (df_proj!$C$2:$C$1000 = $D$2), 0), MATCH(TEXT(AL$8, "####"), df_proj!$E$1:$AD$1,0)) * popn_fut!$C83/popn_fut!$E83,5))} -> #N/A | AM11: =AM10+I11 -> #N/A | AP11: =AP10+W11 -> #N/A
A12: 10 | B12: 10 to 14 | D12: #N/A | I12: #N/A | M12: {=IFERROR(MROUND(INDEX(df_proj!$E$2:$AD$1000, MATCH(1, ($A$2 = df_proj!$A$2:$A$1000) * (df_proj!$B$2:$B$1000 = $B12) * (df_proj!$C$2:$C$1000 = $D$2), 0), MATCH(TEXT(M$8, "####"), df_proj!$E$1:$AD$1,0)),5),MROUND(INDEX(df_proj!$E$2:$AD$1000, MATCH(1, ($B$2 = df_proj!$A$2:$A$1000) * (df_proj!$B$2:$B$1000 = $B12) * (df_proj!$C$2:$C$1000 = $D$2), 0), MATCH(TEXT(M$8, "####"), df_proj!$E$1:$AD$1,0)) * popn_fut!$C84/popn_fut!$E84,5))} -> #N/A | N12: {=IFERROR(MROUND(INDEX(df_proj!$E$2:$AD$1000, MATCH(1, ($A$2 = df_proj!$A$2:$A$1000) * (df_proj!$B$2:$B$1000 = $B12) * (df_proj!$C$2:$C$1000 = $D$2), 0), MATCH(TEXT(N$8, "####"), df_proj!$E$1:$AD$1,0)),5),MROUND(INDEX(df_proj!$E$2:$AD$1000, MATCH(1, ($B$2 = df_proj!$A$2:$A$1000) * (df_proj!$B$2:$B$1000 = $B12) * (df_proj!$C$2:$C$1000 = $D$2), 0), MATCH(TEXT(N$8, "####"), df_proj!$E$1:$AD$1,0)) * popn_fut!$C84/popn_fut!$E84,5))} -> #N/A | O12: {=IFERROR(MROUND(INDEX(df_proj!$E$2:$AD$1000, MATCH(1, ($A$2 = df_proj!$A$2:$A$1000) * (df_proj!$B$2:$B$1000 = $B12) * (df_proj!$C$2:$C$1000 = $D$2), 0), MATCH(TEXT(O$8, "####"), df_proj!$E$1:$AD$1,0)),5),MROUND(INDEX(df_proj!$E$2:$AD$1000, MATCH(1, ($B$2 = df_proj!$A$2:$A$1000) * (df_proj!$B$2:$B$1000 = $B12) * (df_proj!$C$2:$C$1000 = $D$2), 0), MATCH(TEXT(O$8, "####"), df_proj!$E$1:$AD$1,0)) * popn_fut!$C84/popn_fut!$E84,5))} -> #N/A | P12: {=IFERROR(MROUND(INDEX(df_proj!$E$2:$AD$1000, MATCH(1, ($A$2 = df_proj!$A$2:$A$1000) * (df_proj!$B$2:$B$1000 = $B12) * (df_proj!$C$2:$C$1000 = $D$2), 0), MATCH(TEXT(P$8, "####"), df_proj!$E$1:$AD$1,0)),5),MROUND(INDEX(df_proj!$E$2:$AD$1000, MATCH(1, ($B$2 = df_proj!$A$2:$A$1000) * (df_proj!$B$2:$B$1000 = $B12) * (df_proj!$C$2:$C$1000 = $D$2), 0), MATCH(TEXT(P$8, "####"), df_proj!$E$1:$AD$1,0)) * popn_fut!$C84/popn_fut!$E84,5))} -> #N/A | Q12: {=IFERROR(MROUND(INDEX(df_proj!$E$2:$AD$1000, MATCH(1, ($A$2 = df_proj!$A$2:$A$1000) * (df_proj!$B$2:$B$1000 = $B12) * (df_proj!$C$2:$C$1000 = $D$2), 0), MATCH(TEXT(Q$8, "####"), df_proj!$E$1:$AD$1,0)),5),MROUND(INDEX(df_proj!$E$2:$AD$1000, MATCH(1, ($B$2 = df_proj!$A$2:$A$1000) * (df_proj!$B$2:$B$1000 = $B12) * (df_proj!$C$2:$C$1000 = $D$2), 0), MATCH(TEXT(Q$8, "####"), df_proj!$E$1:$AD$1,0)) * popn_fut!$C84/popn_fut!$E84,5))} -> #N/A | R12: {=IFERROR(MROUND(INDEX(df_proj!$E$2:$AD$1000, MATCH(1, ($A$2 = df_proj!$A$2:$A$1000) * (df_proj!$B$2:$B$1000 = $B12) * (df_proj!$C$2:$C$1000 = $D$2), 0), MATCH(TEXT(R$8, "####"), df_proj!$E$1:$AD$1,0)),5),MROUND(INDEX(df_proj!$E$2:$AD$1000, MATCH(1, ($B$2 = df_proj!$A$2:$A$1000) * (df_proj!$B$2:$B$1000 = $B12) * (df_proj!$C$2:$C$1000 = $D$2), 0), MATCH(TEXT(R$8, "####"), df_proj!$E$1:$AD$1,0)) * popn_fut!$C84/popn_fut!$E84,5))} -> #N/A | S12: {=IFERROR(MROUND(INDEX(df_proj!$E$2:$AD$1000, MATCH(1, ($A$2 = df_proj!$A$2:$A$1000) * (df_proj!$B$2:$B$1000 = $B12) * (df_proj!$C$2:$C$1000 = $D$2), 0), MATCH(TEXT(S$8, "####"), df_proj!$E$1:$AD$1,0)),5),MROUND(INDEX(df_proj!$E$2:$AD$1000, MATCH(1, ($B$2 = df_proj!$A$2:$A$1000) * (df_proj!$B$2:$B$1000 = $B12) * (df_proj!$C$2:$C$1000 = $D$2), 0), MATCH(TEXT(S$8, "####"), df_proj!$E$1:$AD$1,0)) * popn_fut!$C84/popn_fut!$E84,5))} -> #N/A | T12: {=IFERROR(MROUND(INDEX(df_proj!$E$2:$AD$1000, MATCH(1, ($A$2 = df_proj!$A$2:$A$1000) * (df_proj!$B$2:$B$1000 = $B12) * (df_proj!$C$2:$C$1000 = $D$2), 0), MATCH(TEXT(T$8, "####"), df_proj!$E$1:$AD$1,0)),5),MROUND(INDEX(df_proj!$E$2:$AD$1000, MATCH(1, ($B$2 = df_proj!$A$2:$A$1000) * (df_proj!$B$2:$B$1000 = $B12) * (df_proj!$C$2:$C$1000 = $D$2), 0), MATCH(TEXT(T$8, "####"), df_proj!$E$1:$AD$1,0)) * popn_fut!$C84/popn_fut!$E84,5))} -> #N/A | ... AL12: {=IFERROR(MROUND(INDEX(df_proj!$E$2:$AD$1000, MATCH(1, ($A$2 = df_proj!$A$2:$A$1000) * (df_proj!$B$2:$B$1000 = $B12) * (df_proj!$C$2:$C$1000 = $D$2), 0), MATCH(TEXT(AL$8, "####"), df_proj!$E$1:$AD$1,0)),5),MROUND(INDEX(df_proj!$E$2:$AD$1000, MATCH(1, ($B$2 = df_proj!$A$2:$A$1000) * (df_proj!$B$2:$B$1000 = $B12) * (df_proj!$C$2:$C$1000 = $D$2), 0), MATCH(TEXT(AL$8, "####"), df_proj!$E$1:$AD$1,0)) * popn_fut!$C84/popn_fut!$E84,5))} -> #N/A | AM12: =AM11+I12 -> #N/A | AP12: =AP11+W12 -> #N/A
A13: 15 | B13: 15 to 19 | D13: #N/A | I13: #N/A | M13: {=IFERROR(MROUND(INDEX(df_proj!$E$2:$AD$1000, MATCH(1, ($A$2 = df_proj!$A$2:$A$1000) * (df_proj!$B$2:$B$1000 = $B13) * (df_proj!$C$2:$C$1000 = $D$2), 0), MATCH(TEXT(M$8, "####"), df_proj!$E$1:$AD$1,0)),5),MROUND(INDEX(df_proj!$E$2:$AD$1000, MATCH(1, ($B$2 = df_proj!$A$2:$A$1000) * (df_proj!$B$2:$B$1000 = $B13) * (df_proj!$C$2:$C$1000 = $D$2), 0), MATCH(TEXT(M$8, "####"), df_proj!$E$1:$AD$1,0)) * popn_fut!$C85/popn_fut!$E85,5))} -> #N/A | N13: {=IFERROR(MROUND(INDEX(df_proj!$E$2:$AD$1000, MATCH(1, ($A$2 = df_proj!$A$2:$A$1000) * (df_proj!$B$2:$B$1000 = $B13) * (df_proj!$C$2:$C$1000 = $D$2), 0), MATCH(TEXT(N$8, "####"), df_proj!$E$1:$AD$1,0)),5),MROUND(INDEX(df_proj!$E$2:$AD$1000, MATCH(1, ($B$2 = df_proj!$A$2:$A$1000) * (df_proj!$B$2:$B$1000 = $B13) * (df_proj!$C$2:$C$1000 = $D$2), 0), MATCH(TEXT(N$8, "####"), df_proj!$E$1:$AD$1,0)) * popn_fut!$C85/popn_fut!$E85,5))} -> #N/A | O13: {=IFERROR(MROUND(INDEX(df_proj!$E$2:$AD$1000, MATCH(1, ($A$2 = df_proj!$A$2:$A$1000) * (df_proj!$B$2:$B$1000 = $B13) * (df_proj!$C$2:$C$1000 = $D$2), 0), MATCH(TEXT(O$8, "####"), df_proj!$E$1:$AD$1,0)),5),MROUND(INDEX(df_proj!$E$2:$AD$1000, MATCH(1, ($B$2 = df_proj!$A$2:$A$1000) * (df_proj!$B$2:$B$1000 = $B13) * (df_proj!$C$2:$C$1000 = $D$2), 0), MATCH(TEXT(O$8, "####"), df_proj!$E$1:$AD$1,0)) * popn_fut!$C85/popn_fut!$E85,5))} -> #N/A | P13: {=IFERROR(MROUND(INDEX(df_proj!$E$2:$AD$1000, MATCH(1, ($A$2 = df_proj!$A$2:$A$1000) * (df_proj!$B$2:$B$1000 = $B13) * (df_proj!$C$2:$C$1000 = $D$2), 0), MATCH(TEXT(P$8, "####"), df_proj!$E$1:$AD$1,0)),5),MROUND(INDEX(df_proj!$E$2:$AD$1000, MATCH(1, ($B$2 = df_proj!$A$2:$A$1000) * (df_proj!$B$2:$B$1000 = $B13) * (df_proj!$C$2:$C$1000 = $D$2), 0), MATCH(TEXT(P$8, "####"), df_proj!$E$1:$AD$1,0)) * popn_fut!$C85/popn_fut!$E85,5))} -> #N/A | Q13: {=IFERROR(MROUND(INDEX(df_proj!$E$2:$AD$1000, MATCH(1, ($A$2 = df_proj!$A$2:$A$1000) * (df_proj!$B$2:$B$1000 = $B13) * (df_proj!$C$2:$C$1000 = $D$2), 0), MATCH(TEXT(Q$8, "####"), df_proj!$E$1:$AD$1,0)),5),MROUND(INDEX(df_proj!$E$2:$AD$1000, MATCH(1, ($B$2 = df_proj!$A$2:$A$1000) * (df_proj!$B$2:$B$1000 = $B13) * (df_proj!$C$2:$C$1000 = $D$2), 0), MATCH(TEXT(Q$8, "####"), df_proj!$E$1:$AD$1,0)) * popn_fut!$C85/popn_fut!$E85,5))} -> #N/A | R13: {=IFERROR(MROUND(INDEX(df_proj!$E$2:$AD$1000, MATCH(1, ($A$2 = df_proj!$A$2:$A$1000) * (df_proj!$B$2:$B$1000 = $B13) * (df_proj!$C$2:$C$1000 = $D$2), 0), MATCH(TEXT(R$8, "####"), df_proj!$E$1:$AD$1,0)),5),MROUND(INDEX(df_proj!$E$2:$AD$1000, MATCH(1, ($B$2 = df_proj!$A$2:$A$1000) * (df_proj!$B$2:$B$1000 = $B13) * (df_proj!$C$2:$C$1000 = $D$2), 0), MATCH(TEXT(R$8, "####"), df_proj!$E$1:$AD$1,0)) * popn_fut!$C85/popn_fut!$E85,5))} -> #N/A | S13: {=IFERROR(MROUND(INDEX(df_proj!$E$2:$AD$1000, MATCH(1, ($A$2 = df_proj!$A$2:$A$1000) * (df_proj!$B$2:$B$1000 = $B13) * (df_proj!$C$2:$C$1000 = $D$2), 0), MATCH(TEXT(S$8, "####"), df_proj!$E$1:$AD$1,0)),5),MROUND(INDEX(df_proj!$E$2:$AD$1000, MATCH(1, ($B$2 = df_proj!$A$2:$A$1000) * (df_proj!$B$2:$B$1000 = $B13) * (df_proj!$C$2:$C$1000 = $D$2), 0), MATCH(TEXT(S$8, "####"), df_proj!$E$1:$AD$1,0)) * popn_fut!$C85/popn_fut!$E85,5))} -> #N/A | T13: {=IFERROR(MROUND(INDEX(df_proj!$E$2:$AD$1000, MATCH(1, ($A$2 = df_proj!$A$2:$A$1000) * (df_proj!$B$2:$B$1000 = $B13) * (df_proj!$C$2:$C$1000 = $D$2), 0), MATCH(TEXT(T$8, "####"), df_proj!$E$1:$AD$1,0)),5),MROUND(INDEX(df_proj!$E$2:$AD$1000, MATCH(1, ($B$2 = df_proj!$A$2:$A$1000) * (df_proj!$B$2:$B$1000 = $B13) * (df_proj!$C$2:$C$1000 = $D$2), 0), MATCH(TEXT(T$8, "####"), df_proj!$E$1:$AD$1,0)) * popn_fut!$C85/popn_fut!$E85,5))} -> #N/A | ... AL13: {=IFERROR(MROUND(INDEX(df_proj!$E$2:$AD$1000, MATCH(1, ($A$2 = df_proj!$A$2:$A$1000) * (df_proj!$B$2:$B$1000 = $B13) * (df_proj!$C$2:$C$1000 = $D$2), 0), MATCH(TEXT(AL$8, "####"), df_proj!$E$1:$AD$1,0)),5),MROUND(INDEX(df_proj!$E$2:$AD$1000, MATCH(1, ($B$2 = df_proj!$A$2:$A$1000) * (df_proj!$B$2:$B$1000 = $B13) * (df_proj!$C$2:$C$1000 = $D$2), 0), MATCH(TEXT(AL$8, "####"), df_proj!$E$1:$AD$1,0)) * popn_fut!$C85/popn_fut!$E85,5))} -> #N/A | AM13: =AM12+I13 -> #N/A | AP13: =AP12+W13 -> #N/A
A14: 20 | B14: 20 to 24 | D14: #N/A | I14: #N/A | M14: {=IFERROR(MROUND(INDEX(df_proj!$E$2:$AD$1000, MATCH(1, ($A$2 = df_proj!$A$2:$A$1000) * (df_proj!$B$2:$B$1000 = $B14) * (df_proj!$C$2:$C$1000 = $D$2), 0), MATCH(TEXT(M$8, "####"), df_proj!$E$1:$AD$1,0)),5),MROUND(INDEX(df_proj!$E$2:$AD$1000, MATCH(1, ($B$2 = df_proj!$A$2:$A$1000) * (df_proj!$B$2:$B$1000 = $B14) * (df_proj!$C$2:$C$1000 = $D$2), 0), MATCH(TEXT(M$8, "####"), df_proj!$E$1:$AD$1,0)) * popn_fut!$C86/popn_fut!$E86,5))} -> #N/A | N14: {=IFERROR(MROUND(INDEX(df_proj!$E$2:$AD$1000, MATCH(1, ($A$2 = df_proj!$A$2:$A$1000) * (df_proj!$B$2:$B$1000 = $B14) * (df_proj!$C$2:$C$1000 = $D$2), 0), MATCH(TEXT(N$8, "####"), df_proj!$E$1:$AD$1,0)),5),MROUND(INDEX(df_proj!$E$2:$AD$1000, MATCH(1, ($B$2 = df_proj!$A$2:$A$1000) * (df_proj!$B$2:$B$1000 = $B14) * (df_proj!$C$2:$C$1000 = $D$2), 0), MATCH(TEXT(N$8, "####"), df_proj!$E$1:$AD$1,0)) * popn_fut!$C86/popn_fut!$E86,5))} -> #N/A | O14: {=IFERROR(MROUND(INDEX(df_proj!$E$2:$AD$1000, MATCH(1, ($A$2 = df_proj!$A$2:$A$1000) * (df_proj!$B$2:$B$1000 = $B14) * (df_proj!$C$2:$C$1000 = $D$2), 0), MATCH(TEXT(O$8, "####"), df_proj!$E$1:$AD$1,0)),5),MROUND(INDEX(df_proj!$E$2:$AD$1000, MATCH(1, ($B$2 = df_proj!$A$2:$A$1000) * (df_proj!$B$2:$B$1000 = $B14) * (df_proj!$C$2:$C$1000 = $D$2), 0), MATCH(TEXT(O$8, "####"), df_proj!$E$1:$AD$1,0)) * popn_fut!$C86/popn_fut!$E86,5))} -> #N/A | P14: {=IFERROR(MROUND(INDEX(df_proj!$E$2:$AD$1000, MATCH(1, ($A$2 = df_proj!$A$2:$A$1000) * (df_proj!$B$2:$B$1000 = $B14) * (df_proj!$C$2:$C$1000 = $D$2), 0), MATCH(TEXT(P$8, "####"), df_proj!$E$1:$AD$1,0)),5),MROUND(INDEX(df_proj!$E$2:$AD$1000, MATCH(1, ($B$2 = df_proj!$A$2:$A$1000) * (df_proj!$B$2:$B$1000 = $B14) * (df_proj!$C$2:$C$1000 = $D$2), 0), MATCH(TEXT(P$8, "####"), df_proj!$E$1:$AD$1,0)) * popn_fut!$C86/popn_fut!$E86,5))} -> #N/A | Q14: {=IFERROR(MROUND(INDEX(df_proj!$E$2:$AD$1000, MATCH(1, ($A$2 = df_proj!$A$2:$A$1000) * (df_proj!$B$2:$B$1000 = $B14) * (df_proj!$C$2:$C$1000 = $D$2), 0), MATCH(TEXT(Q$8, "####"), df_proj!$E$1:$AD$1,0)),5),MROUND(INDEX(df_proj!$E$2:$AD$1000, MATCH(1, ($B$2 = df_proj!$A$2:$A$1000) * (df_proj!$B$2:$B$1000 = $B14) * (df_proj!$C$2:$C$1000 = $D$2), 0), MATCH(TEXT(Q$8, "####"), df_proj!$E$1:$AD$1,0)) * popn_fut!$C86/popn_fut!$E86,5))} -> #N/A | R14: {=IFERROR(MROUND(INDEX(df_proj!$E$2:$AD$1000, MATCH(1, ($A$2 = df_proj!$A$2:$A$1000) * (df_proj!$B$2:$B$1000 = $B14) * (df_proj!$C$2:$C$1000 = $D$2), 0), MATCH(TEXT(R$8, "####"), df_proj!$E$1:$AD$1,0)),5),MROUND(INDEX(df_proj!$E$2:$AD$1000, MATCH(1, ($B$2 = df_proj!$A$2:$A$1000) * (df_proj!$B$2:$B$1000 = $B14) * (df_proj!$C$2:$C$1000 = $D$2), 0), MATCH(TEXT(R$8, "####"), df_proj!$E$1:$AD$1,0)) * popn_fut!$C86/popn_fut!$E86,5))} -> #N/A | S14: {=IFERROR(MROUND(INDEX(df_proj!$E$2:$AD$1000, MATCH(1, ($A$2 = df_proj!$A$2:$A$1000) * (df_proj!$B$2:$B$1000 = $B14) * (df_proj!$C$2:$C$1000 = $D$2), 0), MATCH(TEXT(S$8, "####"), df_proj!$E$1:$AD$1,0)),5),MROUND(INDEX(df_proj!$E$2:$AD$1000, MATCH(1, ($B$2 = df_proj!$A$2:$A$1000) * (df_proj!$B$2:$B$1000 = $B14) * (df_proj!$C$2:$C$1000 = $D$2), 0), MATCH(TEXT(S$8, "####"), df_proj!$E$1:$AD$1,0)) * popn_fut!$C86/popn_fut!$E86,5))} -> #N/A | T14: {=IFERROR(MROUND(INDEX(df_proj!$E$2:$AD$1000, MATCH(1, ($A$2 = df_proj!$A$2:$A$1000) * (df_proj!$B$2:$B$1000 = $B14) * (df_proj!$C$2:$C$1000 = $D$2), 0), MATCH(TEXT(T$8, "####"), df_proj!$E$1:$AD$1,0)),5),MROUND(INDEX(df_proj!$E$2:$AD$1000, MATCH(1, ($B$2 = df_proj!$A$2:$A$1000) * (df_proj!$B$2:$B$1000 = $B14) * (df_proj!$C$2:$C$1000 = $D$2), 0), MATCH(TEXT(T$8, "####"), df_proj!$E$1:$AD$1,0)) * popn_fut!$C86/popn_fut!$E86,5))} -> #N/A | ... AL14: {=IFERROR(MROUND(INDEX(df_proj!$E$2:$AD$1000, MATCH(1, ($A$2 = df_proj!$A$2:$A$1000) * (df_proj!$B$2:$B$1000 = $B14) * (df_proj!$C$2:$C$1000 = $D$2), 0), MATCH(TEXT(AL$8, "####"), df_proj!$E$1:$AD$1,0)),5),MROUND(INDEX(df_proj!$E$2:$AD$1000, MATCH(1, ($B$2 = df_proj!$A$2:$A$1000) * (df_proj!$B$2:$B$1000 = $B14) * (df_proj!$C$2:$C$1000 = $D$2), 0), MATCH(TEXT(AL$8, "####"), df_proj!$E$1:$AD$1,0)) * popn_fut!$C86/popn_fut!$E86,5))} -> #N/A | AM14: =AM13+I14 -> #N/A | AP14: =AP13+W14 -> #N/A
A15: 25 | B15: 25 to 29 | D15: #N/A | I15: #N/A | M15: {=IFERROR(MROUND(INDEX(df_proj!$E$2:$AD$1000, MATCH(1, ($A$2 = df_proj!$A$2:$A$1000) * (df_proj!$B$2:$B$1000 = $B15) * (df_proj!$C$2:$C$1000 = $D$2), 0), MATCH(TEXT(M$8, "####"), df_proj!$E$1:$AD$1,0)),5),MROUND(INDEX(df_proj!$E$2:$AD$1000, MATCH(1, ($B$2 = df_proj!$A$2:$A$1000) * (df_proj!$B$2:$B$1000 = $B15) * (df_proj!$C$2:$C$1000 = $D$2), 0), MATCH(TEXT(M$8, "####"), df_proj!$E$1:$AD$1,0)) * popn_fut!$C87/popn_fut!$E87,5))} -> #N/A | N15: {=IFERROR(MROUND(INDEX(df_proj!$E$2:$AD$1000, MATCH(1, ($A$2 = df_proj!$A$2:$A$1000) * (df_proj!$B$2:$B$1000 = $B15) * (df_proj!$C$2:$C$1000 = $D$2), 0), MATCH(TEXT(N$8, "####"), df_proj!$E$1:$AD$1,0)),5),MROUND(INDEX(df_proj!$E$2:$AD$1000, MATCH(1, ($B$2 = df_proj!$A$2:$A$1000) * (df_proj!$B$2:$B$1000 = $B15) * (df_proj!$C$2:$C$1000 = $D$2), 0), MATCH(TEXT(N$8, "####"), df_proj!$E$1:$AD$1,0)) * popn_fut!$C87/popn_fut!$E87,5))} -> #N/A | O15: {=IFERROR(MROUND(INDEX(df_proj!$E$2:$AD$1000, MATCH(1, ($A$2 = df_proj!$A$2:$A$1000) * (df_proj!$B$2:$B$1000 = $B15) * (df_proj!$C$2:$C$1000 = $D$2), 0), MATCH(TEXT(O$8, "####"), df_proj!$E$1:$AD$1,0)),5),MROUND(INDEX(df_proj!$E$2:$AD$1000, MATCH(1, ($B$2 = df_proj!$A$2:$A$1000) * (df_proj!$B$2:$B$1000 = $B15) * (df_proj!$C$2:$C$1000 = $D$2), 0), MATCH(TEXT(O$8, "####"), df_proj!$E$1:$AD$1,0)) * popn_fut!$C87/popn_fut!$E87,5))} -> #N/A | P15: {=IFERROR(MROUND(INDEX(df_proj!$E$2:$AD$1000, MATCH(1, ($A$2 = df_proj!$A$2:$A$1000) * (df_proj!$B$2:$B$1000 = $B15) * (df_proj!$C$2:$C$1000 = $D$2), 0), MATCH(TEXT(P$8, "####"), df_proj!$E$1:$AD$1,0)),5),MROUND(INDEX(df_proj!$E$2:$AD$1000, MATCH(1, ($B$2 = df_proj!$A$2:$A$1000) * (df_proj!$B$2:$B$1000 = $B15) * (df_proj!$C$2:$C$1000 = $D$2), 0), MATCH(TEXT(P$8, "####"), df_proj!$E$1:$AD$1,0)) * popn_fut!$C87/popn_fut!$E87,5))} -> #N/A | Q15: {=IFERROR(MROUND(INDEX(df_proj!$E$2:$AD$1000, MATCH(1, ($A$2 = df_proj!$A$2:$A$1000) * (df_proj!$B$2:$B$1000 = $B15) * (df_proj!$C$2:$C$1000 = $D$2), 0), MATCH(TEXT(Q$8, "####"), df_proj!$E$1:$AD$1,0)),5),MROUND(INDEX(df_proj!$E$2:$AD$1000, MATCH(1, ($B$2 = df_proj!$A$2:$A$1000) * (df_proj!$B$2:$B$1000 = $B15) * (df_proj!$C$2:$C$1000 = $D$2), 0), MATCH(TEXT(Q$8, "####"), df_proj!$E$1:$AD$1,0)) * popn_fut!$C87/popn_fut!$E87,5))} -> #N/A | R15: {=IFERROR(MROUND(INDEX(df_proj!$E$2:$AD$1000, MATCH(1, ($A$2 = df_proj!$A$2:$A$1000) * (df_proj!$B$2:$B$1000 = $B15) * (df_proj!$C$2:$C$1000 = $D$2), 0), MATCH(TEXT(R$8, "####"), df_proj!$E$1:$AD$1,0)),5),MROUND(INDEX(df_proj!$E$2:$AD$1000, MATCH(1, ($B$2 = df_proj!$A$2:$A$1000) * (df_proj!$B$2:$B$1000 = $B15) * (df_proj!$C$2:$C$1000 = $D$2), 0), MATCH(TEXT(R$8, "####"), df_proj!$E$1:$AD$1,0)) * popn_fut!$C87/popn_fut!$E87,5))} -> #N/A | S15: {=IFERROR(MROUND(INDEX(df_proj!$E$2:$AD$1000, MATCH(1, ($A$2 = df_proj!$A$2:$A$1000) * (df_proj!$B$2:$B$1000 = $B15) * (df_proj!$C$2:$C$1000 = $D$2), 0), MATCH(TEXT(S$8, "####"), df_proj!$E$1:$AD$1,0)),5),MROUND(INDEX(df_proj!$E$2:$AD$1000, MATCH(1, ($B$2 = df_proj!$A$2:$A$1000) * (df_proj!$B$2:$B$1000 = $B15) * (df_proj!$C$2:$C$1000 = $D$2), 0), MATCH(TEXT(S$8, "####"), df_proj!$E$1:$AD$1,0)) * popn_fut!$C87/popn_fut!$E87,5))} -> #N/A | T15: {=IFERROR(MROUND(INDEX(df_proj!$E$2:$AD$1000, MATCH(1, ($A$2 = df_proj!$A$2:$A$1000) * (df_proj!$B$2:$B$1000 = $B15) * (df_proj!$C$2:$C$1000 = $D$2), 0), MATCH(TEXT(T$8, "####"), df_proj!$E$1:$AD$1,0)),5),MROUND(INDEX(df_proj!$E$2:$AD$1000, MATCH(1, ($B$2 = df_proj!$A$2:$A$1000) * (df_proj!$B$2:$B$1000 = $B15) * (df_proj!$C$2:$C$1000 = $D$2), 0), MATCH(TEXT(T$8, "####"), df_proj!$E$1:$AD$1,0)) * popn_fut!$C87/popn_fut!$E87,5))} -> #N/A | ... AL15: {=IFERROR(MROUND(INDEX(df_proj!$E$2:$AD$1000, MATCH(1, ($A$2 = df_proj!$A$2:$A$1000) * (df_proj!$B$2:$B$1000 = $B15) * (df_proj!$C$2:$C$1000 = $D$2), 0), MATCH(TEXT(AL$8, "####"), df_proj!$E$1:$AD$1,0)),5),MROUND(INDEX(df_proj!$E$2:$AD$1000, MATCH(1, ($B$2 = df_proj!$A$2:$A$1000) * (df_proj!$B$2:$B$1000 = $B15) * (df_proj!$C$2:$C$1000 = $D$2), 0), MATCH(TEXT(AL$8, "####"), df_proj!$E$1:$AD$1,0)) * popn_fut!$C87/popn_fut!$E87,5))} -> #N/A | AM15: =AM14+I15 -> #N/A | AP15: =AP14+W15 -> #N/A
A16: 30 | B16: 30 to 34 | D16: #N/A | I16: #N/A | M16: {=IFERROR(MROUND(INDEX(df_proj!$E$2:$AD$1000, MATCH(1, ($A$2 = df_proj!$A$2:$A$1000) * (df_proj!$B$2:$B$1000 = $B16) * (df_proj!$C$2:$C$1000 = $D$2), 0), MATCH(TEXT(M$8, "####"), df_proj!$E$1:$AD$1,0)),5),MROUND(INDEX(df_proj!$E$2:$AD$1000, MATCH(1, ($B$2 = df_proj!$A$2:$A$1000) * (df_proj!$B$2:$B$1000 = $B16) * (df_proj!$C$2:$C$1000 = $D$2), 0), MATCH(TEXT(M$8, "####"), df_proj!$E$1:$AD$1,0)) * popn_fut!$C88/popn_fut!$E88,5))} -> #N/A | N16: {=IFERROR(MROUND(INDEX(df_proj!$E$2:$AD$1000, MATCH(1, ($A$2 = df_proj!$A$2:$A$1000) * (df_proj!$B$2:$B$1000 = $B16) * (df_proj!$C$2:$C$1000 = $D$2), 0), MATCH(TEXT(N$8, "####"), df_proj!$E$1:$AD$1,0)),5),MROUND(INDEX(df_proj!$E$2:$AD$1000, MATCH(1, ($B$2 = df_proj!$A$2:$A$1000) * (df_proj!$B$2:$B$1000 = $B16) * (df_proj!$C$2:$C$1000 = $D$2), 0), MATCH(TEXT(N$8, "####"), df_proj!$E$1:$AD$1,0)) * popn_fut!$C88/popn_fut!$E88,5))} -> #N/A | O16: {=IFERROR(MROUND(INDEX(df_proj!$E$2:$AD$1000, MATCH(1, ($A$2 = df_proj!$A$2:$A$1000) * (df_proj!$B$2:$B$1000 = $B16) * (df_proj!$C$2:$C$1000 = $D$2), 0), MATCH(TEXT(O$8, "####"), df_proj!$E$1:$AD$1,0)),5),MROUND(INDEX(df_proj!$E$2:$AD$1000, MATCH(1, ($B$2 = df_proj!$A$2:$A$1000) * (df_proj!$B$2:$B$1000 = $B16) * (df_proj!$C$2:$C$1000 = $D$2), 0), MATCH(TEXT(O$8, "####"), df_proj!$E$1:$AD$1,0)) * popn_fut!$C88/popn_fut!$E88,5))} -> #N/A | P16: {=IFERROR(MROUND(INDEX(df_proj!$E$2:$AD$1000, MATCH(1, ($A$2 = df_proj!$A$2:$A$1000) * (df_proj!$B$2:$B$1000 = $B16) * (df_proj!$C$2:$C$1000 = $D$2), 0), MATCH(TEXT(P$8, "####"), df_proj!$E$1:$AD$1,0)),5),MROUND(INDEX(df_proj!$E$2:$AD$1000, MATCH(1, ($B$2 = df_proj!$A$2:$A$1000) * (df_proj!$B$2:$B$1000 = $B16) * (df_proj!$C$2:$C$1000 = $D$2), 0), MATCH(TEXT(P$8, "####"), df_proj!$E$1:$AD$1,0)) * popn_fut!$C88/popn_fut!$E88,5))} -> #N/A | Q16: {=IFERROR(MROUND(INDEX(df_proj!$E$2:$AD$1000, MATCH(1, ($A$2 = df_proj!$A$2:$A$1000) * (df_proj!$B$2:$B$1000 = $B16) * (df_proj!$C$2:$C$1000 = $D$2), 0), MATCH(TEXT(Q$8, "####"), df_proj!$E$1:$AD$1,0)),5),MROUND(INDEX(df_proj!$E$2:$AD$1000, MATCH(1, ($B$2 = df_proj!$A$2:$A$1000) * (df_proj!$B$2:$B$1000 = $B16) * (df_proj!$C$2:$C$1000 = $D$2), 0), MATCH(TEXT(Q$8, "####"), df_proj!$E$1:$AD$1,0)) * popn_fut!$C88/popn_fut!$E88,5))} -> #N/A | R16: {=IFERROR(MROUND(INDEX(df_proj!$E$2:$AD$1000, MATCH(1, ($A$2 = df_proj!$A$2:$A$1000) * (df_proj!$B$2:$B$1000 = $B16) * (df_proj!$C$2:$C$1000 = $D$2), 0), MATCH(TEXT(R$8, "####"), df_proj!$E$1:$AD$1,0)),5),MROUND(INDEX(df_proj!$E$2:$AD$1000, MATCH(1, ($B$2 = df_proj!$A$2:$A$1000) * (df_proj!$B$2:$B$1000 = $B16) * (df_proj!$C$2:$C$1000 = $D$2), 0), MATCH(TEXT(R$8, "####"), df_proj!$E$1:$AD$1,0)) * popn_fut!$C88/popn_fut!$E88,5))} -> #N/A | S16: {=IFERROR(MROUND(INDEX(df_proj!$E$2:$AD$1000, MATCH(1, ($A$2 = df_proj!$A$2:$A$1000) * (df_proj!$B$2:$B$1000 = $B16) * (df_proj!$C$2:$C$1000 = $D$2), 0), MATCH(TEXT(S$8, "####"), df_proj!$E$1:$AD$1,0)),5),MROUND(INDEX(df_proj!$E$2:$AD$1000, MATCH(1, ($B$2 = df_proj!$A$2:$A$1000) * (df_proj!$B$2:$B$1000 = $B16) * (df_proj!$C$2:$C$1000 = $D$2), 0), MATCH(TEXT(S$8, "####"), df_proj!$E$1:$AD$1,0)) * popn_fut!$C88/popn_fut!$E88,5))} -> #N/A | T16: {=IFERROR(MROUND(INDEX(df_proj!$E$2:$AD$1000, MATCH(1, ($A$2 = df_proj!$A$2:$A$1000) * (df_proj!$B$2:$B$1000 = $B16) * (df_proj!$C$2:$C$1000 = $D$2), 0), MATCH(TEXT(T$8, "####"), df_proj!$E$1:$AD$1,0)),5),MROUND(INDEX(df_proj!$E$2:$AD$1000, MATCH(1, ($B$2 = df_proj!$A$2:$A$1000) * (df_proj!$B$2:$B$1000 = $B16) * (df_proj!$C$2:$C$1000 = $D$2), 0), MATCH(TEXT(T$8, "####"), df_proj!$E$1:$AD$1,0)) * popn_fut!$C88/popn_fut!$E88,5))} -> #N/A | ... AL16: {=IFERROR(MROUND(INDEX(df_proj!$E$2:$AD$1000, MATCH(1, ($A$2 = df_proj!$A$2:$A$1000) * (df_proj!$B$2:$B$1000 = $B16) * (df_proj!$C$2:$C$1000 = $D$2), 0), MATCH(TEXT(AL$8, "####"), df_proj!$E$1:$AD$1,0)),5),MROUND(INDEX(df_proj!$E$2:$AD$1000, MATCH(1, ($B$2 = df_proj!$A$2:$A$1000) * (df_proj!$B$2:$B$1000 = $B16) * (df_proj!$C$2:$C$1000 = $D$2), 0), MATCH(TEXT(AL$8, "####"), df_proj!$E$1:$AD$1,0)) * popn_fut!$C88/popn_fut!$E88,5))} -> #N/A | AM16: =AM15+I16 -> #N/A | AP16: =AP15+W16 -> #N/A
A17: 35 | B17: 35 to 39 | D17: #N/A | I17: #N/A | M17: {=IFERROR(MROUND(INDEX(df_proj!$E$2:$AD$1000, MATCH(1, ($A$2 = df_proj!$A$2:$A$1000) * (df_proj!$B$2:$B$1000 = $B17) * (df_proj!$C$2:$C$1000 = $D$2), 0), MATCH(TEXT(M$8, "####"), df_proj!$E$1:$AD$1,0)),5),MROUND(INDEX(df_proj!$E$2:$AD$1000, MATCH(1, ($B$2 = df_proj!$A$2:$A$1000) * (df_proj!$B$2:$B$1000 = $B17) * (df_proj!$C$2:$C$1000 = $D$2), 0), MATCH(TEXT(M$8, "####"), df_proj!$E$1:$AD$1,0)) * popn_fut!$C89/popn_fut!$E89,5))} -> #N/A | N17: {=IFERROR(MROUND(INDEX(df_proj!$E$2:$AD$1000, MATCH(1, ($A$2 = df_proj!$A$2:$A$1000) * (df_proj!$B$2:$B$1000 = $B17) * (df_proj!$C$2:$C$1000 = $D$2), 0), MATCH(TEXT(N$8, "####"), df_proj!$E$1:$AD$1,0)),5),MROUND(INDEX(df_proj!$E$2:$AD$1000, MATCH(1, ($B$2 = df_proj!$A$2:$A$1000) * (df_proj!$B$2:$B$1000 = $B17) * (df_proj!$C$2:$C$1000 = $D$2), 0), MATCH(TEXT(N$8, "####"), df_proj!$E$1:$AD$1,0)) * popn_fut!$C89/popn_fut!$E89,5))} -> #N/A | O17: {=IFERROR(MROUND(INDEX(df_proj!$E$2:$AD$1000, MATCH(1, ($A$2 = df_proj!$A$2:$A$1000) * (df_proj!$B$2:$B$1000 = $B17) * (df_proj!$C$2:$C$1000 = $D$2), 0), MATCH(TEXT(O$8, "####"), df_proj!$E$1:$AD$1,0)),5),MROUND(INDEX(df_proj!$E$2:$AD$1000, MATCH(1, ($B$2 = df_proj!$A$2:$A$1000) * (df_proj!$B$2:$B$1000 = $B17) * (df_proj!$C$2:$C$1000 = $D$2), 0), MATCH(TEXT(O$8, "####"), df_proj!$E$1:$AD$1,0)) * popn_fut!$C89/popn_fut!$E89,5))} -> #N/A | P17: {=IFERROR(MROUND(INDEX(df_proj!$E$2:$AD$1000, MATCH(1, ($A$2 = df_proj!$A$2:$A$1000) * (df_proj!$B$2:$B$1000 = $B17) * (df_proj!$C$2:$C$1000 = $D$2), 0), MATCH(TEXT(P$8, "####"), df_proj!$E$1:$AD$1,0)),5),MROUND(INDEX(df_proj!$E$2:$AD$1000, MATCH(1, ($B$2 = df_proj!$A$2:$A$1000) * (df_proj!$B$2:$B$1000 = $B17) * (df_proj!$C$2:$C$1000 = $D$2), 0), MATCH(TEXT(P$8, "####"), df_proj!$E$1:$AD$1,0)) * popn_fut!$C89/popn_fut!$E89,5))} -> #N/A | Q17: {=IFERROR(MROUND(INDEX(df_proj!$E$2:$AD$1000, MATCH(1, ($A$2 = df_proj!$A$2:$A$1000) * (df_proj!$B$2:$B$1000 = $B17) * (df_proj!$C$2:$C$1000 = $D$2), 0), MATCH(TEXT(Q$8, "####"), df_proj!$E$1:$AD$1,0)),5),MROUND(INDEX(df_proj!$E$2:$AD$1000, MATCH(1, ($B$2 = df_proj!$A$2:$A$1000) * (df_proj!$B$2:$B$1000 = $B17) * (df_proj!$C$2:$C$1000 = $D$2), 0), MATCH(TEXT(Q$8, "####"), df_proj!$E$1:$AD$1,0)) * popn_fut!$C89/popn_fut!$E89,5))} -> #N/A | R17: {=IFERROR(MROUND(INDEX(df_proj!$E$2:$AD$1000, MATCH(1, ($A$2 = df_proj!$A$2:$A$1000) * (df_proj!$B$2:$B$1000 = $B17) * (df_proj!$C$2:$C$1000 = $D$2), 0), MATCH(TEXT(R$8, "####"), df_proj!$E$1:$AD$1,0)),5),MROUND(INDEX(df_proj!$E$2:$AD$1000, MATCH(1, ($B$2 = df_proj!$A$2:$A$1000) * (df_proj!$B$2:$B$1000 = $B17) * (df_proj!$C$2:$C$1000 = $D$2), 0), MATCH(TEXT(R$8, "####"), df_proj!$E$1:$AD$1,0)) * popn_fut!$C89/popn_fut!$E89,5))} -> #N/A | S17: {=IFERROR(MROUND(INDEX(df_proj!$E$2:$AD$1000, MATCH(1, ($A$2 = df_proj!$A$2:$A$1000) * (df_proj!$B$2:$B$1000 = $B17) * (df_proj!$C$2:$C$1000 = $D$2), 0), MATCH(TEXT(S$8, "####"), df_proj!$E$1:$AD$1,0)),5),MROUND(INDEX(df_proj!$E$2:$AD$1000, MATCH(1, ($B$2 = df_proj!$A$2:$A$1000) * (df_proj!$B$2:$B$1000 = $B17) * (df_proj!$C$2:$C$1000 = $D$2), 0), MATCH(TEXT(S$8, "####"), df_proj!$E$1:$AD$1,0)) * popn_fut!$C89/popn_fut!$E89,5))} -> #N/A | T17: {=IFERROR(MROUND(INDEX(df_proj!$E$2:$AD$1000, MATCH(1, ($A$2 = df_proj!$A$2:$A$1000) * (df_proj!$B$2:$B$1000 = $B17) * (df_proj!$C$2:$C$1000 = $D$2), 0), MATCH(TEXT(T$8, "####"), df_proj!$E$1:$AD$1,0)),5),MROUND(INDEX(df_proj!$E$2:$AD$1000, MATCH(1, ($B$2 = df_proj!$A$2:$A$1000) * (df_proj!$B$2:$B$1000 = $B17) * (df_proj!$C$2:$C$1000 = $D$2), 0), MATCH(TEXT(T$8, "####"), df_proj!$E$1:$AD$1,0)) * popn_fut!$C89/popn_fut!$E89,5))} -> #N/A | ... AL17: {=IFERROR(MROUND(INDEX(df_proj!$E$2:$AD$1000, MATCH(1, ($A$2 = df_proj!$A$2:$A$1000) * (df_proj!$B$2:$B$1000 = $B17) * (df_proj!$C$2:$C$1000 = $D$2), 0), MATCH(TEXT(AL$8, "####"), df_proj!$E$1:$AD$1,0)),5),MROUND(INDEX(df_proj!$E$2:$AD$1000, MATCH(1, ($B$2 = df_proj!$A$2:$A$1000) * (df_proj!$B$2:$B$1000 = $B17) * (df_proj!$C$2:$C$1000 = $D$2), 0), MATCH(TEXT(AL$8, "####"), df_proj!$E$1:$AD$1,0)) * popn_fut!$C89/popn_fut!$E89,5))} -> #N/A | AM17: =AM16+I17 -> #N/A | AP17: =AP16+W17 -> #N/A
A18: 40 | B18: 40 to 44 | D18: #N/A | I18: #N/A | M18: {=IFERROR(MROUND(INDEX(df_proj!$E$2:$AD$1000, MATCH(1, ($A$2 = df_proj!$A$2:$A$1000) * (df_proj!$B$2:$B$1000 = $B18) * (df_proj!$C$2:$C$1000 = $D$2), 0), MATCH(TEXT(M$8, "####"), df_proj!$E$1:$AD$1,0)),5),MROUND(INDEX(df_proj!$E$2:$AD$1000, MATCH(1, ($B$2 = df_proj!$A$2:$A$1000) * (df_proj!$B$2:$B$1000 = $B18) * (df_proj!$C$2:$C$1000 = $D$2), 0), MATCH(TEXT(M$8, "####"), df_proj!$E$1:$AD$1,0)) * popn_fut!$C90/popn_fut!$E90,5))} -> #N/A | N18: {=IFERROR(MROUND(INDEX(df_proj!$E$2:$AD$1000, MATCH(1, ($A$2 = df_proj!$A$2:$A$1000) * (df_proj!$B$2:$B$1000 = $B18) * (df_proj!$C$2:$C$1000 = $D$2), 0), MATCH(TEXT(N$8, "####"), df_proj!$E$1:$AD$1,0)),5),MROUND(INDEX(df_proj!$E$2:$AD$1000, MATCH(1, ($B$2 = df_proj!$A$2:$A$1000) * (df_proj!$B$2:$B$1000 = $B18) * (df_proj!$C$2:$C$1000 = $D$2), 0), MATCH(TEXT(N$8, "####"), df_proj!$E$1:$AD$1,0)) * popn_fut!$C90/popn_fut!$E90,5))} -> #N/A | O18: {=IFERROR(MROUND(INDEX(df_proj!$E$2:$AD$1000, MATCH(1, ($A$2 = df_proj!$A$2:$A$1000) * (df_proj!$B$2:$B$1000 = $B18) * (df_proj!$C$2:$C$1000 = $D$2), 0), MATCH(TEXT(O$8, "####"), df_proj!$E$1:$AD$1,0)),5),MROUND(INDEX(df_proj!$E$2:$AD$1000, MATCH(1, ($B$2 = df_proj!$A$2:$A$1000) * (df_proj!$B$2:$B$1000 = $B18) * (df_proj!$C$2:$C$1000 = $D$2), 0), MATCH(TEXT(O$8, "####"), df_proj!$E$1:$AD$1,0)) * popn_fut!$C90/popn_fut!$E90,5))} -> #N/A | P18: {=IFERROR(MROUND(INDEX(df_proj!$E$2:$AD$1000, MATCH(1, ($A$2 = df_proj!$A$2:$A$1000) * (df_proj!$B$2:$B$1000 = $B18) * (df_proj!$C$2:$C$1000 = $D$2), 0), MATCH(TEXT(P$8, "####"), df_proj!$E$1:$AD$1,0)),5),MROUND(INDEX(df_proj!$E$2:$AD$1000, MATCH(1, ($B$2 = df_proj!$A$2:$A$1000) * (df_proj!$B$2:$B$1000 = $B18) * (df_proj!$C$2:$C$1000 = $D$2), 0), MATCH(TEXT(P$8, "####"), df_proj!$E$1:$AD$1,0)) * popn_fut!$C90/popn_fut!$E90,5))} -> #N/A | Q18: {=IFERROR(MROUND(INDEX(df_proj!$E$2:$AD$1000, MATCH(1, ($A$2 = df_proj!$A$2:$A$1000) * (df_proj!$B$2:$B$1000 = $B18) * (df_proj!$C$2:$C$1000 = $D$2), 0), MATCH(TEXT(Q$8, "####"), df_proj!$E$1:$AD$1,0)),5),MROUND(INDEX(df_proj!$E$2:$AD$1000, MATCH(1, ($B$2 = df_proj!$A$2:$A$1000) * (df_proj!$B$2:$B$1000 = $B18) * (df_proj!$C$2:$C$1000 = $D$2), 0), MATCH(TEXT(Q$8, "####"), df_proj!$E$1:$AD$1,0)) * popn_fut!$C90/popn_fut!$E90,5))} -> #N/A | R18: {=IFERROR(MROUND(INDEX(df_proj!$E$2:$AD$1000, MATCH(1, ($A$2 = df_proj!$A$2:$A$1000) * (df_proj!$B$2:$B$1000 = $B18) * (df_proj!$C$2:$C$1000 = $D$2), 0), MATCH(TEXT(R$8, "####"), df_proj!$E$1:$AD$1,0)),5),MROUND(INDEX(df_proj!$E$2:$AD$1000, MATCH(1, ($B$2 = df_proj!$A$2:$A$1000) * (df_proj!$B$2:$B$1000 = $B18) * (df_proj!$C$2:$C$1000 = $D$2), 0), MATCH(TEXT(R$8, "####"), df_proj!$E$1:$AD$1,0)) * popn_fut!$C90/popn_fut!$E90,5))} -> #N/A | S18: {=IFERROR(MROUND(INDEX(df_proj!$E$2:$AD$1000, MATCH(1, ($A$2 = df_proj!$A$2:$A$1000) * (df_proj!$B$2:$B$1000 = $B18) * (df_proj!$C$2:$C$1000 = $D$2), 0), MATCH(TEXT(S$8, "####"), df_proj!$E$1:$AD$1,0)),5),MROUND(INDEX(df_proj!$E$2:$AD$1000, MATCH(1, ($B$2 = df_proj!$A$2:$A$1000) * (df_proj!$B$2:$B$1000 = $B18) * (df_proj!$C$2:$C$1000 = $D$2), 0), MATCH(TEXT(S$8, "####"), df_proj!$E$1:$AD$1,0)) * popn_fut!$C90/popn_fut!$E90,5))} -> #N/A | T18: {=IFERROR(MROUND(INDEX(df_proj!$E$2:$AD$1000, MATCH(1, ($A$2 = df_proj!$A$2:$A$1000) * (df_proj!$B$2:$B$1000 = $B18) * (df_proj!$C$2:$C$1000 = $D$2), 0), MATCH(TEXT(T$8, "####"), df_proj!$E$1:$AD$1,0)),5),MROUND(INDEX(df_proj!$E$2:$AD$1000, MATCH(1, ($B$2 = df_proj!$A$2:$A$1000) * (df_proj!$B$2:$B$1000 = $B18) * (df_proj!$C$2:$C$1000 = $D$2), 0), MATCH(TEXT(T$8, "####"), df_proj!$E$1:$AD$1,0)) * popn_fut!$C90/popn_fut!$E90,5))} -> #N/A | ... AL18: {=IFERROR(MROUND(INDEX(df_proj!$E$2:$AD$1000, MATCH(1, ($A$2 = df_proj!$A$2:$A$1000) * (df_proj!$B$2:$B$1000 = $B18) * (df_proj!$C$2:$C$1000 = $D$2), 0), MATCH(TEXT(AL$8, "####"), df_proj!$E$1:$AD$1,0)),5),MROUND(INDEX(df_proj!$E$2:$AD$1000, MATCH(1, ($B$2 = df_proj!$A$2:$A$1000) * (df_proj!$B$2:$B$1000 = $B18) * (df_proj!$C$2:$C$1000 = $D$2), 0), MATCH(TEXT(AL$8, "####"), df_proj!$E$1:$AD$1,0)) * popn_fut!$C90/popn_fut!$E90,5))} -> #N/A | AM18: =AM17+I18 -> #N/A | AP18: =AP17+W18 -> #N/A
A19: 45 | B19: 45 to 49 | D19: #N/A | I19: #N/A | M19: {=IFERROR(MROUND(INDEX(df_proj!$E$2:$AD$1000, MATCH(1, ($A$2 = df_proj!$A$2:$A$1000) * (df_proj!$B$2:$B$1000 = $B19) * (df_proj!$C$2:$C$1000 = $D$2), 0), MATCH(TEXT(M$8, "####"), df_proj!$E$1:$AD$1,0)),5),MROUND(INDEX(df_proj!$E$2:$AD$1000, MATCH(1, ($B$2 = df_proj!$A$2:$A$1000) * (df_proj!$B$2:$B$1000 = $B19) * (df_proj!$C$2:$C$1000 = $D$2), 0), MATCH(TEXT(M$8, "####"), df_proj!$E$1:$AD$1,0)) * popn_fut!$C91/popn_fut!$E91,5))} -> #N/A | N19: {=IFERROR(MROUND(INDEX(df_proj!$E$2:$AD$1000, MATCH(1, ($A$2 = df_proj!$A$2:$A$1000) * (df_proj!$B$2:$B$1000 = $B19) * (df_proj!$C$2:$C$1000 = $D$2), 0), MATCH(TEXT(N$8, "####"), df_proj!$E$1:$AD$1,0)),5),MROUND(INDEX(df_proj!$E$2:$AD$1000, MATCH(1, ($B$2 = df_proj!$A$2:$A$1000) * (df_proj!$B$2:$B$1000 = $B19) * (df_proj!$C$2:$C$1000 = $D$2), 0), MATCH(TEXT(N$8, "####"), df_proj!$E$1:$AD$1,0)) * popn_fut!$C91/popn_fut!$E91,5))} -> #N/A | O19: {=IFERROR(MROUND(INDEX(df_proj!$E$2:$AD$1000, MATCH(1, ($A$2 = df_proj!$A$2:$A$1000) * (df_proj!$B$2:$B$1000 = $B19) * (df_proj!$C$2:$C$1000 = $D$2), 0), MATCH(TEXT(O$8, "####"), df_proj!$E$1:$AD$1,0)),5),MROUND(INDEX(df_proj!$E$2:$AD$1000, MATCH(1, ($B$2 = df_proj!$A$2:$A$1000) * (df_proj!$B$2:$B$1000 = $B19) * (df_proj!$C$2:$C$1000 = $D$2), 0), MATCH(TEXT(O$8, "####"), df_proj!$E$1:$AD$1,0)) * popn_fut!$C91/popn_fut!$E91,5))} -> #N/A | P19: {=IFERROR(MROUND(INDEX(df_proj!$E$2:$AD$1000, MATCH(1, ($A$2 = df_proj!$A$2:$A$1000) * (df_proj!$B$2:$B$1000 = $B19) * (df_proj!$C$2:$C$1000 = $D$2), 0), MATCH(TEXT(P$8, "####"), df_proj!$E$1:$AD$1,0)),5),MROUND(INDEX(df_proj!$E$2:$AD$1000, MATCH(1, ($B$2 = df_proj!$A$2:$A$1000) * (df_proj!$B$2:$B$1000 = $B19) * (df_proj!$C$2:$C$1000 = $D$2), 0), MATCH(TEXT(P$8, "####"), df_proj!$E$1:$AD$1,0)) * popn_fut!$C91/popn_fut!$E91,5))} -> #N/A | Q19: {=IFERROR(MROUND(INDEX(df_proj!$E$2:$AD$1000, MATCH(1, ($A$2 = df_proj!$A$2:$A$1000) * (df_proj!$B$2:$B$1000 = $B19) * (df_proj!$C$2:$C$1000 = $D$2), 0), MATCH(TEXT(Q$8, "####"), df_proj!$E$1:$AD$1,0)),5),MROUND(INDEX(df_proj!$E$2:$AD$1000, MATCH(1, ($B$2 = df_proj!$A$2:$A$1000) * (df_proj!$B$2:$B$1000 = $B19) * (df_proj!$C$2:$C$1000 = $D$2), 0), MATCH(TEXT(Q$8, "####"), df_proj!$E$1:$AD$1,0)) * popn_fut!$C91/popn_fut!$E91,5))} -> #N/A | R19: {=IFERROR(MROUND(INDEX(df_proj!$E$2:$AD$1000, MATCH(1, ($A$2 = df_proj!$A$2:$A$1000) * (df_proj!$B$2:$B$1000 = $B19) * (df_proj!$C$2:$C$1000 = $D$2), 0), MATCH(TEXT(R$8, "####"), df_proj!$E$1:$AD$1,0)),5),MROUND(INDEX(df_proj!$E$2:$AD$1000, MATCH(1, ($B$2 = df_proj!$A$2:$A$1000) * (df_proj!$B$2:$B$1000 = $B19) * (df_proj!$C$2:$C$1000 = $D$2), 0), MATCH(TEXT(R$8, "####"), df_proj!$E$1:$AD$1,0)) * popn_fut!$C91/popn_fut!$E91,5))} -> #N/A | S19: {=IFERROR(MROUND(INDEX(df_proj!$E$2:$AD$1000, MATCH(1, ($A$2 = df_proj!$A$2:$A$1000) * (df_proj!$B$2:$B$1000 = $B19) * (df_proj!$C$2:$C$1000 = $D$2), 0), MATCH(TEXT(S$8, "####"), df_proj!$E$1:$AD$1,0)),5),MROUND(INDEX(df_proj!$E$2:$AD$1000, MATCH(1, ($B$2 = df_proj!$A$2:$A$1000) * (df_proj!$B$2:$B$1000 = $B19) * (df_proj!$C$2:$C$1000 = $D$2), 0), MATCH(TEXT(S$8, "####"), df_proj!$E$1:$AD$1,0)) * popn_fut!$C91/popn_fut!$E91,5))} -> #N/A | T19: {=IFERROR(MROUND(INDEX(df_proj!$E$2:$AD$1000, MATCH(1, ($A$2 = df_proj!$A$2:$A$1000) * (df_proj!$B$2:$B$1000 = $B19) * (df_proj!$C$2:$C$1000 = $D$2), 0), MATCH(TEXT(T$8, "####"), df_proj!$E$1:$AD$1,0)),5),MROUND(INDEX(df_proj!$E$2:$AD$1000, MATCH(1, ($B$2 = df_proj!$A$2:$A$1000) * (df_proj!$B$2:$B$1000 = $B19) * (df_proj!$C$2:$C$1000 = $D$2), 0), MATCH(TEXT(T$8, "####"), df_proj!$E$1:$AD$1,0)) * popn_fut!$C91/popn_fut!$E91,5))} -> #N/A | ... AL19: {=IFERROR(MROUND(INDEX(df_proj!$E$2:$AD$1000, MATCH(1, ($A$2 = df_proj!$A$2:$A$1000) * (df_proj!$B$2:$B$1000 = $B19) * (df_proj!$C$2:$C$1000 = $D$2), 0), MATCH(TEXT(AL$8, "####"), df_proj!$E$1:$AD$1,0)),5),MROUND(INDEX(df_proj!$E$2:$AD$1000, MATCH(1, ($B$2 = df_proj!$A$2:$A$1000) * (df_proj!$B$2:$B$1000 = $B19) * (df_proj!$C$2:$C$1000 = $D$2), 0), MATCH(TEXT(AL$8, "####"), df_proj!$E$1:$AD$1,0)) * popn_fut!$C91/popn_fut!$E91,5))} -> #N/A | AM19: =AM18+I19 -> #N/A | AP19: =AP18+W19 -> #N/A
A20: 50 | B20: 50 to 54 | D20: #N/A | I20: #N/A | M20: {=IFERROR(MROUND(INDEX(df_proj!$E$2:$AD$1000, MATCH(1, ($A$2 = df_proj!$A$2:$A$1000) * (df_proj!$B$2:$B$1000 = $B20) * (df_proj!$C$2:$C$1000 = $D$2), 0), MATCH(TEXT(M$8, "####"), df_proj!$E$1:$AD$1,0)),5),MROUND(INDEX(df_proj!$E$2:$AD$1000, MATCH(1, ($B$2 = df_proj!$A$2:$A$1000) * (df_proj!$B$2:$B$1000 = $B20) * (df_proj!$C$2:$C$1000 = $D$2), 0), MATCH(TEXT(M$8, "####"), df_proj!$E$1:$AD$1,0)) * popn_fut!$C92/popn_fut!$E92,5))} -> #N/A | N20: {=IFERROR(MROUND(INDEX(df_proj!$E$2:$AD$1000, MATCH(1, ($A$2 = df_proj!$A$2:$A$1000) * (df_proj!$B$2:$B$1000 = $B20) * (df_proj!$C$2:$C$1000 = $D$2), 0), MATCH(TEXT(N$8, "####"), df_proj!$E$1:$AD$1,0)),5),MROUND(INDEX(df_proj!$E$2:$AD$1000, MATCH(1, ($B$2 = df_proj!$A$2:$A$1000) * (df_proj!$B$2:$B$1000 = $B20) * (df_proj!$C$2:$C$1000 = $D$2), 0), MATCH(TEXT(N$8, "####"), df_proj!$E$1:$AD$1,0)) * popn_fut!$C92/popn_fut!$E92,5))} -> #N/A | O20: {=IFERROR(MROUND(INDEX(df_proj!$E$2:$AD$1000, MATCH(1, ($A$2 = df_proj!$A$2:$A$1000) * (df_proj!$B$2:$B$1000 = $B20) * (df_proj!$C$2:$C$1000 = $D$2), 0), MATCH(TEXT(O$8, "####"), df_proj!$E$1:$AD$1,0)),5),MROUND(INDEX(df_proj!$E$2:$AD$1000, MATCH(1, ($B$2 = df_proj!$A$2:$A$1000) * (df_proj!$B$2:$B$1000 = $B20) * (df_proj!$C$2:$C$1000 = $D$2), 0), MATCH(TEXT(O$8, "####"), df_proj!$E$1:$AD$1,0)) * popn_fut!$C92/popn_fut!$E92,5))} -> #N/A | P20: {=IFERROR(MROUND(INDEX(df_proj!$E$2:$AD$1000, MATCH(1, ($A$2 = df_proj!$A$2:$A$1000) * (df_proj!$B$2:$B$1000 = $B20) * (df_proj!$C$2:$C$1000 = $D$2), 0), MATCH(TEXT(P$8, "####"), df_proj!$E$1:$AD$1,0)),5),MROUND(INDEX(df_proj!$E$2:$AD$1000, MATCH(1, ($B$2 = df_proj!$A$2:$A$1000) * (df_proj!$B$2:$B$1000 = $B20) * (df_proj!$C$2:$C$1000 = $D$2), 0), MATCH(TEXT(P$8, "####"), df_proj!$E$1:$AD$1,0)) * popn_fut!$C92/popn_fut!$E92,5))} -> #N/A | Q20: {=IFERROR(MROUND(INDEX(df_proj!$E$2:$AD$1000, MATCH(1, ($A$2 = df_proj!$A$2:$A$1000) * (df_proj!$B$2:$B$1000 = $B20) * (df_proj!$C$2:$C$1000 = $D$2), 0), MATCH(TEXT(Q$8, "####"), df_proj!$E$1:$AD$1,0)),5),MROUND(INDEX(df_proj!$E$2:$AD$1000, MATCH(1, ($B$2 = df_proj!$A$2:$A$1000) * (df_proj!$B$2:$B$1000 = $B20) * (df_proj!$C$2:$C$1000 = $D$2), 0), MATCH(TEXT(Q$8, "####"), df_proj!$E$1:$AD$1,0)) * popn_fut!$C92/popn_fut!$E92,5))} -> #N/A | R20: {=IFERROR(MROUND(INDEX(df_proj!$E$2:$AD$1000, MATCH(1, ($A$2 = df_proj!$A$2:$A$1000) * (df_proj!$B$2:$B$1000 = $B20) * (df_proj!$C$2:$C$1000 = $D$2), 0), MATCH(TEXT(R$8, "####"), df_proj!$E$1:$AD$1,0)),5),MROUND(INDEX(df_proj!$E$2:$AD$1000, MATCH(1, ($B$2 = df_proj!$A$2:$A$1000) * (df_proj!$B$2:$B$1000 = $B20) * (df_proj!$C$2:$C$1000 = $D$2), 0), MATCH(TEXT(R$8, "####"), df_proj!$E$1:$AD$1,0)) * popn_fut!$C92/popn_fut!$E92,5))} -> #N/A | S20: {=IFERROR(MROUND(INDEX(df_proj!$E$2:$AD$1000, MATCH(1, ($A$2 = df_proj!$A$2:$A$1000) * (df_proj!$B$2:$B$1000 = $B20) * (df_proj!$C$2:$C$1000 = $D$2), 0), MATCH(TEXT(S$8, "####"), df_proj!$E$1:$AD$1,0)),5),MROUND(INDEX(df_proj!$E$2:$AD$1000, MATCH(1, ($B$2 = df_proj!$A$2:$A$1000) * (df_proj!$B$2:$B$1000 = $B20) * (df_proj!$C$2:$C$1000 = $D$2), 0), MATCH(TEXT(S$8, "####"), df_proj!$E$1:$AD$1,0)) * popn_fut!$C92/popn_fut!$E92,5))} -> #N/A | T20: {=IFERROR(MROUND(INDEX(df_proj!$E$2:$AD$1000, MATCH(1, ($A$2 = df_proj!$A$2:$A$1000) * (df_proj!$B$2:$B$1000 = $B20) * (df_proj!$C$2:$C$1000 = $D$2), 0), MATCH(TEXT(T$8, "####"), df_proj!$E$1:$AD$1,0)),5),MROUND(INDEX(df_proj!$E$2:$AD$1000, MATCH(1, ($B$2 = df_proj!$A$2:$A$1000) * (df_proj!$B$2:$B$1000 = $B20) * (df_proj!$C$2:$C$1000 = $D$2), 0), MATCH(TEXT(T$8, "####"), df_proj!$E$1:$AD$1,0)) * popn_fut!$C92/popn_fut!$E92,5))} -> #N/A | ... AL20: {=IFERROR(MROUND(INDEX(df_proj!$E$2:$AD$1000, MATCH(1, ($A$2 = df_proj!$A$2:$A$1000) * (df_proj!$B$2:$B$1000 = $B20) * (df_proj!$C$2:$C$1000 = $D$2), 0), MATCH(TEXT(AL$8, "####"), df_proj!$E$1:$AD$1,0)),5),MROUND(INDEX(df_proj!$E$2:$AD$1000, MATCH(1, ($B$2 = df_proj!$A$2:$A$1000) * (df_proj!$B$2:$B$1000 = $B20) * (df_proj!$C$2:$C$1000 = $D$2), 0), MATCH(TEXT(AL$8, "####"), df_proj!$E$1:$AD$1,0)) * popn_fut!$C92/popn_fut!$E92,5))} -> #N/A | AM20: =AM19+I20 -> #N/A | AP20: =AP19+W20 -> #N/A
A21: 55 | B21: 55 to 59 | D21: #N/A | I21: #N/A | M21: {=IFERROR(MROUND(INDEX(df_proj!$E$2:$AD$1000, MATCH(1, ($A$2 = df_proj!$A$2:$A$1000) * (df_proj!$B$2:$B$1000 = $B21) * (df_proj!$C$2:$C$1000 = $D$2), 0), MATCH(TEXT(M$8, "####"), df_proj!$E$1:$AD$1,0)),5),MROUND(INDEX(df_proj!$E$2:$AD$1000, MATCH(1, ($B$2 = df_proj!$A$2:$A$1000) * (df_proj!$B$2:$B$1000 = $B21) * (df_proj!$C$2:$C$1000 = $D$2), 0), MATCH(TEXT(M$8, "####"), df_proj!$E$1:$AD$1,0)) * popn_fut!$C93/popn_fut!$E93,5))} -> #N/A | N21: {=IFERROR(MROUND(INDEX(df_proj!$E$2:$AD$1000, MATCH(1, ($A$2 = df_proj!$A$2:$A$1000) * (df_proj!$B$2:$B$1000 = $B21) * (df_proj!$C$2:$C$1000 = $D$2), 0), MATCH(TEXT(N$8, "####"), df_proj!$E$1:$AD$1,0)),5),MROUND(INDEX(df_proj!$E$2:$AD$1000, MATCH(1, ($B$2 = df_proj!$A$2:$A$1000) * (df_proj!$B$2:$B$1000 = $B21) * (df_proj!$C$2:$C$1000 = $D$2), 0), MATCH(TEXT(N$8, "####"), df_proj!$E$1:$AD$1,0)) * popn_fut!$C93/popn_fut!$E93,5))} -> #N/A | O21: {=IFERROR(MROUND(INDEX(df_proj!$E$2:$AD$1000, MATCH(1, ($A$2 = df_proj!$A$2:$A$1000) * (df_proj!$B$2:$B$1000 = $B21) * (df_proj!$C$2:$C$1000 = $D$2), 0), MATCH(TEXT(O$8, "####"), df_proj!$E$1:$AD$1,0)),5),MROUND(INDEX(df_proj!$E$2:$AD$1000, MATCH(1, ($B$2 = df_proj!$A$2:$A$1000) * (df_proj!$B$2:$B$1000 = $B21) * (df_proj!$C$2:$C$1000 = $D$2), 0), MATCH(TEXT(O$8, "####"), df_proj!$E$1:$AD$1,0)) * popn_fut!$C93/popn_fut!$E93,5))} -> #N/A | P21: {=IFERROR(MROUND(INDEX(df_proj!$E$2:$AD$1000, MATCH(1, ($A$2 = df_proj!$A$2:$A$1000) * (df_proj!$B$2:$B$1000 = $B21) * (df_proj!$C$2:$C$1000 = $D$2), 0), MATCH(TEXT(P$8, "####"), df_proj!$E$1:$AD$1,0)),5),MROUND(INDEX(df_proj!$E$2:$AD$1000, MATCH(1, ($B$2 = df_proj!$A$2:$A$1000) * (df_proj!$B$2:$B$1000 = $B21) * (df_proj!$C$2:$C$1000 = $D$2), 0), MATCH(TEXT(P$8, "####"), df_proj!$E$1:$AD$1,0)) * popn_fut!$C93/popn_fut!$E93,5))} -> #N/A | Q21: {=IFERROR(MROUND(INDEX(df_proj!$E$2:$AD$1000, MATCH(1, ($A$2 = df_proj!$A$2:$A$1000) * (df_proj!$B$2:$B$1000 = $B21) * (df_proj!$C$2:$C$1000 = $D$2), 0), MATCH(TEXT(Q$8, "####"), df_proj!$E$1:$AD$1,0)),5),MROUND(INDEX(df_proj!$E$2:$AD$1000, MATCH(1, ($B$2 = df_proj!$A$2:$A$1000) * (df_proj!$B$2:$B$1000 = $B21) * (df_proj!$C$2:$C$1000 = $D$2), 0), MATCH(TEXT(Q$8, "####"), df_proj!$E$1:$AD$1,0)) * popn_fut!$C93/popn_fut!$E93,5))} -> #N/A | R21: {=IFERROR(MROUND(INDEX(df_proj!$E$2:$AD$1000, MATCH(1, ($A$2 = df_proj!$A$2:$A$1000) * (df_proj!$B$2:$B$1000 = $B21) * (df_proj!$C$2:$C$1000 = $D$2), 0), MATCH(TEXT(R$8, "####"), df_proj!$E$1:$AD$1,0)),5),MROUND(INDEX(df_proj!$E$2:$AD$1000, MATCH(1, ($B$2 = df_proj!$A$2:$A$1000) * (df_proj!$B$2:$B$1000 = $B21) * (df_proj!$C$2:$C$1000 = $D$2), 0), MATCH(TEXT(R$8, "####"), df_proj!$E$1:$AD$1,0)) * popn_fut!$C93/popn_fut!$E93,5))} -> #N/A | S21: {=IFERROR(MROUND(INDEX(df_proj!$E$2:$AD$1000, MATCH(1, ($A$2 = df_proj!$A$2:$A$1000) * (df_proj!$B$2:$B$1000 = $B21) * (df_proj!$C$2:$C$1000 = $D$2), 0), MATCH(TEXT(S$8, "####"), df_proj!$E$1:$AD$1,0)),5),MROUND(INDEX(df_proj!$E$2:$AD$1000, MATCH(1, ($B$2 = df_proj!$A$2:$A$1000) * (df_proj!$B$2:$B$1000 = $B21) * (df_proj!$C$2:$C$1000 = $D$2), 0), MATCH(TEXT(S$8, "####"), df_proj!$E$1:$AD$1,0)) * popn_fut!$C93/popn_fut!$E93,5))} -> #N/A | T21: {=IFERROR(MROUND(INDEX(df_proj!$E$2:$AD$1000, MATCH(1, ($A$2 = df_proj!$A$2:$A$1000) * (df_proj!$B$2:$B$1000 = $B21) * (df_proj!$C$2:$C$1000 = $D$2), 0), MATCH(TEXT(T$8, "####"), df_proj!$E$1:$AD$1,0)),5),MROUND(INDEX(df_proj!$E$2:$AD$1000, MATCH(1, ($B$2 = df_proj!$A$2:$A$1000) * (df_proj!$B$2:$B$1000 = $B21) * (df_proj!$C$2:$C$1000 = $D$2), 0), MATCH(TEXT(T$8, "####"), df_proj!$E$1:$AD$1,0)) * popn_fut!$C93/popn_fut!$E93,5))} -> #N/A | ... AL21: {=IFERROR(MROUND(INDEX(df_proj!$E$2:$AD$1000, MATCH(1, ($A$2 = df_proj!$A$2:$A$1000) * (df_proj!$B$2:$B$1000 = $B21) * (df_proj!$C$2:$C$1000 = $D$2), 0), MATCH(TEXT(AL$8, "####"), df_proj!$E$1:$AD$1,0)),5),MROUND(INDEX(df_proj!$E$2:$AD$1000, MATCH(1, ($B$2 = df_proj!$A$2:$A$1000) * (df_proj!$B$2:$B$1000 = $B21) * (df_proj!$C$2:$C$1000 = $D$2), 0), MATCH(TEXT(AL$8, "####"), df_proj!$E$1:$AD$1,0)) * popn_fut!$C93/popn_fut!$E93,5))} -> #N/A | AM21: =AM20+I21 -> #N/A | AP21: =AP20+W21 -> #N/A
A22: 60 | B22: 60 to 64 | D22: #N/A | I22: #N/A | M22: {=IFERROR(MROUND(INDEX(df_proj!$E$2:$AD$1000, MATCH(1, ($A$2 = df_proj!$A$2:$A$1000) * (df_proj!$B$2:$B$1000 = $B22) * (df_proj!$C$2:$C$1000 = $D$2), 0), MATCH(TEXT(M$8, "####"), df_proj!$E$1:$AD$1,0)),5),MROUND(INDEX(df_proj!$E$2:$AD$1000, MATCH(1, ($B$2 = df_proj!$A$2:$A$1000) * (df_proj!$B$2:$B$1000 = $B22) * (df_proj!$C$2:$C$1000 = $D$2), 0), MATCH(TEXT(M$8, "####"), df_proj!$E$1:$AD$1,0)) * popn_fut!$C94/popn_fut!$E94,5))} -> #N/A | N22: {=IFERROR(MROUND(INDEX(df_proj!$E$2:$AD$1000, MATCH(1, ($A$2 = df_proj!$A$2:$A$1000) * (df_proj!$B$2:$B$1000 = $B22) * (df_proj!$C$2:$C$1000 = $D$2), 0), MATCH(TEXT(N$8, "####"), df_proj!$E$1:$AD$1,0)),5),MROUND(INDEX(df_proj!$E$2:$AD$1000, MATCH(1, ($B$2 = df_proj!$A$2:$A$1000) * (df_proj!$B$2:$B$1000 = $B22) * (df_proj!$C$2:$C$1000 = $D$2), 0), MATCH(TEXT(N$8, "####"), df_proj!$E$1:$AD$1,0)) * popn_fut!$C94/popn_fut!$E94,5))} -> #N/A | O22: {=IFERROR(MROUND(INDEX(df_proj!$E$2:$AD$1000, MATCH(1, ($A$2 = df_proj!$A$2:$A$1000) * (df_proj!$B$2:$B$1000 = $B22) * (df_proj!$C$2:$C$1000 = $D$2), 0), MATCH(TEXT(O$8, "####"), df_proj!$E$1:$AD$1,0)),5),MROUND(INDEX(df_proj!$E$2:$AD$1000, MATCH(1, ($B$2 = df_proj!$A$2:$A$1000) * (df_proj!$B$2:$B$1000 = $B22) * (df_proj!$C$2:$C$1000 = $D$2), 0), MATCH(TEXT(O$8, "####"), df_proj!$E$1:$AD$1,0)) * popn_fut!$C94/popn_fut!$E94,5))} -> #N/A | P22: {=IFERROR(MROUND(INDEX(df_proj!$E$2:$AD$1000, MATCH(1, ($A$2 = df_proj!$A$2:$A$1000) * (df_proj!$B$2:$B$1000 = $B22) * (df_proj!$C$2:$C$1000 = $D$2), 0), MATCH(TEXT(P$8, "####"), df_proj!$E$1:$AD$1,0)),5),MROUND(INDEX(df_proj!$E$2:$AD$1000, MATCH(1, ($B$2 = df_proj!$A$2:$A$1000) * (df_proj!$B$2:$B$1000 = $B22) * (df_proj!$C$2:$C$1000 = $D$2), 0), MATCH(TEXT(P$8, "####"), df_proj!$E$1:$AD$1,0)) * popn_fut!$C94/popn_fut!$E94,5))} -> #N/A | Q22: {=IFERROR(MROUND(INDEX(df_proj!$E$2:$AD$1000, MATCH(1, ($A$2 = df_proj!$A$2:$A$1000) * (df_proj!$B$2:$B$1000 = $B22) * (df_proj!$C$2:$C$1000 = $D$2), 0), MATCH(TEXT(Q$8, "####"), df_proj!$E$1:$AD$1,0)),5),MROUND(INDEX(df_proj!$E$2:$AD$1000, MATCH(1, ($B$2 = df_proj!$A$2:$A$1000) * (df_proj!$B$2:$B$1000 = $B22) * (df_proj!$C$2:$C$1000 = $D$2), 0), MATCH(TEXT(Q$8, "####"), df_proj!$E$1:$AD$1,0)) * popn_fut!$C94/popn_fut!$E94,5))} -> #N/A | R22: {=IFERROR(MROUND(INDEX(df_proj!$E$2:$AD$1000, MATCH(1, ($A$2 = df_proj!$A$2:$A$1000) * (df_proj!$B$2:$B$1000 = $B22) * (df_proj!$C$2:$C$1000 = $D$2), 0), MATCH(TEXT(R$8, "####"), df_proj!$E$1:$AD$1,0)),5),MROUND(INDEX(df_proj!$E$2:$AD$1000, MATCH(1, ($B$2 = df_proj!$A$2:$A$1000) * (df_proj!$B$2:$B$1000 = $B22) * (df_proj!$C$2:$C$1000 = $D$2), 0), MATCH(TEXT(R$8, "####"), df_proj!$E$1:$AD$1,0)) * popn_fut!$C94/popn_fut!$E94,5))} -> #N/A | S22: {=IFERROR(MROUND(INDEX(df_proj!$E$2:$AD$1000, MATCH(1, ($A$2 = df_proj!$A$2:$A$1000) * (df_proj!$B$2:$B$1000 = $B22) * (df_proj!$C$2:$C$1000 = $D$2), 0), MATCH(TEXT(S$8, "####"), df_proj!$E$1:$AD$1,0)),5),MROUND(INDEX(df_proj!$E$2:$AD$1000, MATCH(1, ($B$2 = df_proj!$A$2:$A$1000) * (df_proj!$B$2:$B$1000 = $B22) * (df_proj!$C$2:$C$1000 = $D$2), 0), MATCH(TEXT(S$8, "####"), df_proj!$E$1:$AD$1,0)) * popn_fut!$C94/popn_fut!$E94,5))} -> #N/A | T22: {=IFERROR(MROUND(INDEX(df_proj!$E$2:$AD$1000, MATCH(1, ($A$2 = df_proj!$A$2:$A$1000) * (df_proj!$B$2:$B$1000 = $B22) * (df_proj!$C$2:$C$1000 = $D$2), 0), MATCH(TEXT(T$8, "####"), df_proj!$E$1:$AD$1,0)),5),MROUND(INDEX(df_proj!$E$2:$AD$1000, MATCH(1, ($B$2 = df_proj!$A$2:$A$1000) * (df_proj!$B$2:$B$1000 = $B22) * (df_proj!$C$2:$C$1000 = $D$2), 0), MATCH(TEXT(T$8, "####"), df_proj!$E$1:$AD$1,0)) * popn_fut!$C94/popn_fut!$E94,5))} -> #N/A | ... AL22: {=IFERROR(MROUND(INDEX(df_proj!$E$2:$AD$1000, MATCH(1, ($A$2 = df_proj!$A$2:$A$1000) * (df_proj!$B$2:$B$1000 = $B22) * (df_proj!$C$2:$C$1000 = $D$2), 0), MATCH(TEXT(AL$8, "####"), df_proj!$E$1:$AD$1,0)),5),MROUND(INDEX(df_proj!$E$2:$AD$1000, MATCH(1, ($B$2 = df_proj!$A$2:$A$1000) * (df_proj!$B$2:$B$1000 = $B22) * (df_proj!$C$2:$C$1000 = $D$2), 0), MATCH(TEXT(AL$8, "####"), df_proj!$E$1:$AD$1,0)) * popn_fut!$C94/popn_fut!$E94,5))} -> #N/A | AM22: =AM21+I22 -> #N/A | AP22: =AP21+W22 -> #N/A
... A24: 70 | B24: 70 to 74 | D24: #N/A | I24: #N/A | M24: {=IFERROR(MROUND(INDEX(df_proj!$E$2:$AD$1000, MATCH(1, ($A$2 = df_proj!$A$2:$A$1000) * (df_proj!$B$2:$B$1000 = $B24) * (df_proj!$C$2:$C$1000 = $D$2), 0), MATCH(TEXT(M$8, "####"), df_proj!$E$1:$AD$1,0)),5),MROUND(INDEX(df_proj!$E$2:$AD$1000, MATCH(1, ($B$2 = df_proj!$A$2:$A$1000) * (df_proj!$B$2:$B$1000 = $B24) * (df_proj!$C$2:$C$1000 = $D$2), 0), MATCH(TEXT(M$8, "####"), df_proj!$E$1:$AD$1,0)) * popn_fut!$C96/popn_fut!$E96,5))} -> #N/A | N24: {=IFERROR(MROUND(INDEX(df_proj!$E$2:$AD$1000, MATCH(1, ($A$2 = df_proj!$A$2:$A$1000) * (df_proj!$B$2:$B$1000 = $B24) * (df_proj!$C$2:$C$1000 = $D$2), 0), MATCH(TEXT(N$8, "####"), df_proj!$E$1:$AD$1,0)),5),MROUND(INDEX(df_proj!$E$2:$AD$1000, MATCH(1, ($B$2 = df_proj!$A$2:$A$1000) * (df_proj!$B$2:$B$1000 = $B24) * (df_proj!$C$2:$C$1000 = $D$2), 0), MATCH(TEXT(N$8, "####"), df_proj!$E$1:$AD$1,0)) * popn_fut!$C96/popn_fut!$E96,5))} -> #N/A | O24: {=IFERROR(MROUND(INDEX(df_proj!$E$2:$AD$1000, MATCH(1, ($A$2 = df_proj!$A$2:$A$1000) * (df_proj!$B$2:$B$1000 = $B24) * (df_proj!$C$2:$C$1000 = $D$2), 0), MATCH(TEXT(O$8, "####"), df_proj!$E$1:$AD$1,0)),5),MROUND(INDEX(df_proj!$E$2:$AD$1000, MATCH(1, ($B$2 = df_proj!$A$2:$A$1000) * (df_proj!$B$2:$B$1000 = $B24) * (df_proj!$C$2:$C$1000 = $D$2), 0), MATCH(TEXT(O$8, "####"), df_proj!$E$1:$AD$1,0)) * popn_fut!$C96/popn_fut!$E96,5))} -> #N/A | P24: {=IFERROR(MROUND(INDEX(df_proj!$E$2:$AD$1000, MATCH(1, ($A$2 = df_proj!$A$2:$A$1000) * (df_proj!$B$2:$B$1000 = $B24) * (df_proj!$C$2:$C$1000 = $D$2), 0), MATCH(TEXT(P$8, "####"), df_proj!$E$1:$AD$1,0)),5),MROUND(INDEX(df_proj!$E$2:$AD$1000, MATCH(1, ($B$2 = df_proj!$A$2:$A$1000) * (df_proj!$B$2:$B$1000 = $B24) * (df_proj!$C$2:$C$1000 = $D$2), 0), MATCH(TEXT(P$8, "####"), df_proj!$E$1:$AD$1,0)) * popn_fut!$C96/popn_fut!$E96,5))} -> #N/A | Q24: {=IFERROR(MROUND(INDEX(df_proj!$E$2:$AD$1000, MATCH(1, ($A$2 = df_proj!$A$2:$A$1000) * (df_proj!$B$2:$B$1000 = $B24) * (df_proj!$C$2:$C$1000 = $D$2), 0), MATCH(TEXT(Q$8, "####"), df_proj!$E$1:$AD$1,0)),5),MROUND(INDEX(df_proj!$E$2:$AD$1000, MATCH(1, ($B$2 = df_proj!$A$2:$A$1000) * (df_proj!$B$2:$B$1000 = $B24) * (df_proj!$C$2:$C$1000 = $D$2), 0), MATCH(TEXT(Q$8, "####"), df_proj!$E$1:$AD$1,0)) * popn_fut!$C96/popn_fut!$E96,5))} -> #N/A | R24: {=IFERROR(MROUND(INDEX(df_proj!$E$2:$AD$1000, MATCH(1, ($A$2 = df_proj!$A$2:$A$1000) * (df_proj!$B$2:$B$1000 = $B24) * (df_proj!$C$2:$C$1000 = $D$2), 0), MATCH(TEXT(R$8, "####"), df_proj!$E$1:$AD$1,0)),5),MROUND(INDEX(df_proj!$E$2:$AD$1000, MATCH(1, ($B$2 = df_proj!$A$2:$A$1000) * (df_proj!$B$2:$B$1000 = $B24) * (df_proj!$C$2:$C$1000 = $D$2), 0), MATCH(TEXT(R$8, "####"), df_proj!$E$1:$AD$1,0)) * popn_fut!$C96/popn_fut!$E96,5))} -> #N/A | S24: {=IFERROR(MROUND(INDEX(df_proj!$E$2:$AD$1000, MATCH(1, ($A$2 = df_proj!$A$2:$A$1000) * (df_proj!$B$2:$B$1000 = $B24) * (df_proj!$C$2:$C$1000 = $D$2), 0), MATCH(TEXT(S$8, "####"), df_proj!$E$1:$AD$1,0)),5),MROUND(INDEX(df_proj!$E$2:$AD$1000, MATCH(1, ($B$2 = df_proj!$A$2:$A$1000) * (df_proj!$B$2:$B$1000 = $B24) * (df_proj!$C$2:$C$1000 = $D$2), 0), MATCH(TEXT(S$8, "####"), df_proj!$E$1:$AD$1,0)) * popn_fut!$C96/popn_fut!$E96,5))} -> #N/A | T24: {=IFERROR(MROUND(INDEX(df_proj!$E$2:$AD$1000, MATCH(1, ($A$2 = df_proj!$A$2:$A$1000) * (df_proj!$B$2:$B$1000 = $B24) * (df_proj!$C$2:$C$1000 = $D$2), 0), MATCH(TEXT(T$8, "####"), df_proj!$E$1:$AD$1,0)),5),MROUND(INDEX(df_proj!$E$2:$AD$1000, MATCH(1, ($B$2 = df_proj!$A$2:$A$1000) * (df_proj!$B$2:$B$1000 = $B24) * (df_proj!$C$2:$C$1000 = $D$2), 0), MATCH(TEXT(T$8, "####"), df_proj!$E$1:$AD$1,0)) * popn_fut!$C96/popn_fut!$E96,5))} -> #N/A | ... AL24: {=IFERROR(MROUND(INDEX(df_proj!$E$2:$AD$1000, MATCH(1, ($A$2 = df_proj!$A$2:$A$1000) * (df_proj!$B$2:$B$1000 = $B24) * (df_proj!$C$2:$C$1000 = $D$2), 0), MATCH(TEXT(AL$8, "####"), df_proj!$E$1:$AD$1,0)),5),MROUND(INDEX(df_proj!$E$2:$AD$1000, MATCH(1, ($B$2 = df_proj!$A$2:$A$1000) * (df_proj!$B$2:$B$1000 = $B24) * (df_proj!$C$2:$C$1000 = $D$2), 0), MATCH(TEXT(AL$8, "####"), df_proj!$E$1:$AD$1,0)) * popn_fut!$C96/popn_fut!$E96,5))} -> #N/A | AM24: =AM23+I24 -> #N/A | AP24: =AP23+W24 -> #N/A
A25: 75 | B25: 75 to 79 | D25: #N/A | I25: #N/A | M25: {=IFERROR(MROUND(INDEX(df_proj!$E$2:$AD$1000, MATCH(1, ($A$2 = df_proj!$A$2:$A$1000) * (df_proj!$B$2:$B$1000 = $B25) * (df_proj!$C$2:$C$1000 = $D$2), 0), MATCH(TEXT(M$8, "####"), df_proj!$E$1:$AD$1,0)),5),MROUND(INDEX(df_proj!$E$2:$AD$1000, MATCH(1, ($B$2 = df_proj!$A$2:$A$1000) * (df_proj!$B$2:$B$1000 = $B25) * (df_proj!$C$2:$C$1000 = $D$2), 0), MATCH(TEXT(M$8, "####"), df_proj!$E$1:$AD$1,0)) * popn_fut!$C97/popn_fut!$E97,5))} -> #N/A | N25: {=IFERROR(MROUND(INDEX(df_proj!$E$2:$AD$1000, MATCH(1, ($A$2 = df_proj!$A$2:$A$1000) * (df_proj!$B$2:$B$1000 = $B25) * (df_proj!$C$2:$C$1000 = $D$2), 0), MATCH(TEXT(N$8, "####"), df_proj!$E$1:$AD$1,0)),5),MROUND(INDEX(df_proj!$E$2:$AD$1000, MATCH(1, ($B$2 = df_proj!$A$2:$A$1000) * (df_proj!$B$2:$B$1000 = $B25) * (df_proj!$C$2:$C$1000 = $D$2), 0), MATCH(TEXT(N$8, "####"), df_proj!$E$1:$AD$1,0)) * popn_fut!$C97/popn_fut!$E97,5))} -> #N/A | O25: {=IFERROR(MROUND(INDEX(df_proj!$E$2:$AD$1000, MATCH(1, ($A$2 = df_proj!$A$2:$A$1000) * (df_proj!$B$2:$B$1000 = $B25) * (df_proj!$C$2:$C$1000 = $D$2), 0), MATCH(TEXT(O$8, "####"), df_proj!$E$1:$AD$1,0)),5),MROUND(INDEX(df_proj!$E$2:$AD$1000, MATCH(1, ($B$2 = df_proj!$A$2:$A$1000) * (df_proj!$B$2:$B$1000 = $B25) * (df_proj!$C$2:$C$1000 = $D$2), 0), MATCH(TEXT(O$8, "####"), df_proj!$E$1:$AD$1,0)) * popn_fut!$C97/popn_fut!$E97,5))} -> #N/A | P25: {=IFERROR(MROUND(INDEX(df_proj!$E$2:$AD$1000, MATCH(1, ($A$2 = df_proj!$A$2:$A$1000) * (df_proj!$B$2:$B$1000 = $B25) * (df_proj!$C$2:$C$1000 = $D$2), 0), MATCH(TEXT(P$8, "####"), df_proj!$E$1:$AD$1,0)),5),MROUND(INDEX(df_proj!$E$2:$AD$1000, MATCH(1, ($B$2 = df_proj!$A$2:$A$1000) * (df_proj!$B$2:$B$1000 = $B25) * (df_proj!$C$2:$C$1000 = $D$2), 0), MATCH(TEXT(P$8, "####"), df_proj!$E$1:$AD$1,0)) * popn_fut!$C97/popn_fut!$E97,5))} -> #N/A | Q25: {=IFERROR(MROUND(INDEX(df_proj!$E$2:$AD$1000, MATCH(1, ($A$2 = df_proj!$A$2:$A$1000) * (df_proj!$B$2:$B$1000 = $B25) * (df_proj!$C$2:$C$1000 = $D$2), 0), MATCH(TEXT(Q$8, "####"), df_proj!$E$1:$AD$1,0)),5),MROUND(INDEX(df_proj!$E$2:$AD$1000, MATCH(1, ($B$2 = df_proj!$A$2:$A$1000) * (df_proj!$B$2:$B$1000 = $B25) * (df_proj!$C$2:$C$1000 = $D$2), 0), MATCH(TEXT(Q$8, "####"), df_proj!$E$1:$AD$1,0)) * popn_fut!$C97/popn_fut!$E97,5))} -> #N/A | R25: {=IFERROR(MROUND(INDEX(df_proj!$E$2:$AD$1000, MATCH(1, ($A$2 = df_proj!$A$2:$A$1000) * (df_proj!$B$2:$B$1000 = $B25) * (df_proj!$C$2:$C$1000 = $D$2), 0), MATCH(TEXT(R$8, "####"), df_proj!$E$1:$AD$1,0)),5),MROUND(INDEX(df_proj!$E$2:$AD$1000, MATCH(1, ($B$2 = df_proj!$A$2:$A$1000) * (df_proj!$B$2:$B$1000 = $B25) * (df_proj!$C$2:$C$1000 = $D$2), 0), MATCH(TEXT(R$8, "####"), df_proj!$E$1:$AD$1,0)) * popn_fut!$C97/popn_fut!$E97,5))} -> #N/A | S25: {=IFERROR(MROUND(INDEX(df_proj!$E$2:$AD$1000, MATCH(1, ($A$2 = df_proj!$A$2:$A$1000) * (df_proj!$B$2:$B$1000 = $B25) * (df_proj!$C$2:$C$1000 = $D$2), 0), MATCH(TEXT(S$8, "####"), df_proj!$E$1:$AD$1,0)),5),MROUND(INDEX(df_proj!$E$2:$AD$1000, MATCH(1, ($B$2 = df_proj!$A$2:$A$1000) * (df_proj!$B$2:$B$1000 = $B25) * (df_proj!$C$2:$C$1000 = $D$2), 0), MATCH(TEXT(S$8, "####"), df_proj!$E$1:$AD$1,0)) * popn_fut!$C97/popn_fut!$E97,5))} -> #N/A | T25: {=IFERROR(MROUND(INDEX(df_proj!$E$2:$AD$1000, MATCH(1, ($A$2 = df_proj!$A$2:$A$1000) * (df_proj!$B$2:$B$1000 = $B25) * (df_proj!$C$2:$C$1000 = $D$2), 0), MATCH(TEXT(T$8, "####"), df_proj!$E$1:$AD$1,0)),5),MROUND(INDEX(df_proj!$E$2:$AD$1000, MATCH(1, ($B$2 = df_proj!$A$2:$A$1000) * (df_proj!$B$2:$B$1000 = $B25) * (df_proj!$C$2:$C$1000 = $D$2), 0), MATCH(TEXT(T$8, "####"), df_proj!$E$1:$AD$1,0)) * popn_fut!$C97/popn_fut!$E97,5))} -> #N/A | ... AL25: {=IFERROR(MROUND(INDEX(df_proj!$E$2:$AD$1000, MATCH(1, ($A$2 = df_proj!$A$2:$A$1000) * (df_proj!$B$2:$B$1000 = $B25) * (df_proj!$C$2:$C$1000 = $D$2), 0), MATCH(TEXT(AL$8, "####"), df_proj!$E$1:$AD$1,0)),5),MROUND(INDEX(df_proj!$E$2:$AD$1000, MATCH(1, ($B$2 = df_proj!$A$2:$A$1000) * (df_proj!$B$2:$B$1000 = $B25) * (df_proj!$C$2:$C$1000 = $D$2), 0), MATCH(TEXT(AL$8, "####"), df_proj!$E$1:$AD$1,0)) * popn_fut!$C97/popn_fut!$E97,5))} -> #N/A | AM25: =AM24+I25 -> #N/A | AO25: {=SUMPRODUCT(I10:I27,A10:A27+2) / SUM(I10:I27)} -> #N/A | AP25: =AP24+W25 -> #N/A | AR25: =SUMPRODUCT(W10:W27,A10:A27+2) / SUM(W10:W27) -> #N/A | AS25: =AR25-AO25+federal_req!E8 -> #N/A
A26: 80 | B26: 80 to 84 | D26: #N/A | I26: #N/A | M26: {=IFERROR(MROUND(INDEX(df_proj!$E$2:$AD$1000, MATCH(1, ($A$2 = df_proj!$A$2:$A$1000) * (df_proj!$B$2:$B$1000 = $B26) * (df_proj!$C$2:$C$1000 = $D$2), 0), MATCH(TEXT(M$8, "####"), df_proj!$E$1:$AD$1,0)),5),MROUND(INDEX(df_proj!$E$2:$AD$1000, MATCH(1, ($B$2 = df_proj!$A$2:$A$1000) * (df_proj!$B$2:$B$1000 = $B26) * (df_proj!$C$2:$C$1000 = $D$2), 0), MATCH(TEXT(M$8, "####"), df_proj!$E$1:$AD$1,0)) * popn_fut!$C98/popn_fut!$E98,5))} -> #N/A | N26: {=IFERROR(MROUND(INDEX(df_proj!$E$2:$AD$1000, MATCH(1, ($A$2 = df_proj!$A$2:$A$1000) * (df_proj!$B$2:$B$1000 = $B26) * (df_proj!$C$2:$C$1000 = $D$2), 0), MATCH(TEXT(N$8, "####"), df_proj!$E$1:$AD$1,0)),5),MROUND(INDEX(df_proj!$E$2:$AD$1000, MATCH(1, ($B$2 = df_proj!$A$2:$A$1000) * (df_proj!$B$2:$B$1000 = $B26) * (df_proj!$C$2:$C$1000 = $D$2), 0), MATCH(TEXT(N$8, "####"), df_proj!$E$1:$AD$1,0)) * popn_fut!$C98/popn_fut!$E98,5))} -> #N/A | O26: {=IFERROR(MROUND(INDEX(df_proj!$E$2:$AD$1000, MATCH(1, ($A$2 = df_proj!$A$2:$A$1000) * (df_proj!$B$2:$B$1000 = $B26) * (df_proj!$C$2:$C$1000 = $D$2), 0), MATCH(TEXT(O$8, "####"), df_proj!$E$1:$AD$1,0)),5),MROUND(INDEX(df_proj!$E$2:$AD$1000, MATCH(1, ($B$2 = df_proj!$A$2:$A$1000) * (df_proj!$B$2:$B$1000 = $B26) * (df_proj!$C$2:$C$1000 = $D$2), 0), MATCH(TEXT(O$8, "####"), df_proj!$E$1:$AD$1,0)) * popn_fut!$C98/popn_fut!$E98,5))} -> #N/A | P26: {=IFERROR(MROUND(INDEX(df_proj!$E$2:$AD$1000, MATCH(1, ($A$2 = df_proj!$A$2:$A$1000) * (df_proj!$B$2:$B$1000 = $B26) * (df_proj!$C$2:$C$1000 = $D$2), 0), MATCH(TEXT(P$8, "####"), df_proj!$E$1:$AD$1,0)),5),MROUND(INDEX(df_proj!$E$2:$AD$1000, MATCH(1, ($B$2 = df_proj!$A$2:$A$1000) * (df_proj!$B$2:$B$1000 = $B26) * (df_proj!$C$2:$C$1000 = $D$2), 0), MATCH(TEXT(P$8, "####"), df_proj!$E$1:$AD$1,0)) * popn_fut!$C98/popn_fut!$E98,5))} -> #N/A | Q26: {=IFERROR(MROUND(INDEX(df_proj!$E$2:$AD$1000, MATCH(1, ($A$2 = df_proj!$A$2:$A$1000) * (df_proj!$B$2:$B$1000 = $B26) * (df_proj!$C$2:$C$1000 = $D$2), 0), MATCH(TEXT(Q$8, "####"), df_proj!$E$1:$AD$1,0)),5),MROUND(INDEX(df_proj!$E$2:$AD$1000, MATCH(1, ($B$2 = df_proj!$A$2:$A$1000) * (df_proj!$B$2:$B$1000 = $B26) * (df_proj!$C$2:$C$1000 = $D$2), 0), MATCH(TEXT(Q$8, "####"), df_proj!$E$1:$AD$1,0)) * popn_fut!$C98/popn_fut!$E98,5))} -> #N/A | R26: {=IFERROR(MROUND(INDEX(df_proj!$E$2:$AD$1000, MATCH(1, ($A$2 = df_proj!$A$2:$A$1000) * (df_proj!$B$2:$B$1000 = $B26) * (df_proj!$C$2:$C$1000 = $D$2), 0), MATCH(TEXT(R$8, "####"), df_proj!$E$1:$AD$1,0)),5),MROUND(INDEX(df_proj!$E$2:$AD$1000, MATCH(1, ($B$2 = df_proj!$A$2:$A$1000) * (df_proj!$B$2:$B$1000 = $B26) * (df_proj!$C$2:$C$1000 = $D$2), 0), MATCH(TEXT(R$8, "####"), df_proj!$E$1:$AD$1,0)) * popn_fut!$C98/popn_fut!$E98,5))} -> #N/A | S26: {=IFERROR(MROUND(INDEX(df_proj!$E$2:$AD$1000, MATCH(1, ($A$2 = df_proj!$A$2:$A$1000) * (df_proj!$B$2:$B$1000 = $B26) * (df_proj!$C$2:$C$1000 = $D$2), 0), MATCH(TEXT(S$8, "####"), df_proj!$E$1:$AD$1,0)),5),MROUND(INDEX(df_proj!$E$2:$AD$1000, MATCH(1, ($B$2 = df_proj!$A$2:$A$1000) * (df_proj!$B$2:$B$1000 = $B26) * (df_proj!$C$2:$C$1000 = $D$2), 0), MATCH(TEXT(S$8, "####"), df_proj!$E$1:$AD$1,0)) * popn_fut!$C98/popn_fut!$E98,5))} -> #N/A | T26: {=IFERROR(MROUND(INDEX(df_proj!$E$2:$AD$1000, MATCH(1, ($A$2 = df_proj!$A$2:$A$1000) * (df_proj!$B$2:$B$1000 = $B26) * (df_proj!$C$2:$C$1000 = $D$2), 0), MATCH(TEXT(T$8, "####"), df_proj!$E$1:$AD$1,0)),5),MROUND(INDEX(df_proj!$E$2:$AD$1000, MATCH(1, ($B$2 = df_proj!$A$2:$A$1000) * (df_proj!$B$2:$B$1000 = $B26) * (df_proj!$C$2:$C$1000 = $D$2), 0), MATCH(TEXT(T$8, "####"), df_proj!$E$1:$AD$1,0)) * popn_fut!$C98/popn_fut!$E98,5))} -> #N/A | ... AL26: {=IFERROR(MROUND(INDEX(df_proj!$E$2:$AD$1000, MATCH(1, ($A$2 = df_proj!$A$2:$A$1000) * (df_proj!$B$2:$B$1000 = $B26) * (df_proj!$C$2:$C$1000 = $D$2), 0), MATCH(TEXT(AL$8, "####"), df_proj!$E$1:$AD$1,0)),5),MROUND(INDEX(df_proj!$E$2:$AD$1000, MATCH(1, ($B$2 = df_proj!$A$2:$A$1000) * (df_proj!$B$2:$B$1000 = $B26) * (df_proj!$C$2:$C$1000 = $D$2), 0), MATCH(TEXT(AL$8, "####"), df_proj!$E$1:$AD$1,0)) * popn_fut!$C98/popn_fut!$E98,5))} -> #N/A | AM26: =AM25+I26 -> #N/A | AO26: =AO27+5*(AM28-AN27)/(AN28-AN27) -> #N/A | AP26: =AP25+W26 -> #N/A | AR26: =AR27+5*(AP28-AQ27)/(AQ28-AQ27) -> #N/A | AS26: =AR26-AO26+federal_req!E9 -> #N/A
A27: 85 | B27: 85+ | D27: #N/A | I27: #N/A | M27: {=IFERROR(MROUND(INDEX(df_proj!$E$2:$AD$1000, MATCH(1, ($A$2 = df_proj!$A$2:$A$1000) * (df_proj!$B$2:$B$1000 & "+" = $B27) * (df_proj!$C$2:$C$1000 = $D$2), 0), MATCH(TEXT(M$8, "####"), df_proj!$E$1:$AD$1,0)),5),MROUND(INDEX(df_proj!$E$2:$AD$1000, MATCH(1, ($B$2 = df_proj!$A$2:$A$1000) * (df_proj!$B$2:$B$1000 & "+" = $B27) * (df_proj!$C$2:$C$1000 = $D$2), 0), MATCH(TEXT(M$8, "####"), df_proj!$E$1:$AD$1,0)) * popn_fut!$C99/popn_fut!$E99,5))} -> #N/A | N27: {=IFERROR(MROUND(INDEX(df_proj!$E$2:$AD$1000, MATCH(1, ($A$2 = df_proj!$A$2:$A$1000) * (df_proj!$B$2:$B$1000 & "+" = $B27) * (df_proj!$C$2:$C$1000 = $D$2), 0), MATCH(TEXT(N$8, "####"), df_proj!$E$1:$AD$1,0)),5),MROUND(INDEX(df_proj!$E$2:$AD$1000, MATCH(1, ($B$2 = df_proj!$A$2:$A$1000) * (df_proj!$B$2:$B$1000 & "+" = $B27) * (df_proj!$C$2:$C$1000 = $D$2), 0), MATCH(TEXT(N$8, "####"), df_proj!$E$1:$AD$1,0)) * popn_fut!$C99/popn_fut!$E99,5))} -> #N/A | O27: {=IFERROR(MROUND(INDEX(df_proj!$E$2:$AD$1000, MATCH(1, ($A$2 = df_proj!$A$2:$A$1000) * (df_proj!$B$2:$B$1000 & "+" = $B27) * (df_proj!$C$2:$C$1000 = $D$2), 0), MATCH(TEXT(O$8, "####"), df_proj!$E$1:$AD$1,0)),5),MROUND(INDEX(df_proj!$E$2:$AD$1000, MATCH(1, ($B$2 = df_proj!$A$2:$A$1000) * (df_proj!$B$2:$B$1000 & "+" = $B27) * (df_proj!$C$2:$C$1000 = $D$2), 0), MATCH(TEXT(O$8, "####"), df_proj!$E$1:$AD$1,0)) * popn_fut!$C99/popn_fut!$E99,5))} -> #N/A | P27: {=IFERROR(MROUND(INDEX(df_proj!$E$2:$AD$1000, MATCH(1, ($A$2 = df_proj!$A$2:$A$1000) * (df_proj!$B$2:$B$1000 & "+" = $B27) * (df_proj!$C$2:$C$1000 = $D$2), 0), MATCH(TEXT(P$8, "####"), df_proj!$E$1:$AD$1,0)),5),MROUND(INDEX(df_proj!$E$2:$AD$1000, MATCH(1, ($B$2 = df_proj!$A$2:$A$1000) * (df_proj!$B$2:$B$1000 & "+" = $B27) * (df_proj!$C$2:$C$1000 = $D$2), 0), MATCH(TEXT(P$8, "####"), df_proj!$E$1:$AD$1,0)) * popn_fut!$C99/popn_fut!$E99,5))} -> #N/A | Q27: {=IFERROR(MROUND(INDEX(df_proj!$E$2:$AD$1000, MATCH(1, ($A$2 = df_proj!$A$2:$A$1000) * (df_proj!$B$2:$B$1000 & "+" = $B27) * (df_proj!$C$2:$C$1000 = $D$2), 0), MATCH(TEXT(Q$8, "####"), df_proj!$E$1:$AD$1,0)),5),MROUND(INDEX(df_proj!$E$2:$AD$1000, MATCH(1, ($B$2 = df_proj!$A$2:$A$1000) * (df_proj!$B$2:$B$1000 & "+" = $B27) * (df_proj!$C$2:$C$1000 = $D$2), 0), MATCH(TEXT(Q$8, "####"), df_proj!$E$1:$AD$1,0)) * popn_fut!$C99/popn_fut!$E99,5))} -> #N/A | R27: {=IFERROR(MROUND(INDEX(df_proj!$E$2:$AD$1000, MATCH(1, ($A$2 = df_proj!$A$2:$A$1000) * (df_proj!$B$2:$B$1000 & "+" = $B27) * (df_proj!$C$2:$C$1000 = $D$2), 0), MATCH(TEXT(R$8, "####"), df_proj!$E$1:$AD$1,0)),5),MROUND(INDEX(df_proj!$E$2:$AD$1000, MATCH(1, ($B$2 = df_proj!$A$2:$A$1000) * (df_proj!$B$2:$B$1000 & "+" = $B27) * (df_proj!$C$2:$C$1000 = $D$2), 0), MATCH(TEXT(R$8, "####"), df_proj!$E$1:$AD$1,0)) * popn_fut!$C99/popn_fut!$E99,5))} -> #N/A | S27: {=IFERROR(MROUND(INDEX(df_proj!$E$2:$AD$1000, MATCH(1, ($A$2 = df_proj!$A$2:$A$1000) * (df_proj!$B$2:$B$1000 & "+" = $B27) * (df_proj!$C$2:$C$1000 = $D$2), 0), MATCH(TEXT(S$8, "####"), df_proj!$E$1:$AD$1,0)),5),MROUND(INDEX(df_proj!$E$2:$AD$1000, MATCH(1, ($B$2 = df_proj!$A$2:$A$1000) * (df_proj!$B$2:$B$1000 & "+" = $B27) * (df_proj!$C$2:$C$1000 = $D$2), 0), MATCH(TEXT(S$8, "####"), df_proj!$E$1:$AD$1,0)) * popn_fut!$C99/popn_fut!$E99,5))} -> #N/A | T27: {=IFERROR(MROUND(INDEX(df_proj!$E$2:$AD$1000, MATCH(1, ($A$2 = df_proj!$A$2:$A$1000) * (df_proj!$B$2:$B$1000 & "+" = $B27) * (df_proj!$C$2:$C$1000 = $D$2), 0), MATCH(TEXT(T$8, "####"), df_proj!$E$1:$AD$1,0)),5),MROUND(INDEX(df_proj!$E$2:$AD$1000, MATCH(1, ($B$2 = df_proj!$A$2:$A$1000) * (df_proj!$B$2:$B$1000 & "+" = $B27) * (df_proj!$C$2:$C$1000 = $D$2), 0), MATCH(TEXT(T$8, "####"), df_proj!$E$1:$AD$1,0)) * popn_fut!$C99/popn_fut!$E99,5))} -> #N/A | ... AL27: {=IFERROR(MROUND(INDEX(df_proj!$E$2:$AD$1000, MATCH(1, ($A$2 = df_proj!$A$2:$A$1000) * (df_proj!$B$2:$B$1000 & "+" = $B27) * (df_proj!$C$2:$C$1000 = $D$2), 0), MATCH(TEXT(AL$8, "####"), df_proj!$E$1:$AD$1,0)),5),MROUND(INDEX(df_proj!$E$2:$AD$1000, MATCH(1, ($B$2 = df_proj!$A$2:$A$1000) * (df_proj!$B$2:$B$1000 & "+" = $B27) * (df_proj!$C$2:$C$1000 = $D$2), 0), MATCH(TEXT(AL$8, "####"), df_proj!$E$1:$AD$1,0)) * popn_fut!$C99/popn_fut!$E99,5))} -> #N/A | AM27: =AM26+I27 -> #N/A | AN27: =INDEX($AM$10:$AM$27,MATCH(AN28,AM10:AM27,0)-1,0) -> #N/A | AO27: =INDEX(A10:A27,MATCH(AN27,AM10:AM27,0),0)+5 -> #N/A | AP27: =AP26+L27 -> #N/A | AQ27: =INDEX($AP$10:$AP$27,MATCH(AQ28,AP10:AP27,0)-1,0) -> #N/A | AR27: =INDEX(A10:A27,MATCH(AQ27,AP10:AP27,0),0)+5 -> #N/A
AM28: =AM27/2 -> #N/A | AN28: =_xlfn.MINIFS(AM11:AM27,AM11:AM27,">"&AM28) -> #N/A | AO28: =AO27+4 -> #N/A | AP28: =AP27/2 -> #N/A | AQ28: =_xlfn.MINIFS(AP11:AP27,AP11:AP27,">"&AP28) -> #N/A | AR28: =AR27+4 -> #N/A
B29: HOUSEHOLDS
C30: 2015 | D30: 2016 | E30: 2017 | F30: 2018 | G30: 2019 | H30: 2020 | I30: 2021 | J30: 2022 | K30: 2023 | L30: 2024 | M30: 2025 | N30: 2026 | O30: 2027 | P30: 2028 | Q30: 2029 | R30: 2030 | S30: 2031 | T30: 2032 | U30: 2033 | V30: 2034 | W30: 2035 | X30: 2036 | Y30: 2037 | Z30: 2038 | AA30: 2039 | AB30: 2040 | AC30: 2041 | AD30: 2042 | AE30: 2043 | AF30: 2044 | AG30: 2045 | AH30: 2046 | AI30: 2047 | AJ30: 2048 | AK30: 2049 | AL30: 2050
B31: Total households | D31: {=hh!D72:D80} -> #N/A | I31: {=hh!E72:E80} -> #N/A | J31: =SUM(J32:J39) -> #N/A | K31: =SUM(K32:K39) -> #N/A | L31: =SUM(L32:L39) -> #N/A | M31: =MROUND(SUM(M32:M39),5) -> 0 | N31: =MROUND(SUM(N32:N39),5) -> 0 | O31: =MROUND(SUM(O32:O39),5) -> 0 | P31: =MROUND(SUM(P32:P39),5) -> 0 | Q31: =MROUND(SUM(Q32:Q39),5) -> 0 | R31: =MROUND(SUM(R32:R39),5) -> 0 | S31: =MROUND(SUM(S32:S39),5) -> 0 | T31: =MROUND(SUM(T32:T39),5) -> 0 | ... AL31: =MROUND(SUM(AL32:AL39),5) -> 0
A32: 15 | B32: 15 to 24 | D32: #N/A | I32: #N/A | J32: =(M32-I32)/4+I32 -> #N/A | K32: =(M32-I32)/4+J32 -> #N/A | L32: =(M32-I32)/4+K32 -> #N/A | M32: {=IFERROR(MROUND(IFERROR($D$32/SUM($D$13:$D$14)*SUM(M13:M14), $I$32/SUM($I$13:$I$14)*SUM(M13:M14)),5),0)} -> 0 | N32: {=IFERROR(MROUND(IFERROR($D$32/SUM($D$13:$D$14)*SUM(N13:N14), $I$32/SUM($I$13:$I$14)*SUM(N13:N14)),5),0)} -> 0 | O32: {=IFERROR(MROUND(IFERROR($D$32/SUM($D$13:$D$14)*SUM(O13:O14), $I$32/SUM($I$13:$I$14)*SUM(O13:O14)),5),0)} -> 0 | P32: {=IFERROR(MROUND(IFERROR($D$32/SUM($D$13:$D$14)*SUM(P13:P14), $I$32/SUM($I$13:$I$14)*SUM(P13:P14)),5),0)} -> 0 | Q32: {=IFERROR(MROUND(IFERROR($D$32/SUM($D$13:$D$14)*SUM(Q13:Q14), $I$32/SUM($I$13:$I$14)*SUM(Q13:Q14)),5),0)} -> 0 | R32: {=IFERROR(MROUND(IFERROR($D$32/SUM($D$13:$D$14)*SUM(R13:R14), $I$32/SUM($I$13:$I$14)*SUM(R13:R14)),5),0)} -> 0 | S32: {=IFERROR(MROUND(IFERROR($D$32/SUM($D$13:$D$14)*SUM(S13:S14), $I$32/SUM($I$13:$I$14)*SUM(S13:S14)),5),0)} -> 0 | T32: {=IFERROR(MROUND(IFERROR($D$32/SUM($D$13:$D$14)*SUM(T13:T14), $I$32/SUM($I$13:$I$14)*SUM(T13:T14)),5),0)} -> 0 | ... AL32: {=IFERROR(MROUND(IFERROR($D$32/SUM($D$13:$D$14)*SUM(AL13:AL14), $I$32/SUM($I$13:$I$14)*SUM(AL13:AL14)),5),0)} -> 0 | AM32: =W32 -> 0
A33: 25 | B33: 25 to 34 | D33: #N/A | I33: #N/A | J33: =(M33-I33)/4+I33 -> #N/A | K33: =(M33-I33)/4+J33 -> #N/A | L33: =(M33-I33)/4+K33 -> #N/A | M33: {=IFERROR(MROUND(IFERROR($D$33/SUM($D$15:$D$16)*SUM(M15:M16), $I$33/SUM($I$15:$I$16)*SUM(M15:M16)),5),0)} -> 0 | N33: {=IFERROR(MROUND(IFERROR($D$33/SUM($D$15:$D$16)*SUM(N15:N16), $I$33/SUM($I$15:$I$16)*SUM(N15:N16)),5),0)} -> 0 | O33: {=IFERROR(MROUND(IFERROR($D$33/SUM($D$15:$D$16)*SUM(O15:O16), $I$33/SUM($I$15:$I$16)*SUM(O15:O16)),5),0)} -> 0 | P33: {=IFERROR(MROUND(IFERROR($D$33/SUM($D$15:$D$16)*SUM(P15:P16), $I$33/SUM($I$15:$I$16)*SUM(P15:P16)),5),0)} -> 0 | Q33: {=IFERROR(MROUND(IFERROR($D$33/SUM($D$15:$D$16)*SUM(Q15:Q16), $I$33/SUM($I$15:$I$16)*SUM(Q15:Q16)),5),0)} -> 0 | R33: {=IFERROR(MROUND(IFERROR($D$33/SUM($D$15:$D$16)*SUM(R15:R16), $I$33/SUM($I$15:$I$16)*SUM(R15:R16)),5),0)} -> 0 | S33: {=IFERROR(MROUND(IFERROR($D$33/SUM($D$15:$D$16)*SUM(S15:S16), $I$33/SUM($I$15:$I$16)*SUM(S15:S16)),5),0)} -> 0 | T33: {=IFERROR(MROUND(IFERROR($D$33/SUM($D$15:$D$16)*SUM(T15:T16), $I$33/SUM($I$15:$I$16)*SUM(T15:T16)),5),0)} -> 0 | ... AL33: {=IFERROR(MROUND(IFERROR($D$33/SUM($D$15:$D$16)*SUM(AL15:AL16), $I$33/SUM($I$15:$I$16)*SUM(AL15:AL16)),5),0)} -> 0 | AM33: =AM32+W33 -> 0
A34: 35 | B34: 35 to 44 | D34: #N/A | I34: #N/A | J34: =(M34-I34)/4+I34 -> #N/A | K34: =(M34-I34)/4+J34 -> #N/A | L34: =(M34-I34)/4+K34 -> #N/A | M34: {=IFERROR(MROUND(IFERROR($D$34/SUM($D$17:$D$18)*SUM(M17:M18), $I$34/SUM($I$17:$I$18)*SUM(M17:M18)),5),0)} -> 0 | N34: {=IFERROR(MROUND(IFERROR($D$34/SUM($D$17:$D$18)*SUM(N17:N18), $I$34/SUM($I$17:$I$18)*SUM(N17:N18)),5),0)} -> 0 | O34: {=IFERROR(MROUND(IFERROR($D$34/SUM($D$17:$D$18)*SUM(O17:O18), $I$34/SUM($I$17:$I$18)*SUM(O17:O18)),5),0)} -> 0 | P34: {=IFERROR(MROUND(IFERROR($D$34/SUM($D$17:$D$18)*SUM(P17:P18), $I$34/SUM($I$17:$I$18)*SUM(P17:P18)),5),0)} -> 0 | Q34: {=IFERROR(MROUND(IFERROR($D$34/SUM($D$17:$D$18)*SUM(Q17:Q18), $I$34/SUM($I$17:$I$18)*SUM(Q17:Q18)),5),0)} -> 0 | R34: {=IFERROR(MROUND(IFERROR($D$34/SUM($D$17:$D$18)*SUM(R17:R18), $I$34/SUM($I$17:$I$18)*SUM(R17:R18)),5),0)} -> 0 | S34: {=IFERROR(MROUND(IFERROR($D$34/SUM($D$17:$D$18)*SUM(S17:S18), $I$34/SUM($I$17:$I$18)*SUM(S17:S18)),5),0)} -> 0 | T34: {=IFERROR(MROUND(IFERROR($D$34/SUM($D$17:$D$18)*SUM(T17:T18), $I$34/SUM($I$17:$I$18)*SUM(T17:T18)),5),0)} -> 0 | ... AL34: {=IFERROR(MROUND(IFERROR($D$34/SUM($D$17:$D$18)*SUM(AL17:AL18), $I$34/SUM($I$17:$I$18)*SUM(AL17:AL18)),5),0)} -> 0 | AM34: =AM33+W34 -> 0
A35: 45 | B35: 45 to 54 | D35: #N/A | I35: #N/A | J35: =(M35-I35)/4+I35 -> #N/A | K35: =(M35-I35)/4+J35 -> #N/A | L35: =(M35-I35)/4+K35 -> #N/A | M35: {=IFERROR(MROUND(IFERROR($D$35/SUM($D$19:$D$20)*SUM(M19:M20), $I$35/SUM($I$19:$I$20)*SUM(M19:M20)),5),0)} -> 0 | N35: {=IFERROR(MROUND(IFERROR($D$35/SUM($D$19:$D$20)*SUM(N19:N20), $I$35/SUM($I$19:$I$20)*SUM(N19:N20)),5),0)} -> 0 | O35: {=IFERROR(MROUND(IFERROR($D$35/SUM($D$19:$D$20)*SUM(O19:O20), $I$35/SUM($I$19:$I$20)*SUM(O19:O20)),5),0)} -> 0 | P35: {=IFERROR(MROUND(IFERROR($D$35/SUM($D$19:$D$20)*SUM(P19:P20), $I$35/SUM($I$19:$I$20)*SUM(P19:P20)),5),0)} -> 0 | Q35: {=IFERROR(MROUND(IFERROR($D$35/SUM($D$19:$D$20)*SUM(Q19:Q20), $I$35/SUM($I$19:$I$20)*SUM(Q19:Q20)),5),0)} -> 0 | R35: {=IFERROR(MROUND(IFERROR($D$35/SUM($D$19:$D$20)*SUM(R19:R20), $I$35/SUM($I$19:$I$20)*SUM(R19:R20)),5),0)} -> 0 | S35: {=IFERROR(MROUND(IFERROR($D$35/SUM($D$19:$D$20)*SUM(S19:S20), $I$35/SUM($I$19:$I$20)*SUM(S19:S20)),5),0)} -> 0 | T35: {=IFERROR(MROUND(IFERROR($D$35/SUM($D$19:$D$20)*SUM(T19:T20), $I$35/SUM($I$19:$I$20)*SUM(T19:T20)),5),0)} -> 0 | ... AL35: {=IFERROR(MROUND(IFERROR($D$35/SUM($D$19:$D$20)*SUM(AL19:AL20), $I$35/SUM($I$19:$I$20)*SUM(AL19:AL20)),5),0)} -> 0 | AM35: =AM34+W35 -> 0
A36: 55 | B36: 55 to 64 | D36: #N/A | I36: #N/A | J36: =(M36-I36)/4+I36 -> #N/A | K36: =(M36-I36)/4+J36 -> #N/A | L36: =(M36-I36)/4+K36 -> #N/A | M36: {=IFERROR(MROUND(IFERROR($D$36/SUM($D$21:$D$22)*SUM(M21:M22), $I$36/SUM($I$21:$I$22)*SUM(M21:M22)),5),0)} -> 0 | N36: {=IFERROR(MROUND(IFERROR($D$36/SUM($D$21:$D$22)*SUM(N21:N22), $I$36/SUM($I$21:$I$22)*SUM(N21:N22)),5),0)} -> 0 | O36: {=IFERROR(MROUND(IFERROR($D$36/SUM($D$21:$D$22)*SUM(O21:O22), $I$36/SUM($I$21:$I$22)*SUM(O21:O22)),5),0)} -> 0 | P36: {=IFERROR(MROUND(IFERROR($D$36/SUM($D$21:$D$22)*SUM(P21:P22), $I$36/SUM($I$21:$I$22)*SUM(P21:P22)),5),0)} -> 0 | Q36: {=IFERROR(MROUND(IFERROR($D$36/SUM($D$21:$D$22)*SUM(Q21:Q22), $I$36/SUM($I$21:$I$22)*SUM(Q21:Q22)),5),0)} -> 0 | R36: {=IFERROR(MROUND(IFERROR($D$36/SUM($D$21:$D$22)*SUM(R21:R22), $I$36/SUM($I$21:$I$22)*SUM(R21:R22)),5),0)} -> 0 | S36: {=IFERROR(MROUND(IFERROR($D$36/SUM($D$21:$D$22)*SUM(S21:S22), $I$36/SUM($I$21:$I$22)*SUM(S21:S22)),5),0)} -> 0 | T36: {=IFERROR(MROUND(IFERROR($D$36/SUM($D$21:$D$22)*SUM(T21:T22), $I$36/SUM($I$21:$I$22)*SUM(T21:T22)),5),0)} -> 0 | ... AL36: {=IFERROR(MROUND(IFERROR($D$36/SUM($D$21:$D$22)*SUM(AL21:AL22), $I$36/SUM($I$21:$I$22)*SUM(AL21:AL22)),5),0)} -> 0 | AM36: =AM35+W36 -> 0
A37: 65 | B37: 65 to 74 | D37: #N/A | I37: #N/A | J37: =(M37-I37)/4+I37 -> #N/A | K37: =(M37-I37)/4+J37 -> #N/A | L37: =(M37-I37)/4+K37 -> #N/A | M37: {=IFERROR(MROUND(IFERROR($D$37/SUM($D$23:$D$24)*SUM(M23:M24), $I$37/SUM($I$23:$I$24)*SUM(M23:M24)),5),0)} -> 0 | N37: {=IFERROR(MROUND(IFERROR($D$37/SUM($D$23:$D$24)*SUM(N23:N24), $I$37/SUM($I$23:$I$24)*SUM(N23:N24)),5),0)} -> 0 | O37: {=IFERROR(MROUND(IFERROR($D$37/SUM($D$23:$D$24)*SUM(O23:O24), $I$37/SUM($I$23:$I$24)*SUM(O23:O24)),5),0)} -> 0 | P37: {=IFERROR(MROUND(IFERROR($D$37/SUM($D$23:$D$24)*SUM(P23:P24), $I$37/SUM($I$23:$I$24)*SUM(P23:P24)),5),0)} -> 0 | Q37: {=IFERROR(MROUND(IFERROR($D$37/SUM($D$23:$D$24)*SUM(Q23:Q24), $I$37/SUM($I$23:$I$24)*SUM(Q23:Q24)),5),0)} -> 0 | R37: {=IFERROR(MROUND(IFERROR($D$37/SUM($D$23:$D$24)*SUM(R23:R24), $I$37/SUM($I$23:$I$24)*SUM(R23:R24)),5),0)} -> 0 | S37: {=IFERROR(MROUND(IFERROR($D$37/SUM($D$23:$D$24)*SUM(S23:S24), $I$37/SUM($I$23:$I$24)*SUM(S23:S24)),5),0)} -> 0 | T37: {=IFERROR(MROUND(IFERROR($D$37/SUM($D$23:$D$24)*SUM(T23:T24), $I$37/SUM($I$23:$I$24)*SUM(T23:T24)),5),0)} -> 0 | ... AL37: {=IFERROR(MROUND(IFERROR($D$37/SUM($D$23:$D$24)*SUM(AL23:AL24), $I$37/SUM($I$23:$I$24)*SUM(AL23:AL24)),5),0)} -> 0 | AM37: =AM36+W37 -> 0 | AO37: =SUMPRODUCT(I32:I39,A32:A39+4.5) / SUM(I32:I39) -> #N/A
A38: 75 | B38: 75 to 84 | D38: #N/A | I38: #N/A | J38: =(M38-I38)/4+I38 -> #N/A | K38: =(M38-I38)/4+J38 -> #N/A | L38: =(M38-I38)/4+K38 -> #N/A | M38: {=IFERROR(MROUND(IFERROR($D$37/SUM($D$25:$D$26)*SUM(M25:M26), $I$37/SUM($I$25:$I$26)*SUM(M25:M26)),5),0)} -> 0 | N38: {=IFERROR(MROUND(IFERROR($D$37/SUM($D$25:$D$26)*SUM(N25:N26), $I$37/SUM($I$25:$I$26)*SUM(N25:N26)),5),0)} -> 0 | O38: {=IFERROR(MROUND(IFERROR($D$37/SUM($D$25:$D$26)*SUM(O25:O26), $I$37/SUM($I$25:$I$26)*SUM(O25:O26)),5),0)} -> 0 | P38: {=IFERROR(MROUND(IFERROR($D$37/SUM($D$25:$D$26)*SUM(P25:P26), $I$37/SUM($I$25:$I$26)*SUM(P25:P26)),5),0)} -> 0 | Q38: {=IFERROR(MROUND(IFERROR($D$37/SUM($D$25:$D$26)*SUM(Q25:Q26), $I$37/SUM($I$25:$I$26)*SUM(Q25:Q26)),5),0)} -> 0 | R38: {=IFERROR(MROUND(IFERROR($D$37/SUM($D$25:$D$26)*SUM(R25:R26), $I$37/SUM($I$25:$I$26)*SUM(R25:R26)),5),0)} -> 0 | S38: {=IFERROR(MROUND(IFERROR($D$37/SUM($D$25:$D$26)*SUM(S25:S26), $I$37/SUM($I$25:$I$26)*SUM(S25:S26)),5),0)} -> 0 | T38: {=IFERROR(MROUND(IFERROR($D$37/SUM($D$25:$D$26)*SUM(T25:T26), $I$37/SUM($I$25:$I$26)*SUM(T25:T26)),5),0)} -> 0 | ... AL38: {=IFERROR(MROUND(IFERROR($D$37/SUM($D$25:$D$26)*SUM(AL25:AL26), $I$37/SUM($I$25:$I$26)*SUM(AL25:AL26)),5),0)} -> 0 | AM38: =AM37+W38 -> 0 | AO38: =AO39+10*(AM40-AN39)/(AN40-AN39) -> #DIV/0!
A39: 85 | B39: 85+ | D39: #N/A | I39: #N/A | J39: =(M39-I39)/4+I39 -> #N/A | K39: =(M39-I39)/4+J39 -> #N/A | L39: =(M39-I39)/4+K39 -> #N/A | M39: {=IFERROR(MROUND(IFERROR($D$39/SUM($D$27)*SUM(M27), $I$39/SUM($I$27)*SUM(M27)),5),0)} -> 0 | N39: {=IFERROR(MROUND(IFERROR($D$39/SUM($D$27)*SUM(N27), $I$39/SUM($I$27)*SUM(N27)),5),0)} -> 0 | O39: {=IFERROR(MROUND(IFERROR($D$39/SUM($D$27)*SUM(O27), $I$39/SUM($I$27)*SUM(O27)),5),0)} -> 0 | P39: {=IFERROR(MROUND(IFERROR($D$39/SUM($D$27)*SUM(P27), $I$39/SUM($I$27)*SUM(P27)),5),0)} -> 0 | Q39: {=IFERROR(MROUND(IFERROR($D$39/SUM($D$27)*SUM(Q27), $I$39/SUM($I$27)*SUM(Q27)),5),0)} -> 0 | R39: {=IFERROR(MROUND(IFERROR($D$39/SUM($D$27)*SUM(R27), $I$39/SUM($I$27)*SUM(R27)),5),0)} -> 0 | S39: {=IFERROR(MROUND(IFERROR($D$39/SUM($D$27)*SUM(S27), $I$39/SUM($I$27)*SUM(S27)),5),0)} -> 0 | T39: {=IFERROR(MROUND(IFERROR($D$39/SUM($D$27)*SUM(T27), $I$39/SUM($I$27)*SUM(T27)),5),0)} -> 0 | ... AL39: {=IFERROR(MROUND(IFERROR($D$39/SUM($D$27)*SUM(AL27), $I$39/SUM($I$27)*SUM(AL27)),5),0)} -> 0 | AM39: =AM38+W39 -> 0 | AN39: =INDEX($AM$32:$AM$39,MATCH(AN40,AM32:AM39,0)-1,0) -> 0 | AO39: =INDEX(A32:A39,MATCH(AN39,AM32:AM39,0),0)+10 -> 25
B40: Estimated dwellings | I40: =dwell!$N$17 -> #N/A | J40: =MROUND($I$40/$I$31*J31,5) -> #N/A | K40: =MROUND($I$40/$I$31*K31,5) -> #N/A | L40: =MROUND($I$40/$I$31*L31,5) -> #N/A | M40: =MROUND($I$40/$I$31*M31,5) -> #N/A | N40: =MROUND($I$40/$I$31*N31,5) -> #N/A | O40: =MROUND($I$40/$I$31*O31,5) -> #N/A | P40: =MROUND($I$40/$I$31*P31,5) -> #N/A | Q40: =MROUND($I$40/$I$31*Q31,5) -> #N/A | ... AL40: =MROUND($I$40/$I$31*AL31,5) -> #N/A | AM40: =AM39/2 -> 0 | AN40: =_xlfn.MINIFS(AM32:AM39,AM32:AM39,">"&AM40) -> 0 | AO40: =AO39+9 -> 34
B44: SHORTAGE
B46: SUPPRESSED HOUSEHOLDS | J46: VACANCY | Q46: UNHOUSED | T46: EXTREME CORE HOUSING NEED
C48: 2021 household formation | E48: Suppressed households | G48: sum | H48: value | L48: vacancy | M48: RHH% | N48: RHHs | O48: 2025e | R48: 2025 | V48: CSD | W48: CD | X48: PR | Y48: 2025e
B49: Age group | C49: Actual | D49: Expected* | G49: All | H49: =E50 -> x | J49: Target vacancy | L49: 0.03 | M49: =dwell!E102 -> x | N49: =ROUND(M49*M31,0) -> #VALUE! | O49: =ROUND(N49/(1-L49),0) -> #VALUE! | Q49: Total CD | R49: =INDEX(df_unhoused!$B$2:$B$100, MATCH($B$2, df_unhoused!$A$2:$A$100, 0), 0) -> #N/A | T49: Examined HHs | V49: {=need!D95:D96} -> 0 | W49: {=need!E95:E96} -> 0 | X49: {=need!F95:F96} -> 0 | Y49: =M31 -> 0
B50: Total | C50: {=hh!E88:G96} -> x | D50: 0 | E50: x | G50: Positive | H50: =SUMIF(E51:E58,">"&0) -> 0 | J50: Local vacancy | L50: =IF(rental!D34 = "x",rental!F34,rental!D34) -> x | M50: =M49 -> x | N50: =N49 -> #VALUE! | O50: =ROUND(N50/(1-L50),0) -> #VALUE! | Q50: Estimate CSD | R50: =ROUND(R49*popn_now!L12/popn_now!N12,0) -> #N/A | T50: ECHN | V50: 0 | W50: 0 | X50: 0 | Y50: =ROUND(Y49*Y51,0) -> #DIV/0!
A51: 0 | B51: 15 to 24 | C51: x | D51: x | E51: x | G51: Negative | H51: =SUMIF(E51:E58,"<"&0) -> 0 | J51: Total | O51: =O49-O50 -> #VALUE! | T51: Rate | V51: =V50/V49 -> #DIV/0! | W51: =W50/W49 -> #DIV/0! | X51: =X50/X49 -> #DIV/0! | Y51: =IFERROR(IF(V51=0,AVERAGE(W51:X51),V51),AVERAGE(W51:X51)) -> #DIV/0!
A52: 1 | B52: 25 to 34 | C52: x | D52: x | E52: x
A53: 2 | B53: 35 to 44 | C53: x | D53: x | E53: x
A54: 3 | B54: 45 to 54 | C54: x | D54: x | E54: x
A55: 4 | B55: 55 to 64 | C55: x | D55: x | E55: x
A56: 5 | B56: 65 to 74 | C56: x | D56: x | E56: x
A57: 6 | B57: 75 to 84 | C57: x | D57: x | E57: x
B58: 85+ | C58: x | D58: x | E58: x
B62: BRIEF PROJECTION SUMMARY
B64: SHORTAGE SUMMARY | F64: HH --> DWELLING | J64: ANTICIPATED NEED
B65: Item | C65: Value | D65: Adj | H65: 2021 | K65: 2021 | L65: 2025 | M65: '21-'25 | N65: 2035 | O65: 2045 | P65: 25-'35 | Q65: '25-'45
B66: Suppressed 2021 | C66: =IF(H50 >0, H50, 0) -> 0 | D66: =MROUND(C66*$H$68,5) -> #N/A | F66: Total dwellings | H66: =I40 -> #N/A | J66: Households | K66: =I31 -> #N/A | L66: =M31 -> 0 | M66: =L66-K66 -> #N/A | N66: =ROUND(INDEX($M$31:$W$31,0,MATCH($N$65,$M$30:$W$30,0)),0) -> 0 | O66: =ROUND(INDEX($M$31:$AH$31,0,MATCH($O$65,$M$30:$AH$30,0)),0) -> 0 | P66: =N66-L66 -> 0 | Q66: =O66-N66+P66 -> 0
B67: Since 2021 | C67: =M66 -> #N/A | D67: =IFERROR(MROUND(C67*$H$68,5),MROUND(C67*$H$68,-5)) -> #N/A | F67: Usual dwellings | H67: =I31 -> #N/A | J67: Adjusted | M67: =MROUND(M66*$H$68,5) -> #N/A | P67: =MROUND(P66*$H$68,5) -> #N/A | Q67: =MROUND(Q66*$H$68,5) -> #N/A
B68: Vacancy | C68: =IF(O51>0,O51,0) -> #VALUE! | D68: =MROUND(C68*$H$68,5) -> #VALUE! | F68: Usual / total | H68: =H66/H67 -> #N/A
B69: Unhoused | C69: =IFERROR(R50,0) -> 0 | D69: =MROUND(C69*$H$68,5) -> #N/A
B70: ECHN | C70: =MROUND(Y50,5) -> #DIV/0! | D70: =MROUND(C70*$H$68,5) -> #DIV/0!
B71: LESS: Built | C71: =IF(MROUND(D71/H68,5) < 1, MROUND(dwell!C58/5 * (L65-K65), 5), MROUND(D71/H68,5)) -> #N/A | D71: =IF(MROUND(AVERAGE(dwell!$C$17:$H$17) * (L65-K65),5) < 5, MROUND(dwell!C58/5 * (L65-K65) * H68, 5), MROUND(AVERAGE(dwell!$C$17:$H$17) * (L65-K65),5)) -> #N/A
B72: Total | C72: =SUM(C66:C69)-C71 -> #N/A | D72: =SUM(D66:D69)-D71 -> #N/A
B76: CHANGE IN SUPPLY OVER TIME
B78: Variable | D78: 2021 | E78: 2022 | F78: 2023 | G78: 2024 | H78: 2025 | I78: 2026 | J78: 2027 | K78: 2028 | L78: 2029 | M78: 2030 | N78: 2031 | O78: 2032 | P78: 2033 | Q78: 2034 | R78: 2035 | S78: 2036 | T78: 2037 | U78: 2038 | V78: 2039 | W78: 2040
B79: Total household demand | D79: =I31 -> #N/A | E79: =J31 -> #N/A | F79: =K31 -> #N/A | G79: =L31 -> #N/A | H79: =M31 -> 0 | I79: =N31 -> 0 | J79: =O31 -> 0 | K79: =P31 -> 0 | ... W79: =AB31 -> 0
B80: Total dwelling demand | D80: =I40 -> #N/A | E80: =J40 -> #N/A | F80: =K40 -> #N/A | G80: =L40 -> #N/A | H80: =M40 -> #N/A | I80: =N40 -> #N/A | J80: =O40 -> #N/A | K80: =P40 -> #N/A | ... W80: =AB40 -> #N/A
B81: Year over year demand | I81: =I80-H80 -> #N/A | J81: =J80-I80 -> #N/A | K81: =K80-J80 -> #N/A | L81: =L80-K80 -> #N/A | M81: =M80-L80 -> #N/A | N81: =N80-M80 -> #N/A | O81: =O80-N80 -> #N/A | P81: =P80-O80 -> #N/A | ... W81: =W80-V80 -> #N/A
B82: Cumulative new demand since 2025 | H82: 0 | I82: =H82+I81 -> #N/A | J82: =I82+J81 -> #N/A | K82: =J82+K81 -> #N/A | L82: =K82+L81 -> #N/A | M82: =L82+M81 -> #N/A | N82: =M82+N81 -> #N/A | O82: =N82+O81 -> #N/A | P82: =O82+P81 -> #N/A | ... W82: =V82+W81 -> #N/A
B83: Estimated 2025 shortage | H83: =D72 -> #N/A | I83: =H83 -> #N/A | J83: =I83 -> #N/A | K83: =J83 -> #N/A | L83: =K83 -> #N/A | M83: =L83 -> #N/A | N83: =M83 -> #N/A | O83: =N83 -> #N/A | P83: =O83 -> #N/A | ... W83: =V83 -> #N/A
B84: Cumulative new demand since 2025 + 2025 shortage | H84: =SUM(H82,H83) -> #N/A | I84: =SUM(I82,I83) -> #N/A | J84: =SUM(J82,J83) -> #N/A | K84: =SUM(K82,K83) -> #N/A | L84: =SUM(L82,L83) -> #N/A | M84: =SUM(M82,M83) -> #N/A | N84: =SUM(N82,N83) -> #N/A | O84: =SUM(O82,O83) -> #N/A | ... W84: =SUM(W82,W83) -> #N/A
B85: Anticipated annual construction | I85: =MROUND(AVERAGE(dwell!$C$17:$H$17),5) -> 0 | J85: =MROUND(AVERAGE(dwell!$C$17:$H$17),5) -> 0 | K85: =MROUND(AVERAGE(dwell!$C$17:$H$17),5) -> 0 | L85: =MROUND(AVERAGE(dwell!$C$17:$H$17),5) -> 0 | M85: =MROUND(AVERAGE(dwell!$C$17:$H$17),5) -> 0 | N85: =MROUND(AVERAGE(dwell!$C$17:$H$17),5) -> 0 | O85: =MROUND(AVERAGE(dwell!$C$17:$H$17),5) -> 0 | P85: =MROUND(AVERAGE(dwell!$C$17:$H$17),5) -> 0 | ... W85: =MROUND(AVERAGE(dwell!$C$17:$H$17),5) -> 0
B86: Cumulative construction | I86: =I85+H86 -> 0 | J86: =J85+I86 -> 0 | K86: =K85+J86 -> 0 | L86: =L85+K86 -> 0 | M86: =M85+L86 -> 0 | N86: =N85+M86 -> 0 | O86: =O85+N86 -> 0 | P86: =P85+O86 -> 0 | ... W86: =W85+V86 -> 0
B87: Running shortage (total demand minus cumulative supply) | H87: =H84-H86 -> #N/A | I87: =I84-I86 -> #N/A | J87: =J84-J86 -> #N/A | K87: =K84-K86 -> #N/A | L87: =L84-L86 -> #N/A | M87: =M84-M86 -> #N/A | N87: =N84-N86 -> #N/A | O87: =O84-O86 -> #N/A | ... W87: =W84-W86 -> #N/A
B106: CALCULATION OF FUTURE DEMAND BY CATEGORY
B109: NATIONAL OCCUPANCY STANDARD
B111: A: Maintainer age by bedroom size - as per NOS (based on PUMF data) | I111: B: Anticipated maintainers | Q111: C: Households distributed by number of bedrooms (sum[A x D>]) | Y111: D: Distribution of number of bedrooms
C112: Total | D112: 0 / 1 bed | E112: 2 bed | F112: 3 bed | G112: 4+ bed | J112: 2021 | K112: 2025 | L112: =K112+5 -> 2030 | M112: =L112+5 -> 2035 | N112: =M112+5 -> 2040 | O112: =N112+5 -> 2045 | R112: 2021 | S112: {=K112:O112} -> 2025 | T112: 2030 | U112: 2035 | V112: 2040 | W112: 2045 | Z112: =R112 -> 2021 | AA112: =S112 -> 2025 | AB112: =T112 -> 2030 | AC112: =U112 -> 2035 | AD112: =V112 -> 2040 | AE112: =W112 -> 2045
B113: Total | C113: {=nos!K3:O10} -> 303917.94 | D113: 209184.69 | E113: 45570.736 | F113: 26627.55 | G113: 22349.742 | I113: Total households | J113: {=IFERROR(INDEX($C$31:$AF$38,MATCH($I113,$B$31:$B$38,0),MATCH(J$112,$C$30:$AF$30,0)),SUM(J114:J120))} -> 0 | K113: {=IFERROR(INDEX($C$31:$AF$38,MATCH($I113,$B$31:$B$38,0),MATCH(K$112,$C$30:$AF$30,0)),SUM(K114:K120))} -> 0 | L113: {=IFERROR(INDEX($C$31:$AF$38,MATCH($I113,$B$31:$B$38,0),MATCH(L$112,$C$30:$AF$30,0)),SUM(L114:L120))} -> 0 | M113: {=IFERROR(INDEX($C$31:$AF$38,MATCH($I113,$B$31:$B$38,0),MATCH(M$112,$C$30:$AF$30,0)),SUM(M114:M120))} -> 0 | N113: {=IFERROR(INDEX($C$31:$AF$38,MATCH($I113,$B$31:$B$38,0),MATCH(N$112,$C$30:$AF$30,0)),SUM(N114:N120))} -> 0 | O113: {=IFERROR(INDEX($C$31:$AF$38,MATCH($I113,$B$31:$B$38,0),MATCH(O$112,$C$30:$AF$30,0)),SUM(O114:O120))} -> 0 | Q113: 0-/1-bed | R113: {=SUMPRODUCT($D$124:$D$130,J$114:J$120)} -> 0 | S113: {=SUMPRODUCT($D$124:$D$130,K$114:K$120)} -> 0 | T113: {=SUMPRODUCT($D$124:$D$130,L$114:L$120)} -> 0 | U113: {=SUMPRODUCT($D$124:$D$130,M$114:M$120)} -> 0 | V113: {=SUMPRODUCT($D$124:$D$130,N$114:N$120)} -> 0 | W113: {=SUMPRODUCT($D$124:$D$130,O$114:O$120)} -> 0 | Y113: 0- / 1-bed | Z113: =R113/SUM(R$113:R$116) -> #DIV/0! | AA113: =S113/SUM(S$113:S$116) -> #DIV/0! | AB113: =T113/SUM(T$113:T$116) -> #DIV/0! | AC113: =U113/SUM(U$113:U$116) -> #DIV/0! | AD113: =V113/SUM(V$113:V$116) -> #DIV/0! | AE113: =W113/SUM(W$113:W$116) -> #DIV/0!
B114: 15-24 | C114: 10036.324 | D114: 5055.2067 | E114: 2758.8898 | F114: 1425.8923 | G114: 722.26248 | I114: 15 to 24 | J114: {=IFERROR(INDEX($C$31:$AF$38,MATCH($I114,$B$31:$B$38,0),MATCH(J$112,$C$30:$AF$30,0)),0)} -> 0 | K114: {=IFERROR(INDEX($C$31:$AF$38,MATCH($I114,$B$31:$B$38,0),MATCH(K$112,$C$30:$AF$30,0)),0)} -> 0 | L114: {=IFERROR(INDEX($C$31:$AF$38,MATCH($I114,$B$31:$B$38,0),MATCH(L$112,$C$30:$AF$30,0)),0)} -> 0 | M114: {=IFERROR(INDEX($C$31:$AF$38,MATCH($I114,$B$31:$B$38,0),MATCH(M$112,$C$30:$AF$30,0)),0)} -> 0 | N114: {=IFERROR(INDEX($C$31:$AF$38,MATCH($I114,$B$31:$B$38,0),MATCH(N$112,$C$30:$AF$30,0)),0)} -> 0 | O114: {=IFERROR(INDEX($C$31:$AL$38,MATCH($I114,$B$31:$B$38,0),MATCH(O$112,$C$30:$AL$30,0)),0)} -> 0 | Q114: 2-bed | R114: {=SUMPRODUCT($E$124:$E$130,J$114:J$120)} -> 0 | S114: {=SUMPRODUCT($E$124:$E$130,K$114:K$120)} -> 0 | T114: {=SUMPRODUCT($E$124:$E$130,L$114:L$120)} -> 0 | U114: {=SUMPRODUCT($E$124:$E$130,M$114:M$120)} -> 0 | V114: {=SUMPRODUCT($E$124:$E$130,N$114:N$120)} -> 0 | W114: {=SUMPRODUCT($E$124:$E$130,O$114:O$120)} -> 0 | Y114: 2-bed | Z114: =R114/SUM(R$113:R$116) -> #DIV/0! | AA114: =S114/SUM(S$113:S$116) -> #DIV/0! | AB114: =T114/SUM(T$113:T$116) -> #DIV/0! | AC114: =U114/SUM(U$113:U$116) -> #DIV/0! | AD114: =V114/SUM(V$113:V$116) -> #DIV/0! | AE114: =W114/SUM(W$113:W$116) -> #DIV/0!
B115: 25-34 | C115: 31517.223 | D115: 13481.451 | E115: 6092.0679 | F115: 5814.6039 | G115: 6129.0999 | I115: 25 to 34 | J115: {=IFERROR(INDEX($C$31:$AF$38,MATCH($I115,$B$31:$B$38,0),MATCH(J$112,$C$30:$AF$30,0)),0)} -> 0 | K115: {=IFERROR(INDEX($C$31:$AF$38,MATCH($I115,$B$31:$B$38,0),MATCH(K$112,$C$30:$AF$30,0)),0)} -> 0 | L115: {=IFERROR(INDEX($C$31:$AF$38,MATCH($I115,$B$31:$B$38,0),MATCH(L$112,$C$30:$AF$30,0)),0)} -> 0 | M115: {=IFERROR(INDEX($C$31:$AF$38,MATCH($I115,$B$31:$B$38,0),MATCH(M$112,$C$30:$AF$30,0)),0)} -> 0 | N115: {=IFERROR(INDEX($C$31:$AF$38,MATCH($I115,$B$31:$B$38,0),MATCH(N$112,$C$30:$AF$30,0)),0)} -> 0 | O115: {=IFERROR(INDEX($C$31:$AL$38,MATCH($I115,$B$31:$B$38,0),MATCH(O$112,$C$30:$AL$30,0)),0)} -> 0 | Q115: 3-bed | R115: {=SUMPRODUCT($F$124:$F$130,J$114:J$120)} -> 0 | S115: {=SUMPRODUCT($F$124:$F$130,K$114:K$120)} -> 0 | T115: {=SUMPRODUCT($F$124:$F$130,L$114:L$120)} -> 0 | U115: {=SUMPRODUCT($F$124:$F$130,M$114:M$120)} -> 0 | V115: {=SUMPRODUCT($F$124:$F$130,N$114:N$120)} -> 0 | W115: {=SUMPRODUCT($F$124:$F$130,O$114:O$120)} -> 0 | Y115: 3-bed | Z115: =R115/SUM(R$113:R$116) -> #DIV/0! | AA115: =S115/SUM(S$113:S$116) -> #DIV/0! | AB115: =T115/SUM(T$113:T$116) -> #DIV/0! | AC115: =U115/SUM(U$113:U$116) -> #DIV/0! | AD115: =V115/SUM(V$113:V$116) -> #DIV/0! | AE115: =W115/SUM(W$113:W$116) -> #DIV/0!
B116: 35-44 | C116: 37961.351 | D116: 15888.8 | E116: 5907.0707 | F116: 7684.8595 | G116: 8443.5537 | I116: 35 to 44 | J116: {=IFERROR(INDEX($C$31:$AF$38,MATCH($I116,$B$31:$B$38,0),MATCH(J$112,$C$30:$AF$30,0)),0)} -> 0 | K116: {=IFERROR(INDEX($C$31:$AF$38,MATCH($I116,$B$31:$B$38,0),MATCH(K$112,$C$30:$AF$30,0)),0)} -> 0 | L116: {=IFERROR(INDEX($C$31:$AF$38,MATCH($I116,$B$31:$B$38,0),MATCH(L$112,$C$30:$AF$30,0)),0)} -> 0 | M116: {=IFERROR(INDEX($C$31:$AF$38,MATCH($I116,$B$31:$B$38,0),MATCH(M$112,$C$30:$AF$30,0)),0)} -> 0 | N116: {=IFERROR(INDEX($C$31:$AF$38,MATCH($I116,$B$31:$B$38,0),MATCH(N$112,$C$30:$AF$30,0)),0)} -> 0 | O116: {=IFERROR(INDEX($C$31:$AL$38,MATCH($I116,$B$31:$B$38,0),MATCH(O$112,$C$30:$AL$30,0)),0)} -> 0 | Q116: 4+ bed | R116: {=SUMPRODUCT($G$124:$G$130,J$114:J$120)} -> 0 | S116: {=SUMPRODUCT($G$124:$G$130,K$114:K$120)} -> 0 | T116: {=SUMPRODUCT($G$124:$G$130,L$114:L$120)} -> 0 | U116: {=SUMPRODUCT($G$124:$G$130,M$114:M$120)} -> 0 | V116: {=SUMPRODUCT($G$124:$G$130,N$114:N$120)} -> 0 | W116: {=SUMPRODUCT($G$124:$G$130,O$114:O$120)} -> 0 | Y116: 4+ bed | Z116: =R116/SUM(R$113:R$116) -> #DIV/0! | AA116: =S116/SUM(S$113:S$116) -> #DIV/0! | AB116: =T116/SUM(T$113:T$116) -> #DIV/0! | AC116: =U116/SUM(U$113:U$116) -> #DIV/0! | AD116: =V116/SUM(V$113:V$116) -> #DIV/0! | AE116: =W116/SUM(W$113:W$116) -> #DIV/0!
B117: 45-54 | C117: 42665.52 | D117: 24111.998 | E117: 7962.4451 | F117: 5721.338 | G117: 4869.7389 | I117: 45 to 54 | J117: {=IFERROR(INDEX($C$31:$AF$38,MATCH($I117,$B$31:$B$38,0),MATCH(J$112,$C$30:$AF$30,0)),0)} -> 0 | K117: {=IFERROR(INDEX($C$31:$AF$38,MATCH($I117,$B$31:$B$38,0),MATCH(K$112,$C$30:$AF$30,0)),0)} -> 0 | L117: {=IFERROR(INDEX($C$31:$AF$38,MATCH($I117,$B$31:$B$38,0),MATCH(L$112,$C$30:$AF$30,0)),0)} -> 0 | M117: {=IFERROR(INDEX($C$31:$AF$38,MATCH($I117,$B$31:$B$38,0),MATCH(M$112,$C$30:$AF$30,0)),0)} -> 0 | N117: {=IFERROR(INDEX($C$31:$AF$38,MATCH($I117,$B$31:$B$38,0),MATCH(N$112,$C$30:$AF$30,0)),0)} -> 0 | O117: {=IFERROR(INDEX($C$31:$AL$38,MATCH($I117,$B$31:$B$38,0),MATCH(O$112,$C$30:$AL$30,0)),0)} -> 0
B118: 55-64 | C118: 76555.146 | D118: 59926.879 | E118: 11591.785 | F118: 3536.6124 | G118: 1462.8509 | I118: 55 to 64 | J118: {=IFERROR(INDEX($C$31:$AF$38,MATCH($I118,$B$31:$B$38,0),MATCH(J$112,$C$30:$AF$30,0)),0)} -> 0 | K118: {=IFERROR(INDEX($C$31:$AF$38,MATCH($I118,$B$31:$B$38,0),MATCH(K$112,$C$30:$AF$30,0)),0)} -> 0 | L118: {=IFERROR(INDEX($C$31:$AF$38,MATCH($I118,$B$31:$B$38,0),MATCH(L$112,$C$30:$AF$30,0)),0)} -> 0 | M118: {=IFERROR(INDEX($C$31:$AF$38,MATCH($I118,$B$31:$B$38,0),MATCH(M$112,$C$30:$AF$30,0)),0)} -> 0 | N118: {=IFERROR(INDEX($C$31:$AF$38,MATCH($I118,$B$31:$B$38,0),MATCH(N$112,$C$30:$AF$30,0)),0)} -> 0 | O118: {=IFERROR(INDEX($C$31:$AL$38,MATCH($I118,$B$31:$B$38,0),MATCH(O$112,$C$30:$AL$30,0)),0)} -> 0
B119: 65-74 | C119: 57591.806 | D119: 48722.067 | E119: 6999.462 | F119: 1314.6907 | G119: 518.52302 | I119: 65 to 74 | J119: {=IFERROR(INDEX($C$31:$AF$38,MATCH($I119,$B$31:$B$38,0),MATCH(J$112,$C$30:$AF$30,0)),0)} -> 0 | K119: {=IFERROR(INDEX($C$31:$AF$38,MATCH($I119,$B$31:$B$38,0),MATCH(K$112,$C$30:$AF$30,0)),0)} -> 0 | L119: {=IFERROR(INDEX($C$31:$AF$38,MATCH($I119,$B$31:$B$38,0),MATCH(L$112,$C$30:$AF$30,0)),0)} -> 0 | M119: {=IFERROR(INDEX($C$31:$AF$38,MATCH($I119,$B$31:$B$38,0),MATCH(M$112,$C$30:$AF$30,0)),0)} -> 0 | N119: {=IFERROR(INDEX($C$31:$AF$38,MATCH($I119,$B$31:$B$38,0),MATCH(N$112,$C$30:$AF$30,0)),0)} -> 0 | O119: {=IFERROR(INDEX($C$31:$AL$38,MATCH($I119,$B$31:$B$38,0),MATCH(O$112,$C$30:$AL$30,0)),0)} -> 0
B120: 75+ | C120: 47590.57 | D120: 41998.288 | E120: 4259.0163 | F120: 1129.5534 | G120: 203.71309 | I120: 75+ | J120: {=IFERROR(INDEX($C$39:$AL$39,0,MATCH(J$112,$C$30:$AL$30,0))+INDEX($C$38:$AL$38,0,MATCH(J$112,$C$30:$AL$30,0)),0)} -> 0 | K120: {=IFERROR(INDEX($C$39:$AL$39,0,MATCH(K$112,$C$30:$AL$30,0))+INDEX($C$38:$AL$38,0,MATCH(K$112,$C$30:$AL$30,0)),0)} -> 0 | L120: {=IFERROR(INDEX($C$39:$AL$39,0,MATCH(L$112,$C$30:$AL$30,0))+INDEX($C$38:$AL$38,0,MATCH(L$112,$C$30:$AL$30,0)),0)} -> 0 | M120: {=IFERROR(INDEX($C$39:$AL$39,0,MATCH(M$112,$C$30:$AL$30,0))+INDEX($C$38:$AL$38,0,MATCH(M$112,$C$30:$AL$30,0)),0)} -> 0 | N120: {=IFERROR(INDEX($C$39:$AL$39,0,MATCH(N$112,$C$30:$AL$30,0))+INDEX($C$38:$AL$38,0,MATCH(N$112,$C$30:$AL$30,0)),0)} -> 0 | O120: {=IFERROR(INDEX($C$39:$AL$39,0,MATCH(O$112,$C$30:$AL$30,0))+INDEX($C$38:$AL$38,0,MATCH(O$112,$C$30:$AL$30,0)),0)} -> 0
C122: Total | D122: 0 / 1 bed | E122: 2 bed | F122: 3 bed | G122: 4+ bed
B123: Total | C123: =C113 -> 303917.94 | D123: =D113 -> 209184.69 | E123: =E113 -> 45570.736 | F123: =F113 -> 26627.55 | G123: =G113 -> 22349.742
B124: 15-24 | C124: =C114 -> 10036.324 | D124: =D114/$C114 -> 0.50369107 | E124: =E114/$C114 -> 0.27489047 | F124: =F114/$C114 -> 0.14207316 | G124: =G114/$C114 -> 0.071964844
B125: 25-34 | C125: =C115 -> 31517.223 | D125: =D115/$C115 -> 0.4277487 | E125: =E115/$C115 -> 0.1932933 | F125: =F115/$C115 -> 0.18448973 | G125: =G115/$C115 -> 0.19446827
B126: 35-44 | C126: =C116 -> 37961.351 | D126: =D116/$C116 -> 0.41855201 | E126: =E116/$C116 -> 0.15560749 | F126: =F116/$C116 -> 0.20243904 | G126: =G116/$C116 -> 0.222425
B127: 45-54 | C127: =C117 -> 42665.52 | D127: =D117/$C117 -> 0.56514014 | E127: =E117/$C117 -> 0.18662482 | F127: =F117/$C117 -> 0.13409746 | G127: =G117/$C117 -> 0.11413757
B128: 55-64 | C128: =C118 -> 76555.146 | D128: =D118/$C118 -> 0.78279361 | E128: =E118/$C118 -> 0.15141744 | F128: =F118/$C118 -> 0.046196926 | G128: =G118/$C118 -> 0.01910846
B129: 65-74 | C129: =C119 -> 57591.806 | D129: =D119/$C119 -> 0.84598957 | E129: =E119/$C119 -> 0.12153573 | F129: =F119/$C119 -> 0.022827738 | G129: =G119/$C119 -> 0.0090034165
B130: 75+ | C130: =C120 -> 47590.57 | D130: =D120/$C120 -> 0.88249179 | E130: =E120/$C120 -> 0.089492861 | F130: =F120/$C120 -> 0.023734816 | G130: =G120/$C120 -> 0.0042805347
B136: FUTURE BEDROOM (AND TENURE) DEMAND
C137: hh_15_24 | D137: hh_25_34 | E137: hh_35_44 | F137: hh_45_54 | G137: hh_55_64 | H137: hh_65_74 | I137: hh_75
B138: A: Maintainer age by bedroom size (people who moved in last 5 years) | K138: C: Household summary | S138: G: PUMF Owners | AB138: I: Number of owner / renter households (sum[A x Bprev x Dprev])
B139: 2016 | C139: 15 to 24 | D139: 25 to 34 | E139: 35 to 44 | F139: 45 to 54 | G139: 55 to 64 | H139: 65 to 74 | I139: 75+ | L139: {=J112:O112} -> 2021 | M139: 2025 | N139: 2030 | O139: 2035 | P139: 2040 | Q139: 2045 | S139: =B139 -> 2016 | T139: 15 to 24 | U139: 25 to 34 | V139: 35 to 44 | W139: 45 to 54 | X139: 55 to 64 | Y139: 65 to 74 | Z139: 75+ | AB139: Owners | AC139: =L149 -> 2021 | AD139: =M149 -> 2025 | AE139: =N149 -> 2030 | AF139: =O149 -> 2035 | AG139: =P149 -> 2040 | AH139: =Q149 -> 2045
A140: 0 | B140: Studio | C140: {=SUMPRODUCT(dem!$D$2:$J$1000 * ("bedrm" = dem!$K$2:$K$1000) * ($A140 = dem!$A$2:$A$1000) * ($B$139 = dem!$C$2:$C$1000) * (dem!$D$1:$J$1 = projection!C$137))} -> 301.34739 | D140: {=SUMPRODUCT(dem!$D$2:$J$1000 * ("bedrm" = dem!$K$2:$K$1000) * ($A140 = dem!$A$2:$A$1000) * ($B$139 = dem!$C$2:$C$1000) * (dem!$D$1:$J$1 = projection!D$137))} -> 200.55044 | E140: {=SUMPRODUCT(dem!$D$2:$J$1000 * ("bedrm" = dem!$K$2:$K$1000) * ($A140 = dem!$A$2:$A$1000) * ($B$139 = dem!$C$2:$C$1000) * (dem!$D$1:$J$1 = projection!E$137))} -> 301.11001 | F140: {=SUMPRODUCT(dem!$D$2:$J$1000 * ("bedrm" = dem!$K$2:$K$1000) * ($A140 = dem!$A$2:$A$1000) * ($B$139 = dem!$C$2:$C$1000) * (dem!$D$1:$J$1 = projection!F$137))} -> 602.21833 | G140: {=SUMPRODUCT(dem!$D$2:$J$1000 * ("bedrm" = dem!$K$2:$K$1000) * ($A140 = dem!$A$2:$A$1000) * ($B$139 = dem!$C$2:$C$1000) * (dem!$D$1:$J$1 = projection!G$137))} -> 0 | H140: {=SUMPRODUCT(dem!$D$2:$J$1000 * ("bedrm" = dem!$K$2:$K$1000) * ($A140 = dem!$A$2:$A$1000) * ($B$139 = dem!$C$2:$C$1000) * (dem!$D$1:$J$1 = projection!H$137))} -> 100.9437 | I140: {=SUMPRODUCT(dem!$D$2:$J$1000 * ("bedrm" = dem!$K$2:$K$1000) * ($A140 = dem!$A$2:$A$1000) * ($B$139 = dem!$C$2:$C$1000) * (dem!$D$1:$J$1 = projection!I$137))} -> 0 | K140: 15 to 24 | L140: {=J114:O120} -> 0 | M140: 0 | N140: 0 | O140: 0 | P140: 0 | Q140: 0 | S140: Studio | T140: {=IFERROR(INDEX(dem!$D$2:$J$1000, MATCH(1, ($S$139 = dem!$C$2:$C$1000) * (1 = dem!$B$2:$B$1000) * ($A140 = dem!$A$2:$A$1000) * (dem!$K$2:$K$1000 = "bedrm"), 0), MATCH(C$137, dem!$D$1:$J$1,0)),0)} -> 0 | U140: {=IFERROR(INDEX(dem!$D$2:$J$1000, MATCH(1, ($S$139 = dem!$C$2:$C$1000) * (1 = dem!$B$2:$B$1000) * ($A140 = dem!$A$2:$A$1000) * (dem!$K$2:$K$1000 = "bedrm"), 0), MATCH(D$137, dem!$D$1:$J$1,0)),0)} -> 0 | V140: {=IFERROR(INDEX(dem!$D$2:$J$1000, MATCH(1, ($S$139 = dem!$C$2:$C$1000) * (1 = dem!$B$2:$B$1000) * ($A140 = dem!$A$2:$A$1000) * (dem!$K$2:$K$1000 = "bedrm"), 0), MATCH(E$137, dem!$D$1:$J$1,0)),0)} -> 0 | W140: {=IFERROR(INDEX(dem!$D$2:$J$1000, MATCH(1, ($S$139 = dem!$C$2:$C$1000) * (1 = dem!$B$2:$B$1000) * ($A140 = dem!$A$2:$A$1000) * (dem!$K$2:$K$1000 = "bedrm"), 0), MATCH(F$137, dem!$D$1:$J$1,0)),0)} -> 0 | X140: {=IFERROR(INDEX(dem!$D$2:$J$1000, MATCH(1, ($S$139 = dem!$C$2:$C$1000) * (1 = dem!$B$2:$B$1000) * ($A140 = dem!$A$2:$A$1000) * (dem!$K$2:$K$1000 = "bedrm"), 0), MATCH(G$137, dem!$D$1:$J$1,0)),0)} -> 0 | Y140: {=IFERROR(INDEX(dem!$D$2:$J$1000, MATCH(1, ($S$139 = dem!$C$2:$C$1000) * (1 = dem!$B$2:$B$1000) * ($A140 = dem!$A$2:$A$1000) * (dem!$K$2:$K$1000 = "bedrm"), 0), MATCH(H$137, dem!$D$1:$J$1,0)),0)} -> 0 | Z140: {=IFERROR(INDEX(dem!$D$2:$J$1000, MATCH(1, ($S$139 = dem!$C$2:$C$1000) * (1 = dem!$B$2:$B$1000) * ($A140 = dem!$A$2:$A$1000) * (dem!$K$2:$K$1000 = "bedrm"), 0), MATCH(I$137, dem!$D$1:$J$1,0)),0)} -> 0 | AB140: Studio | AC140: {=IF(L150 = 0, 0, SUMPRODUCT($C149:$I149,TRANSPOSE(L$140:L$146), ($T149:$Z149)))} -> 0 | AD140: {=IF(M150 = 0, 0, SUMPRODUCT($C149:$I149,TRANSPOSE(M$140:M$146), ($T149:$Z149)))} -> 0 | AE140: {=IF(N150 = 0, 0, SUMPRODUCT($C149:$I149,TRANSPOSE(N$140:N$146), ($T149:$Z149)))} -> 0 | AF140: {=IF(O150 = 0, 0, SUMPRODUCT($C149:$I149,TRANSPOSE(O$140:O$146), ($T149:$Z149)))} -> 0 | AG140: {=IF(P150 = 0, 0, SUMPRODUCT($C149:$I149,TRANSPOSE(P$140:P$146), ($T149:$Z149)))} -> 0 | AH140: {=IF(Q150 = 0, 0, SUMPRODUCT($C149:$I149,TRANSPOSE(Q$140:Q$146), ($T149:$Z149)))} -> 0
A141: 1 | B141: 1-bed | C141: {=SUMPRODUCT(dem!$D$2:$J$1000 * ("bedrm" = dem!$K$2:$K$1000) * ($A141 = dem!$A$2:$A$1000) * ($B$139 = dem!$C$2:$C$1000) * (dem!$D$1:$J$1 = projection!C$137))} -> 4923.0444 | D141: {=SUMPRODUCT(dem!$D$2:$J$1000 * ("bedrm" = dem!$K$2:$K$1000) * ($A141 = dem!$A$2:$A$1000) * ($B$139 = dem!$C$2:$C$1000) * (dem!$D$1:$J$1 = projection!D$137))} -> 5022.5583 | E141: {=SUMPRODUCT(dem!$D$2:$J$1000 * ("bedrm" = dem!$K$2:$K$1000) * ($A141 = dem!$A$2:$A$1000) * ($B$139 = dem!$C$2:$C$1000) * (dem!$D$1:$J$1 = projection!E$137))} -> 4220 | F141: {=SUMPRODUCT(dem!$D$2:$J$1000 * ("bedrm" = dem!$K$2:$K$1000) * ($A141 = dem!$A$2:$A$1000) * ($B$139 = dem!$C$2:$C$1000) * (dem!$D$1:$J$1 = projection!F$137))} -> 6024.3748 | G141: {=SUMPRODUCT(dem!$D$2:$J$1000 * ("bedrm" = dem!$K$2:$K$1000) * ($A141 = dem!$A$2:$A$1000) * ($B$139 = dem!$C$2:$C$1000) * (dem!$D$1:$J$1 = projection!G$137))} -> 6027.6798 | H141: {=SUMPRODUCT(dem!$D$2:$J$1000 * ("bedrm" = dem!$K$2:$K$1000) * ($A141 = dem!$A$2:$A$1000) * ($B$139 = dem!$C$2:$C$1000) * (dem!$D$1:$J$1 = projection!H$137))} -> 2310.9245 | I141: {=SUMPRODUCT(dem!$D$2:$J$1000 * ("bedrm" = dem!$K$2:$K$1000) * ($A141 = dem!$A$2:$A$1000) * ($B$139 = dem!$C$2:$C$1000) * (dem!$D$1:$J$1 = projection!I$137))} -> 1306.2774 | K141: 25 to 34 | L141: 0 | M141: 0 | N141: 0 | O141: 0 | P141: 0 | Q141: 0 | S141: 1-bed | T141: {=IFERROR(INDEX(dem!$D$2:$J$1000, MATCH(1, ($S$139 = dem!$C$2:$C$1000) * (1 = dem!$B$2:$B$1000) * ($A141 = dem!$A$2:$A$1000) * (dem!$K$2:$K$1000 = "bedrm"), 0), MATCH(C$137, dem!$D$1:$J$1,0)),0)} -> 100.19689 | U141: {=IFERROR(INDEX(dem!$D$2:$J$1000, MATCH(1, ($S$139 = dem!$C$2:$C$1000) * (1 = dem!$B$2:$B$1000) * ($A141 = dem!$A$2:$A$1000) * (dem!$K$2:$K$1000 = "bedrm"), 0), MATCH(D$137, dem!$D$1:$J$1,0)),0)} -> 502.78317 | V141: {=IFERROR(INDEX(dem!$D$2:$J$1000, MATCH(1, ($S$139 = dem!$C$2:$C$1000) * (1 = dem!$B$2:$B$1000) * ($A141 = dem!$A$2:$A$1000) * (dem!$K$2:$K$1000 = "bedrm"), 0), MATCH(E$137, dem!$D$1:$J$1,0)),0)} -> 300.96496 | W141: {=IFERROR(INDEX(dem!$D$2:$J$1000, MATCH(1, ($S$139 = dem!$C$2:$C$1000) * (1 = dem!$B$2:$B$1000) * ($A141 = dem!$A$2:$A$1000) * (dem!$K$2:$K$1000 = "bedrm"), 0), MATCH(F$137, dem!$D$1:$J$1,0)),0)} -> 400.96405 | X141: {=IFERROR(INDEX(dem!$D$2:$J$1000, MATCH(1, ($S$139 = dem!$C$2:$C$1000) * (1 = dem!$B$2:$B$1000) * ($A141 = dem!$A$2:$A$1000) * (dem!$K$2:$K$1000 = "bedrm"), 0), MATCH(G$137, dem!$D$1:$J$1,0)),0)} -> 803.03198 | Y141: {=IFERROR(INDEX(dem!$D$2:$J$1000, MATCH(1, ($S$139 = dem!$C$2:$C$1000) * (1 = dem!$B$2:$B$1000) * ($A141 = dem!$A$2:$A$1000) * (dem!$K$2:$K$1000 = "bedrm"), 0), MATCH(H$137, dem!$D$1:$J$1,0)),0)} -> 99.704497 | Z141: {=IFERROR(INDEX(dem!$D$2:$J$1000, MATCH(1, ($S$139 = dem!$C$2:$C$1000) * (1 = dem!$B$2:$B$1000) * ($A141 = dem!$A$2:$A$1000) * (dem!$K$2:$K$1000 = "bedrm"), 0), MATCH(I$137, dem!$D$1:$J$1,0)),0)} -> 0 | AB141: 1-bed | AC141: {=IF(L151 = 0, 0, SUMPRODUCT($C150:$I150,TRANSPOSE(L$140:L$146), ($T150:$Z150)))} -> 0 | AD141: {=IF(M151 = 0, 0, SUMPRODUCT($C150:$I150,TRANSPOSE(M$140:M$146), ($T150:$Z150)))} -> 0 | AE141: {=IF(N151 = 0, 0, SUMPRODUCT($C150:$I150,TRANSPOSE(N$140:N$146), ($T150:$Z150)))} -> 0 | AF141: {=IF(O151 = 0, 0, SUMPRODUCT($C150:$I150,TRANSPOSE(O$140:O$146), ($T150:$Z150)))} -> 0 | AG141: {=IF(P151 = 0, 0, SUMPRODUCT($C150:$I150,TRANSPOSE(P$140:P$146), ($T150:$Z150)))} -> 0 | AH141: {=IF(Q151 = 0, 0, SUMPRODUCT($C150:$I150,TRANSPOSE(Q$140:Q$146), ($T150:$Z150)))} -> 0
A142: 2 | B142: 2-bed | C142: {=SUMPRODUCT(dem!$D$2:$J$1000 * ("bedrm" = dem!$K$2:$K$1000) * ($A142 = dem!$A$2:$A$1000) * ($B$139 = dem!$C$2:$C$1000) * (dem!$D$1:$J$1 = projection!C$137))} -> 7430.1273 | D142: {=SUMPRODUCT(dem!$D$2:$J$1000 * ("bedrm" = dem!$K$2:$K$1000) * ($A142 = dem!$A$2:$A$1000) * ($B$139 = dem!$C$2:$C$1000) * (dem!$D$1:$J$1 = projection!D$137))} -> 15064.621 | E142: {=SUMPRODUCT(dem!$D$2:$J$1000 * ("bedrm" = dem!$K$2:$K$1000) * ($A142 = dem!$A$2:$A$1000) * ($B$139 = dem!$C$2:$C$1000) * (dem!$D$1:$J$1 = projection!E$137))} -> 8136.2755 | F142: {=SUMPRODUCT(dem!$D$2:$J$1000 * ("bedrm" = dem!$K$2:$K$1000) * ($A142 = dem!$A$2:$A$1000) * ($B$139 = dem!$C$2:$C$1000) * (dem!$D$1:$J$1 = projection!F$137))} -> 8939.9646 | G142: {=SUMPRODUCT(dem!$D$2:$J$1000 * ("bedrm" = dem!$K$2:$K$1000) * ($A142 = dem!$A$2:$A$1000) * ($B$139 = dem!$C$2:$C$1000) * (dem!$D$1:$J$1 = projection!G$137))} -> 5523.5029 | H142: {=SUMPRODUCT(dem!$D$2:$J$1000 * ("bedrm" = dem!$K$2:$K$1000) * ($A142 = dem!$A$2:$A$1000) * ($B$139 = dem!$C$2:$C$1000) * (dem!$D$1:$J$1 = projection!H$137))} -> 3111.2984 | I142: {=SUMPRODUCT(dem!$D$2:$J$1000 * ("bedrm" = dem!$K$2:$K$1000) * ($A142 = dem!$A$2:$A$1000) * ($B$139 = dem!$C$2:$C$1000) * (dem!$D$1:$J$1 = projection!I$137))} -> 1206.0829 | K142: 35 to 44 | L142: 0 | M142: 0 | N142: 0 | O142: 0 | P142: 0 | Q142: 0 | S142: 2-bed | T142: {=IFERROR(INDEX(dem!$D$2:$J$1000, MATCH(1, ($S$139 = dem!$C$2:$C$1000) * (1 = dem!$B$2:$B$1000) * ($A142 = dem!$A$2:$A$1000) * (dem!$K$2:$K$1000 = "bedrm"), 0), MATCH(C$137, dem!$D$1:$J$1,0)),0)} -> 602.92315 | U142: {=IFERROR(INDEX(dem!$D$2:$J$1000, MATCH(1, ($S$139 = dem!$C$2:$C$1000) * (1 = dem!$B$2:$B$1000) * ($A142 = dem!$A$2:$A$1000) * (dem!$K$2:$K$1000 = "bedrm"), 0), MATCH(D$137, dem!$D$1:$J$1,0)),0)} -> 2410.4691 | V142: {=IFERROR(INDEX(dem!$D$2:$J$1000, MATCH(1, ($S$139 = dem!$C$2:$C$1000) * (1 = dem!$B$2:$B$1000) * ($A142 = dem!$A$2:$A$1000) * (dem!$K$2:$K$1000 = "bedrm"), 0), MATCH(E$137, dem!$D$1:$J$1,0)),0)} -> 2209.7194 | W142: {=IFERROR(INDEX(dem!$D$2:$J$1000, MATCH(1, ($S$139 = dem!$C$2:$C$1000) * (1 = dem!$B$2:$B$1000) * ($A142 = dem!$A$2:$A$1000) * (dem!$K$2:$K$1000 = "bedrm"), 0), MATCH(F$137, dem!$D$1:$J$1,0)),0)} -> 2108.7134 | X142: {=IFERROR(INDEX(dem!$D$2:$J$1000, MATCH(1, ($S$139 = dem!$C$2:$C$1000) * (1 = dem!$B$2:$B$1000) * ($A142 = dem!$A$2:$A$1000) * (dem!$K$2:$K$1000 = "bedrm"), 0), MATCH(G$137, dem!$D$1:$J$1,0)),0)} -> 1506.2747 | Y142: {=IFERROR(INDEX(dem!$D$2:$J$1000, MATCH(1, ($S$139 = dem!$C$2:$C$1000) * (1 = dem!$B$2:$B$1000) * ($A142 = dem!$A$2:$A$1000) * (dem!$K$2:$K$1000 = "bedrm"), 0), MATCH(H$137, dem!$D$1:$J$1,0)),0)} -> 1003.134 | Z142: {=IFERROR(INDEX(dem!$D$2:$J$1000, MATCH(1, ($S$139 = dem!$C$2:$C$1000) * (1 = dem!$B$2:$B$1000) * ($A142 = dem!$A$2:$A$1000) * (dem!$K$2:$K$1000 = "bedrm"), 0), MATCH(I$137, dem!$D$1:$J$1,0)),0)} -> 200.72121 | AB142: 2-bed | AC142: {=IF(L152 = 0, 0, SUMPRODUCT($C151:$I151,TRANSPOSE(L$140:L$146), ($T151:$Z151)))} -> 0 | AD142: {=IF(M152 = 0, 0, SUMPRODUCT($C151:$I151,TRANSPOSE(M$140:M$146), ($T151:$Z151)))} -> 0 | AE142: {=IF(N152 = 0, 0, SUMPRODUCT($C151:$I151,TRANSPOSE(N$140:N$146), ($T151:$Z151)))} -> 0 | AF142: {=IF(O152 = 0, 0, SUMPRODUCT($C151:$I151,TRANSPOSE(O$140:O$146), ($T151:$Z151)))} -> 0 | AG142: {=IF(P152 = 0, 0, SUMPRODUCT($C151:$I151,TRANSPOSE(P$140:P$146), ($T151:$Z151)))} -> 0 | AH142: {=IF(Q152 = 0, 0, SUMPRODUCT($C151:$I151,TRANSPOSE(Q$140:Q$146), ($T151:$Z151)))} -> 0
A143: 3 | B143: 3-bed | C143: {=SUMPRODUCT(dem!$D$2:$J$1000 * ("bedrm" = dem!$K$2:$K$1000) * ($A143 = dem!$A$2:$A$1000) * ($B$139 = dem!$C$2:$C$1000) * (dem!$D$1:$J$1 = projection!C$137))} -> 4418.874 | D143: {=SUMPRODUCT(dem!$D$2:$J$1000 * ("bedrm" = dem!$K$2:$K$1000) * ($A143 = dem!$A$2:$A$1000) * ($B$139 = dem!$C$2:$C$1000) * (dem!$D$1:$J$1 = projection!D$137))} -> 15065.73 | E143: {=SUMPRODUCT(dem!$D$2:$J$1000 * ("bedrm" = dem!$K$2:$K$1000) * ($A143 = dem!$A$2:$A$1000) * ($B$139 = dem!$C$2:$C$1000) * (dem!$D$1:$J$1 = projection!E$137))} -> 11652.872 | F143: {=SUMPRODUCT(dem!$D$2:$J$1000 * ("bedrm" = dem!$K$2:$K$1000) * ($A143 = dem!$A$2:$A$1000) * ($B$139 = dem!$C$2:$C$1000) * (dem!$D$1:$J$1 = projection!F$137))} -> 8538.0399 | G143: {=SUMPRODUCT(dem!$D$2:$J$1000 * ("bedrm" = dem!$K$2:$K$1000) * ($A143 = dem!$A$2:$A$1000) * ($B$139 = dem!$C$2:$C$1000) * (dem!$D$1:$J$1 = projection!G$137))} -> 4214.6 | H143: {=SUMPRODUCT(dem!$D$2:$J$1000 * ("bedrm" = dem!$K$2:$K$1000) * ($A143 = dem!$A$2:$A$1000) * ($B$139 = dem!$C$2:$C$1000) * (dem!$D$1:$J$1 = projection!H$137))} -> 1405.8502 | I143: {=SUMPRODUCT(dem!$D$2:$J$1000 * ("bedrm" = dem!$K$2:$K$1000) * ($A143 = dem!$A$2:$A$1000) * ($B$139 = dem!$C$2:$C$1000) * (dem!$D$1:$J$1 = projection!I$137))} -> 703.54999 | K143: 45 to 54 | L143: 0 | M143: 0 | N143: 0 | O143: 0 | P143: 0 | Q143: 0 | S143: 3-bed | T143: {=IFERROR(INDEX(dem!$D$2:$J$1000, MATCH(1, ($S$139 = dem!$C$2:$C$1000) * (1 = dem!$B$2:$B$1000) * ($A143 = dem!$A$2:$A$1000) * (dem!$K$2:$K$1000 = "bedrm"), 0), MATCH(C$137, dem!$D$1:$J$1,0)),0)} -> 703.43788 | U143: {=IFERROR(INDEX(dem!$D$2:$J$1000, MATCH(1, ($S$139 = dem!$C$2:$C$1000) * (1 = dem!$B$2:$B$1000) * ($A143 = dem!$A$2:$A$1000) * (dem!$K$2:$K$1000 = "bedrm"), 0), MATCH(D$137, dem!$D$1:$J$1,0)),0)} -> 5926.3443 | V143: {=IFERROR(INDEX(dem!$D$2:$J$1000, MATCH(1, ($S$139 = dem!$C$2:$C$1000) * (1 = dem!$B$2:$B$1000) * ($A143 = dem!$A$2:$A$1000) * (dem!$K$2:$K$1000 = "bedrm"), 0), MATCH(E$137, dem!$D$1:$J$1,0)),0)} -> 4520.2724 | W143: {=IFERROR(INDEX(dem!$D$2:$J$1000, MATCH(1, ($S$139 = dem!$C$2:$C$1000) * (1 = dem!$B$2:$B$1000) * ($A143 = dem!$A$2:$A$1000) * (dem!$K$2:$K$1000 = "bedrm"), 0), MATCH(F$137, dem!$D$1:$J$1,0)),0)} -> 4719.6846 | X143: {=IFERROR(INDEX(dem!$D$2:$J$1000, MATCH(1, ($S$139 = dem!$C$2:$C$1000) * (1 = dem!$B$2:$B$1000) * ($A143 = dem!$A$2:$A$1000) * (dem!$K$2:$K$1000 = "bedrm"), 0), MATCH(G$137, dem!$D$1:$J$1,0)),0)} -> 2409.1983 | Y143: {=IFERROR(INDEX(dem!$D$2:$J$1000, MATCH(1, ($S$139 = dem!$C$2:$C$1000) * (1 = dem!$B$2:$B$1000) * ($A143 = dem!$A$2:$A$1000) * (dem!$K$2:$K$1000 = "bedrm"), 0), MATCH(H$137, dem!$D$1:$J$1,0)),0)} -> 602.20176 | Z143: {=IFERROR(INDEX(dem!$D$2:$J$1000, MATCH(1, ($S$139 = dem!$C$2:$C$1000) * (1 = dem!$B$2:$B$1000) * ($A143 = dem!$A$2:$A$1000) * (dem!$K$2:$K$1000 = "bedrm"), 0), MATCH(I$137, dem!$D$1:$J$1,0)),0)} -> 301.84214 | AB143: 3-bed | AC143: {=IF(L153 = 0, 0, SUMPRODUCT($C152:$I152,TRANSPOSE(L$140:L$146), ($T152:$Z152)))} -> 0 | AD143: {=IF(M153 = 0, 0, SUMPRODUCT($C152:$I152,TRANSPOSE(M$140:M$146), ($T152:$Z152)))} -> 0 | AE143: {=IF(N153 = 0, 0, SUMPRODUCT($C152:$I152,TRANSPOSE(N$140:N$146), ($T152:$Z152)))} -> 0 | AF143: {=IF(O153 = 0, 0, SUMPRODUCT($C152:$I152,TRANSPOSE(O$140:O$146), ($T152:$Z152)))} -> 0 | AG143: {=IF(P153 = 0, 0, SUMPRODUCT($C152:$I152,TRANSPOSE(P$140:P$146), ($T152:$Z152)))} -> 0 | AH143: {=IF(Q153 = 0, 0, SUMPRODUCT($C152:$I152,TRANSPOSE(Q$140:Q$146), ($T152:$Z152)))} -> 0
A144: 4 | B144: 4-bed | C144: {=SUMPRODUCT(dem!$D$2:$J$1000 * ("bedrm" = dem!$K$2:$K$1000) * ($A144 = dem!$A$2:$A$1000) * ($B$139 = dem!$C$2:$C$1000) * (dem!$D$1:$J$1 = projection!C$137))} -> 1205.417 | D144: {=SUMPRODUCT(dem!$D$2:$J$1000 * ("bedrm" = dem!$K$2:$K$1000) * ($A144 = dem!$A$2:$A$1000) * ($B$139 = dem!$C$2:$C$1000) * (dem!$D$1:$J$1 = projection!D$137))} -> 5323.3978 | E144: {=SUMPRODUCT(dem!$D$2:$J$1000 * ("bedrm" = dem!$K$2:$K$1000) * ($A144 = dem!$A$2:$A$1000) * ($B$139 = dem!$C$2:$C$1000) * (dem!$D$1:$J$1 = projection!E$137))} -> 5323.2014 | F144: {=SUMPRODUCT(dem!$D$2:$J$1000 * ("bedrm" = dem!$K$2:$K$1000) * ($A144 = dem!$A$2:$A$1000) * ($B$139 = dem!$C$2:$C$1000) * (dem!$D$1:$J$1 = projection!F$137))} -> 3012.1789 | G144: {=SUMPRODUCT(dem!$D$2:$J$1000 * ("bedrm" = dem!$K$2:$K$1000) * ($A144 = dem!$A$2:$A$1000) * ($B$139 = dem!$C$2:$C$1000) * (dem!$D$1:$J$1 = projection!G$137))} -> 904.56639 | H144: {=SUMPRODUCT(dem!$D$2:$J$1000 * ("bedrm" = dem!$K$2:$K$1000) * ($A144 = dem!$A$2:$A$1000) * ($B$139 = dem!$C$2:$C$1000) * (dem!$D$1:$J$1 = projection!H$137))} -> 502.44099 | I144: {=SUMPRODUCT(dem!$D$2:$J$1000 * ("bedrm" = dem!$K$2:$K$1000) * ($A144 = dem!$A$2:$A$1000) * ($B$139 = dem!$C$2:$C$1000) * (dem!$D$1:$J$1 = projection!I$137))} -> 0 | K144: 55 to 64 | L144: 0 | M144: 0 | N144: 0 | O144: 0 | P144: 0 | Q144: 0 | S144: 4-bed | T144: {=IFERROR(INDEX(dem!$D$2:$J$1000, MATCH(1, ($S$139 = dem!$C$2:$C$1000) * (1 = dem!$B$2:$B$1000) * ($A144 = dem!$A$2:$A$1000) * (dem!$K$2:$K$1000 = "bedrm"), 0), MATCH(C$137, dem!$D$1:$J$1,0)),0)} -> 201.45777 | U144: {=IFERROR(INDEX(dem!$D$2:$J$1000, MATCH(1, ($S$139 = dem!$C$2:$C$1000) * (1 = dem!$B$2:$B$1000) * ($A144 = dem!$A$2:$A$1000) * (dem!$K$2:$K$1000 = "bedrm"), 0), MATCH(D$137, dem!$D$1:$J$1,0)),0)} -> 2911.7523 | V144: {=IFERROR(INDEX(dem!$D$2:$J$1000, MATCH(1, ($S$139 = dem!$C$2:$C$1000) * (1 = dem!$B$2:$B$1000) * ($A144 = dem!$A$2:$A$1000) * (dem!$K$2:$K$1000 = "bedrm"), 0), MATCH(E$137, dem!$D$1:$J$1,0)),0)} -> 3514.7159 | W144: {=IFERROR(INDEX(dem!$D$2:$J$1000, MATCH(1, ($S$139 = dem!$C$2:$C$1000) * (1 = dem!$B$2:$B$1000) * ($A144 = dem!$A$2:$A$1000) * (dem!$K$2:$K$1000 = "bedrm"), 0), MATCH(F$137, dem!$D$1:$J$1,0)),0)} -> 2107.8322 | X144: {=IFERROR(INDEX(dem!$D$2:$J$1000, MATCH(1, ($S$139 = dem!$C$2:$C$1000) * (1 = dem!$B$2:$B$1000) * ($A144 = dem!$A$2:$A$1000) * (dem!$K$2:$K$1000 = "bedrm"), 0), MATCH(G$137, dem!$D$1:$J$1,0)),0)} -> 603.48472 | Y144: {=IFERROR(INDEX(dem!$D$2:$J$1000, MATCH(1, ($S$139 = dem!$C$2:$C$1000) * (1 = dem!$B$2:$B$1000) * ($A144 = dem!$A$2:$A$1000) * (dem!$K$2:$K$1000 = "bedrm"), 0), MATCH(H$137, dem!$D$1:$J$1,0)),0)} -> 200.89811 | Z144: {=IFERROR(INDEX(dem!$D$2:$J$1000, MATCH(1, ($S$139 = dem!$C$2:$C$1000) * (1 = dem!$B$2:$B$1000) * ($A144 = dem!$A$2:$A$1000) * (dem!$K$2:$K$1000 = "bedrm"), 0), MATCH(I$137, dem!$D$1:$J$1,0)),0)} -> 0 | AB144: 4-bed | AC144: {=IF(L154 = 0, 0, SUMPRODUCT($C153:$I153,TRANSPOSE(L$140:L$146), ($T153:$Z153)))} -> 0 | AD144: {=IF(M154 = 0, 0, SUMPRODUCT($C153:$I153,TRANSPOSE(M$140:M$146), ($T153:$Z153)))} -> 0 | AE144: {=IF(N154 = 0, 0, SUMPRODUCT($C153:$I153,TRANSPOSE(N$140:N$146), ($T153:$Z153)))} -> 0 | AF144: {=IF(O154 = 0, 0, SUMPRODUCT($C153:$I153,TRANSPOSE(O$140:O$146), ($T153:$Z153)))} -> 0 | AG144: {=IF(P154 = 0, 0, SUMPRODUCT($C153:$I153,TRANSPOSE(P$140:P$146), ($T153:$Z153)))} -> 0 | AH144: {=IF(Q154 = 0, 0, SUMPRODUCT($C153:$I153,TRANSPOSE(Q$140:Q$146), ($T153:$Z153)))} -> 0
...

Sheet federal_req
B2: Table 2.2.1: Population | G2: Table 5.2.1: Housing Units Currently Occupied / Available | L2: Income Categories and Affordable Shelter Costs (HART)
B3: Characteristic | C3: Data | D3: Source | E3: Value | G3: Characteristic | H3: Data | I3: Source | J3: Value | L3: Income Category | M3: Income Range | N3: Max Rent (30%) | O3: HH Count | P3: % in Core Need
B4: Total population | C4: 2016 | D4: Census profile | E4: =IFERROR(popn_now!C12,"x") -> x | G4: Total private dwellings | H4: Total | I4: Census profile | J4: =IFERROR(dwell!N17,"x") -> x | L4: Very Low | M4: {=IFERROR(TRANSPOSE(income!D97:H98),"x")} -> x | N4: =IFERROR(Q4*0.3/12,"x") -> x | O4: {=IF(income!D65:D69 = 0, "x", income!D65:D69)} -> x | P4: {=IFERROR(N14:N18/O4:O8,"x")} -> x | Q4: {=TRANSPOSE(income!D108:H108)} -> #N/A
C5: 2021 | D5: Census profile | E5: =IFERROR(popn_now!D12,"x") -> x | G5: Dwellings by structural type | H5: Single-detached | I5: Census profile | J5: =IFERROR(dwell!C79,"x") -> x | L5: Low | M5: x | N5: =IFERROR(Q5*0.3/12,"x") -> x | O5: x | P5: x | Q5: #N/A
B6: Population growth | C6: Total | D6: Census profile | E6: =IFERROR(E5-E4,"x") -> x | H6: Semi-detached | I6: Census profile | J6: =IFERROR(dwell!C80,"x") -> x | L6: Moderate | M6: x | N6: =IFERROR(Q6*0.3/12,"x") -> x | O6: x | P6: x | Q6: #N/A
C7: Percentage | D7: Census profile | E7: =IFERROR(E5/E4-1,"x") -> x | H7: Row house | I7: Census profile | J7: =IFERROR(dwell!C81,"x") -> x | L7: Median | M7: x | N7: =IFERROR(Q7*0.3/12,"x") -> x | O7: x | P7: x | Q7: #N/A
A8: 39 | B8: Age (years) | C8: Average | D8: Census profile | E8: {=IFERROR(IF(INDEX(df_pop!$C$2:$C$1000, MATCH(1, (cover!$C$4 = df_pop!$A$2:$A$1000) * ($A8 = df_pop!$B$2:$B$1000) * (df_pop!$E$2:$E$1000 = 2016),0),0) = 0, "x", INDEX(df_pop!$C$2:$C$1000, MATCH(1, (cover!$C$4 = df_pop!$A$2:$A$1000) * ($A8 = df_pop!$B$2:$B$1000) * (df_pop!$E$2:$E$1000 = 2016),0),0)),"x")} -> x | H8: Apartment/flat in duplex | I8: Census profile | J8: =IFERROR(dwell!C82,"x") -> x | L8: High | M8: x | N8: =Q8*0.3/12 -> 0 | O8: x | P8: x | Q8: 0
A9: 40 | C9: Median | D9: Census profile | E9: {=IFERROR(IF(INDEX(df_pop!$C$2:$C$1000, MATCH(1, (cover!$C$4 = df_pop!$A$2:$A$1000) * ($A9 = df_pop!$B$2:$B$1000) * (df_pop!$E$2:$E$1000 = 2016),0),0) = 0, "x", INDEX(df_pop!$C$2:$C$1000, MATCH(1, (cover!$C$4 = df_pop!$A$2:$A$1000) * ($A9 = df_pop!$B$2:$B$1000) * (df_pop!$E$2:$E$1000 = 2016),0),0)),"x")} -> x | H9: Apartment (<5 storeys) | I9: Census profile | J9: =IFERROR(dwell!C83,"x") -> x
B10: Age distribution | C10: 0 to 14 | D10: Census profile | E10: =IFERROR(SUM(popn_now!D13:D15),"x") -> x | H10: Apartment (5+ storeys) | I10: Census profile | J10: =IFERROR(dwell!C84,"x") -> x
C11: 15 to 64 | D11: Census profile | E11: =IFERROR(SUM(popn_now!D16:D25),"x") -> x | H11: Other single attached | I11: Census profile | J11: =IFERROR(dwell!C85,"x") -> x | L11: Core Housing Need by Income Category and Household Size
C12: 65+ | D12: Census profile | E12: =IFERROR(SUM(popn_now!D26:D30),"x") -> x | H12: Movable dwelling | I12: Census profile | J12: =IFERROR(dwell!C86,"x") -> x | L12: Income category | M12: Max affordable shelter cost | N12: Total | O12: 1 person HH | P12: 2 person HH | Q12: 3 person HH | R12: 4 person HH | S12: 5+ person HH
B13: Mobility | C13: Non-movers | D13: Census profile | E13: =IFERROR(popn_now!D149,"x") -> x | G13: Dwellings by size | H13: No bedrooms | I13: Census profile | J13: =dwell!C121 -> 0 | L13: Total | N13: {=IF(need!D199:I204 = 0, "x", need!D199:I204)} -> x | O13: x | P13: x | Q13: x | R13: x | S13: x
C14: Non-migrants | D14: Census profile | E14: =IFERROR(popn_now!D151,"x") -> x | H14: 1 bedroom | I14: Census profile | J14: =dwell!C122 -> 0 | L14: Very low | M14: {=need!C200:C204} -> x | N14: x | O14: x | P14: x | Q14: x | R14: x | S14: x
C15: Migrants | D15: Census profile | E15: =IFERROR(popn_now!D152,"x") -> x | H15: 2 bedrooms | I15: Census profile | J15: =dwell!C123 -> 0 | L15: Low | M15: x | N15: x | O15: x | P15: x | Q15: x | R15: x | S15: x
H16: 3 bedrooms | I16: Census profile | J16: =dwell!C124 -> 0 | L16: Moderate | M16: x | N16: x | O16: x | P16: x | Q16: x | R16: x | S16: x
H17: 4+ bedrooms | I17: Census profile | J17: =dwell!C125 -> 0 | L17: Median | M17: x | N17: x | O17: x | P17: x | Q17: x | R17: x | S17: x
B18: Table 2.2.2: Demographic Information | G18: Dwellings by date built | H18: 1960 or before | I18: Census profile | J18: =IFERROR(dwell!C51,"x") -> x | L18: High | M18: >x | N18: x | O18: x | P18: x | Q18: x | R18: x | S18: x
B19: Characteristic | C19: Data | D19: Source | E19: Value | H19: 1961–1980 | I19: Census profile | J19: =IFERROR(dwell!C52,"x") -> x
B20: Immigrants | C20: Total | D20: Census profile | E20: =IFERROR(popn_now!D179,"x") -> x | H20: 1981–1990 | I20: Census profile | J20: =IFERROR(dwell!C53,"x") -> x
B21: Non-immigrants | C21: Total | D21: Census profile | E21: =IFERROR(popn_now!D176-popn_now!D179,"x") -> x | H21: 1991–2000 | I21: Census profile | J21: =IFERROR(dwell!C54,"x") -> x | L21: Table 6.3.1: Anticipated Population by 2035
B22: Recent immigrants (2016–2021) | C22: Total | D22: Census profile | E22: =IFERROR(popn_now!D180,"x") -> x | H22: 2001–2005 | I22: Census profile | J22: =IFERROR(dwell!C55,"x") -> x | L22: Characteristic | M22: Data | N22: Source | O22: Value
B23: Interprovincial migrants (2016–2021) | C23: Total | D23: Census profile | E23: =IFERROR(popn_now!D155,"x") -> x | H23: 2006–2010 | I23: Census profile | J23: =IFERROR(dwell!C56,"x") -> x | L23: Anticipated population | M23: Total | N23: Table 17-10-0162 | O23: =IFERROR(popn_fut!L81,"x") -> x
B24: Indigenous identity | C24: Total | D24: Census profile | E24: =IFERROR(popn_now!D177,"x") -> x | H24: 2011–2015 | I24: Census profile | J24: =IFERROR(dwell!C57,"x") -> x | L24: Anticipated growth | M24: Total | N24: Table 17-10-0162 | O24: =IFERROR(popn_fut!L81-popn_fut!K81,"x") -> x
H25: 2016–2021 | I25: Census profile | J25: =IFERROR(dwell!C58,"x") -> x | M25: Percentage | N25: Table 17-10-0162 | O25: =IFERROR(popn_fut!L81/popn_fut!K81-1,"x") -> x
G26: Rental vacancy rate | H26: Total | I26: CMHC RMS | J26: =rental!D34 -> x | L26: Anticipated age | M26: Average | N26: Estimated | O26: {=IFERROR(projection!AS25,"x")} -> x
B27: Table 3.1.1: Household Income and Profile | H27: Studio | I27: CMHC RMS | J27: =rental!D35 -> x | M27: Median | N27: Estimated | O27: {=IFERROR(projection!AS26,"x")} -> x
B28: Characteristic | C28: Data | D28: Source | E28: Value | H28: 1 bedroom | I28: CMHC RMS | J28: =rental!D36 -> x | L28: Age distribution | M28: 0–14 | N28: Table 17-10-0162 | O28: =IFERROR(SUM(popn_fut!D82:D84),"x") -> x
B29: Total number of households | C29: 2016 | D29: Census profile | E29: {=IFERROR(IF(hh!D72 = 0, "x", hh!D72),"x")} -> x | H29: 2 bedrooms | I29: CMHC RMS | J29: =rental!D37 -> x | M29: 15–19 | N29: Table 17-10-0162 | O29: =IFERROR(popn_fut!D85,"x") -> x
C30: 2021 | D30: Census profile | E30: =IFERROR(IF(hh!E72 = 0, "x", hh!E72),"x") -> x | H30: 3+ bedrooms | I30: CMHC RMS | J30: =rental!D38 -> x | M30: 20–24 | N30: Table 17-10-0162 | O30: =IFERROR(popn_fut!D86,"x") -> x
A31: 252 | B31: Annual household income | C31: Average | D31: Census profile | E31: {=IFERROR(IF(INDEX(df_census_misc!$C$2:$C$1000, MATCH(1, (cover!$C$4 = df_census_misc!$A$2:$A$1000) * (df_census_misc!$B$2:$B$1000 = $A31), 0), 0)=0,"x", INDEX(df_census_misc!$C$2:$C$1000, MATCH(1, (cover!$C$4 = df_census_misc!$A$2:$A$1000) * (df_census_misc!$B$2:$B$1000 = $A31), 0), 0)),"x")} -> x | G31: Primary rental units | H31: Total | I31: CMHC RMS | J31: =rental!J66 -> 0 | M31: 25–64 | N31: Table 17-10-0162 | O31: =IFERROR(SUM(popn_fut!D87:D94),"x") -> x
A32: 243 | C32: Median | D32: Census profile | E32: {=IFERROR(IF(INDEX(df_census_misc!$C$2:$C$1000, MATCH(1, (cover!$C$4 = df_census_misc!$A$2:$A$1000) * (df_census_misc!$B$2:$B$1000 = $A32), 0), 0)=0,"x", INDEX(df_census_misc!$C$2:$C$1000, MATCH(1, (cover!$C$4 = df_census_misc!$A$2:$A$1000) * (df_census_misc!$B$2:$B$1000 = $A32), 0), 0)),"x")} -> x | G32: Secondary rental units | H32: Total | I32: Estimate | J32: =rental!K66 -> x | M32: 65–84 | N32: Table 17-10-0162 | O32: =IFERROR(SUM(popn_fut!D95:D98),"x") -> x
B33: Annual tenant household income | C33: Average | D33: Estimate | E33: =IFERROR(income!J33,"x") -> x | G33: Short-term rental units | H33: Total | I33: AirDNA© | J33: =dwell!C256 -> x | M33: 85+ | N33: Table 17-10-0162 | O33: =IFERROR(popn_fut!D99,"x") -> x
C34: Median | D34: Estimate | E34: =IFERROR(income!C43,"x") -> x
B35: Annual owner household income | C35: Average | D35: Estimate | E35: =IFERROR(income!J32,"x") -> x
C36: Median | D36: Estimate | E36: =income!C42 -> x | G36: Table 5.7.1: Current Non-Market Housing Units | L36: Table 6.3.2: Anticipated Households by 2035
B37: Average household size | C37: Average | D37: Census profile | E37: =IFERROR(hh!D30,"x") -> x | G37: Characteristic | H37: Data | I37: Source | J37: Value | L37: Characteristic | M37: Data | N37: Source | O37: Value
B38: Household breakdown by size | C38: Total | D38: Census profile | E38: =E30 -> x | G38: Subsidized housing units | H38: Total | I38: Census profile | J38: {=IFERROR(dwell!D136,"x")} -> x | L38: Current number of households | M38: Total | N38: See methodology | O38: =projection!M31 -> 0
C39: 1 person | D39: Census profile | E39: =IFERROR(hh!D25,"x") -> x | G39: Below-market rent units (private) | H39: Total | I39: HART | J39: =dwell!C222 -> x | L39: Anticipated number of households | M39: Total | N39: See methodology | O39: =projection!W31 -> 0
C40: 2 persons | D40: Census profile | E40: =IFERROR(hh!D26,"x") -> x | G40: Co-operative housing units | H40: Total | I40: Multiple | J40: =IFERROR(IF(dwell!D376 > 0, dwell!D376, "x"),"x") -> - | L40: Anticipated household age | M40: Average | N40: Estimated | O40: =IFERROR(projection!AO37,"x") -> x
C41: 3 persons | D41: Census profile | E41: =IFERROR(hh!D27,"x") -> x | G41: Other non-market units (supportive, transitional) | H41: Total (beds + units) | I41: Multiple | J41: =IFERROR(IF(SUM(dwell!C377:D381) > 0, SUM(dwell!C377:D381), "x"), "x") -> x | M41: Median | N41: Estimated | O41: =IFERROR(projection!AO38,"x") -> x
C42: 4 persons | D42: Census profile | E42: =IFERROR(hh!D28,"x") -> x | L42: By tenure | M42: Tenant | N42: See methodology | O42: =IFERROR(MROUND($O$39*P42/SUM($P$42:$P$43),5),"x") -> x | P42: =IFERROR(MROUND(SUM(projection!AD265:AD269),5),0) -> 0
C43: 5 or more persons | D43: Census profile | E43: =IFERROR(hh!D29,"x") -> x | M43: Owner | N43: See methodology | O43: =IFERROR(MROUND($O$39*P43/SUM($P$42:$P$43),5),"x") -> x | P43: =MROUND(SUM(projection!V265:V269),5) -> 0
B44: Tenant households | C44: Total | D44: Census profile | E44: =IFERROR(hh!F11,"x") -> x | G44: Table 5.9.1: Housing Values | L44: By type | M44: Total | N44: See methodology | O44: =IFERROR(projection!H241,"x") -> x
C45: Percentage | D45: Census profile | E45: =IFERROR(IF(E44/SUM(E44,E46) = 0, "x", E44/SUM(E44,E46)),"x") -> x | G45: Characteristic | H45: Data | I45: Source | J45: Value | M45: Single-detached | N45: See methodology | O45: =IFERROR(MROUND(P45,5),"x") -> x | P45: {=projection!V284:V286} -> #N/A
B46: Owner households | C46: Total | D46: Census profile | E46: =IFERROR(hh!E11,"x") -> x | F46: 1494 | G46: Median monthly tenant shelter costs | H46: Median | I46: Census profile | J46: {=IFERROR(IF(INDEX(df_census_misc!$C$2:$C$1000, MATCH(1, (cover!$C$4 = df_census_misc!$A$2:$A$1000) * (df_census_misc!$B$2:$B$1000 = $F46), 0), 0)=0,"x", INDEX(df_census_misc!$C$2:$C$1000, MATCH(1, (cover!$C$4 = df_census_misc!$A$2:$A$1000) * (df_census_misc!$B$2:$B$1000 = $F46), 0), 0)),"x")} -> x | M46: Apartment | N46: See methodology | O46: =IFERROR(MROUND(P46,5),"x") -> x | P46: #N/A
C47: Percentage | D47: Census profile | E47: =IFERROR(E46/SUM(E44,E46),"x") -> x | G47: Purpose-built rental price (average) | H47: Total | I47: CMHC RMS | J47: {=IFERROR(IF(rental!L12:L16 = 0, "x", rental!L12:L16),"x")} -> x | M47: Other | N47: See methodology | O47: =IFERROR(MROUND(P47,5),"x") -> x | P47: #N/A
B48: % tenant HH in subsidized housing | C48: Percentage | D48: Census profile | E48: =IFERROR(dwell!D136/dwell!D135,"x") -> x | H48: Studio | I48: CMHC RMS | J48: x | L48: By bedrooms | M48: Total | N48: See methodology | O48: =O44 -> x
B49: One-parent families | C49: Total | D49: Census profile | E49: =IFERROR(hh!D22,"x") -> x | H49: 1 bedroom | I49: CMHC RMS | J49: x | M49: Studio | N49: See methodology | O49: =IFERROR(MROUND(P49,5),"x") -> x | P49: {=projection!N265:N269} -> #N/A
C50: Percentage | D50: Census profile | E50: =IFERROR(E49/E30,"x") -> x | H50: 2 bedrooms | I50: CMHC RMS | J50: x | M50: 1 bedroom | N50: See methodology | O50: =IFERROR(MROUND(P50,5),"x") -> x | P50: #N/A
B51: Parent is a woman+ | C51: Total | D51: Census profile | E51: =IF(need!C175 = 0, "x", need!C175) -> x | H51: 3+ bedrooms | I51: CMHC RMS | J51: x | M51: 2 bedrooms | N51: See methodology | O51: =IFERROR(MROUND(P51,5),"x") -> x | P51: #N/A
B52: Parent is a man+ | C52: Total | D52: Census profile | E52: =IF(need!C174-need!C175 = 0, "x", need!C174-need!C175) -> x | G52: Purpose-built rental price (median) | H52: Total | I52: CMHC RMS | J52: {=IFERROR(IF(rental!E12:E16 = 0, "x", rental!E12:E16),"x")} -> x | M52: 3 bedrooms | N52: See methodology | O52: =IFERROR(MROUND(P52,5),"x") -> x | P52: #N/A
B53: Household by income category | C53: Very low (up to 20% AMHI) | D53: HART | E53: =IF(income!D65 = 0, "x", income!D65) -> x | H53: Studio | I53: CMHC RMS | J53: x | M53: 4+ bedrooms | N53: See methodology | O53: =IFERROR(MROUND(P53,5),"x") -> x | P53: #N/A
C54: Low (21–50% AMHI) | D54: HART | E54: =IF(income!D66 = 0, "x", income!D66) -> x | H54: 1 bedroom | I54: CMHC RMS | J54: x | L54: By income | M54: Average | N54: See methodology | O54: {=projection!S325:S330} -> 0
C55: Moderate (51–80% AMHI) | D55: HART | E55: =IF(income!D67 = 0, "x", income!D67) -> x | H55: 2 bedrooms | I55: CMHC RMS | J55: x | M55: Very low | N55: See methodology | O55: x
C56: Median (81–120% AMHI) | D56: HART | E56: =IF(income!D68 = 0, "x", income!D68) -> x | H56: 3+ bedrooms | I56: CMHC RMS | J56: x | M56: Low | N56: See methodology | O56: x
C57: High (>120% AMHI) | D57: HART | E57: =IF(income!D69 = 0, "x", income!D69) -> x | G57: Sale prices | H57: Average | I57: MLS® | J57: =IFERROR(IF(sales!E22 = 0, "x", sales!E22),"x") -> x | M57: Moderate | N57: See methodology | O57: x
H58: Median | I58: MLS® | J58: =IFERROR(IF(sales!E12 = 0, "x", sales!E12),"x") -> x | M58: Median | N58: See methodology | O58: x
G59: Sale prices by size (average) | H59: Total | I59: MLS® | J59: {=IFERROR(sales!I34:I38,"x")} -> x | M59: High | N59: See methodology | O59: x
B60: Table 3.4.1: Economy and Labour Force | H60: Studio | I60: MLS® | J60: x | L60: Average household size | M60: Total | N60: Estimated | O60: =IFERROR(projection!AK218,"x") -> x
B61: Characteristic | C61: Data | D61: Source | E61: Value | H61: 1 bedroom | I61: MLS® | J61: x | L61: Draft approved lots | M61: Total
B62: Workers in labour force | C62: Total | D62: Census profile | E62: =IFERROR(econ!D11,"x") -> x | H62: 2 bedrooms | I62: MLS® | J62: x | M62: Tenant
B63: Workers by industry | C63: {=econ!B63:B72} | D63: Census profile | E63: {=IFERROR(econ!P38:P47,"x")} -> x | H63: 3+ bedrooms | I63: MLS® | J63: x | M63: Owner
D64: Census profile | E64: x | G64: Sale prices by size (median) | H64: Total | I64: MLS® | J64: {=sales!C34:C38} -> x
D65: Census profile | E65: x | H65: Studio | I65: MLS® | J65: x
D66: Census profile | E66: x | H66: 1 bedroom | I66: MLS® | J66: x | L66: Table 6.1.1: Projected Households by Household Size and Income Category
D67: Census profile | E67: x | H67: 2 bedrooms | I67: MLS® | J67: x | L67: Income category | M67: Total | N67: 1 person HH | O67: 2 person HH | P67: 3 person HH | Q67: 4 person HH | R67: 5+ person HH
D68: Census profile | E68: x | H68: 3+ bedrooms | I68: MLS® | J68: x | L68: Total | M68: {=projection!S325:X330} -> 0 | N68: x | O68: x | P68: x | Q68: x | R68: x
D69: Census profile | E69: x | L69: Very low | M69: x | N69: x | O69: x | P69: x | Q69: x | R69: x
D70: Census profile | E70: x | L70: Low | M70: x | N70: x | O70: x | P70: x | Q70: x | R70: x
D71: Census profile | E71: x | G71: Table 5.9.2: Change in Housing Stock | J71: 45839 | L71: Moderate | M71: x | N71: x | O71: x | P71: x | Q71: x | R71: x
D72: Census profile | E72: x | G72: Characteristic | H72: Data | I72: Source | J72: Value | L72: Median | M72: x | N72: x | O72: x | P72: x | Q72: x | R72: x
B73: Unemployment rate (Percent) | C73: Percentage | D73: Census profile | E73: =econ!C26 -> x | G73: Demolished | H73: Tenant | I73: Local gov't | J73: x | L73: High | M73: x | N73: x | O73: x | P73: x | Q73: x | R73: x
B74: Participation rate (Percent) | C74: Percentage | D74: Census profile | E74: =econ!C24 -> x | H74: Owner | I74: Local gov't | J74: x
A75: 2239 | B75: All classes of workers (Number) | C75: Total | D75: Census profile | E75: {=IFERROR(INDEX(df_lf!$C$2:$C$1000, MATCH(1, (cover!$C$4 = df_lf!$A$2:$A$1000) * ($A75 = df_lf!$B$2:$B$1000), 0), 0),"x")} -> x | F75: t_total | G75: Completed | H75: Total | I75: CMHC SCSS | J75: {=IFERROR(INDEX(df_cmhc_scss!$D$2:$AB$1000, MATCH(1, (cover!$C$4 = df_cmhc_scss!$A$2:$A$1000) * (df_cmhc_scss!$C$2:$C$1000 = "completions") * (df_cmhc_scss!$B$2:$B$1000 = federal_req!$J$71), 0), MATCH(federal_req!$F75, df_cmhc_scss!$D$1:$AB$1,0)),"x")} -> x
A76: 2240 | C76: Employees | D76: Census profile | E76: {=IFERROR(INDEX(df_lf!$C$2:$C$1000, MATCH(1, (cover!$C$4 = df_lf!$A$2:$A$1000) * ($A76 = df_lf!$B$2:$B$1000), 0), 0),"x")} -> x | F76: t_single | H76: Single | I76: CMHC SCSS | J76: {=IFERROR(INDEX(df_cmhc_scss!$D$2:$AB$1000, MATCH(1, (cover!$C$4 = df_cmhc_scss!$A$2:$A$1000) * (df_cmhc_scss!$C$2:$C$1000 = "completions") * (df_cmhc_scss!$B$2:$B$1000 = federal_req!$J$71), 0), MATCH(federal_req!$F76, df_cmhc_scss!$D$1:$AB$1,0)),"x")} -> x
A77: 2241 | C77: Permanent position | D77: Census profile | E77: {=IFERROR(INDEX(df_lf!$C$2:$C$1000, MATCH(1, (cover!$C$4 = df_lf!$A$2:$A$1000) * ($A77 = df_lf!$B$2:$B$1000), 0), 0),"x")} -> x | F77: t_semi | H77: Semi-detached | I77: CMHC SCSS | J77: {=IFERROR(INDEX(df_cmhc_scss!$D$2:$AB$1000, MATCH(1, (cover!$C$4 = df_cmhc_scss!$A$2:$A$1000) * (df_cmhc_scss!$C$2:$C$1000 = "completions") * (df_cmhc_scss!$B$2:$B$1000 = federal_req!$J$71), 0), MATCH(federal_req!$F77, df_cmhc_scss!$D$1:$AB$1,0)),"x")} -> x
A78: 2242 | C78: Temporary position | D78: Census profile | E78: {=IFERROR(INDEX(df_lf!$C$2:$C$1000, MATCH(1, (cover!$C$4 = df_lf!$A$2:$A$1000) * ($A78 = df_lf!$B$2:$B$1000), 0), 0),"x")} -> x | F78: t_row | H78: Row | I78: CMHC SCSS | J78: {=IFERROR(INDEX(df_cmhc_scss!$D$2:$AB$1000, MATCH(1, (cover!$C$4 = df_cmhc_scss!$A$2:$A$1000) * (df_cmhc_scss!$C$2:$C$1000 = "completions") * (df_cmhc_scss!$B$2:$B$1000 = federal_req!$J$71), 0), MATCH(federal_req!$F78, df_cmhc_scss!$D$1:$AB$1,0)),"x")} -> x
A79: 2243 | C79: Fixed term (1+ year) | D79: Census profile | E79: {=IFERROR(INDEX(df_lf!$C$2:$C$1000, MATCH(1, (cover!$C$4 = df_lf!$A$2:$A$1000) * ($A79 = df_lf!$B$2:$B$1000), 0), 0),"x")} -> x | F79: t_apt | H79: Apartment | I79: CMHC SCSS | J79: {=IFERROR(INDEX(df_cmhc_scss!$D$2:$AB$1000, MATCH(1, (cover!$C$4 = df_cmhc_scss!$A$2:$A$1000) * (df_cmhc_scss!$C$2:$C$1000 = "completions") * (df_cmhc_scss!$B$2:$B$1000 = federal_req!$J$71), 0), MATCH(federal_req!$F79, df_cmhc_scss!$D$1:$AB$1,0)),"x")} -> x
A80: 2244 | C80: Casual, seasonal or short-term (<1 year) | D80: Census profile | E80: {=IFERROR(INDEX(df_lf!$C$2:$C$1000, MATCH(1, (cover!$C$4 = df_lf!$A$2:$A$1000) * ($A80 = df_lf!$B$2:$B$1000), 0), 0),"x")} -> x | F80: r_total | G80: Completed by tenure | H80: Tenant | I80: CMHC SCSS | J80: {=IFERROR(INDEX(df_cmhc_scss!$D$2:$AB$1000, MATCH(1, (cover!$C$4 = df_cmhc_scss!$A$2:$A$1000) * (df_cmhc_scss!$C$2:$C$1000 = "completions") * (df_cmhc_scss!$B$2:$B$1000 = federal_req!$J$71), 0), MATCH(federal_req!$F80, df_cmhc_scss!$D$1:$AB$1,0)),"x")} -> x
A81: 2245 | C81: Self-employed | D81: Census profile | E81: {=IFERROR(INDEX(df_lf!$C$2:$C$1000, MATCH(1, (cover!$C$4 = df_lf!$A$2:$A$1000) * ($A81 = df_lf!$B$2:$B$1000), 0), 0),"x")} -> x | F81: h_total | H81: Owner | I81: CMHC SCSS | J81: {=IFERROR(INDEX(df_cmhc_scss!$D$2:$AB$1000, MATCH(1, (cover!$C$4 = df_cmhc_scss!$A$2:$A$1000) * (df_cmhc_scss!$C$2:$C$1000 = "completions") * (df_cmhc_scss!$B$2:$B$1000 = federal_req!$J$71), 0), MATCH(federal_req!$F81, df_cmhc_scss!$D$1:$AB$1,0)),"x")} -> x
A82: 2599 | B82: Commuters | C82: Within CSD | D82: Census profile | E82: =IFERROR(INDEX(df_lf!$C$2:$C$1000, MATCH(1, (cover!$C$4 = df_lf!$A$2:$A$1000) * ($A82 = df_lf!$B$2:$B$1000), 0), 0),"x") -> x | F82: co_total | H82: Condo | I82: CMHC SCSS | J82: {=IFERROR(INDEX(df_cmhc_scss!$D$2:$AB$1000, MATCH(1, (cover!$C$4 = df_cmhc_scss!$A$2:$A$1000) * (df_cmhc_scss!$C$2:$C$1000 = "completions") * (df_cmhc_scss!$B$2:$B$1000 = federal_req!$J$71), 0), MATCH(federal_req!$F82, df_cmhc_scss!$D$1:$AB$1,0)),"x")} -> x
A83: 2600 | C83: To different CSD | D83: Census profile | E83: =IFERROR(INDEX(df_lf!$C$2:$C$1000, MATCH(1, (cover!$C$4 = df_lf!$A$2:$A$1000) * ($A83 = df_lf!$B$2:$B$1000), 0), 0),"x") -> x | F83: cp_total | H83: Co-op | I83: CMHC SCSS | J83: {=IFERROR(INDEX(df_cmhc_scss!$D$2:$AB$1000, MATCH(1, (cover!$C$4 = df_cmhc_scss!$A$2:$A$1000) * (df_cmhc_scss!$C$2:$C$1000 = "completions") * (df_cmhc_scss!$B$2:$B$1000 = federal_req!$J$71), 0), MATCH(federal_req!$F83, df_cmhc_scss!$D$1:$AB$1,0)),"x")} -> x
A84: 2601 | C84: To different CD | D84: Census profile | E84: =IFERROR(INDEX(df_lf!$C$2:$C$1000, MATCH(1, (cover!$C$4 = df_lf!$A$2:$A$1000) * ($A84 = df_lf!$B$2:$B$1000), 0), 0),"x") -> x | F84: r_total | G84: Starts by structural type and tenure | H84: Tenant | I84: CMHC SCSS | J84: {=IFERROR(INDEX(df_cmhc_scss!$D$2:$AB$1000, MATCH(1, (cover!$C$4 = df_cmhc_scss!$A$2:$A$1000) * (df_cmhc_scss!$C$2:$C$1000 = "starts") * (df_cmhc_scss!$B$2:$B$1000 = federal_req!$J$71), 0), MATCH(federal_req!$F84, df_cmhc_scss!$D$1:$AB$1,0)),"x")} -> x
A85: 2602 | C85: To another province/territory | D85: Census profile | E85: =IFERROR(INDEX(df_lf!$C$2:$C$1000, MATCH(1, (cover!$C$4 = df_lf!$A$2:$A$1000) * ($A85 = df_lf!$B$2:$B$1000), 0), 0),"x") -> x | F85: h_total | H85: Owner | I85: CMHC SCSS | J85: {=IFERROR(INDEX(df_cmhc_scss!$D$2:$AB$1000, MATCH(1, (cover!$C$4 = df_cmhc_scss!$A$2:$A$1000) * (df_cmhc_scss!$C$2:$C$1000 = "starts") * (df_cmhc_scss!$B$2:$B$1000 = federal_req!$J$71), 0), MATCH(federal_req!$F85, df_cmhc_scss!$D$1:$AB$1,0)),"x")} -> x
A86: 2604 | B86: Commuting mode | C86: Car, truck, or van | D86: Census profile | E86: =IFERROR(INDEX(df_lf!$C$2:$C$1000, MATCH(1, (cover!$C$4 = df_lf!$A$2:$A$1000) * ($A86 = df_lf!$B$2:$B$1000), 0), 0),"x") -> x | F86: co_total | H86: Condo | I86: CMHC SCSS | J86: {=IFERROR(INDEX(df_cmhc_scss!$D$2:$AB$1000, MATCH(1, (cover!$C$4 = df_cmhc_scss!$A$2:$A$1000) * (df_cmhc_scss!$C$2:$C$1000 = "starts") * (df_cmhc_scss!$B$2:$B$1000 = federal_req!$J$71), 0), MATCH(federal_req!$F86, df_cmhc_scss!$D$1:$AB$1,0)),"x")} -> x
A87: 2607 | C87: Public transit | D87: Census profile | E87: =IFERROR(INDEX(df_lf!$C$2:$C$1000, MATCH(1, (cover!$C$4 = df_lf!$A$2:$A$1000) * ($A87 = df_lf!$B$2:$B$1000), 0), 0),"x") -> x | F87: cp_total | H87: Co-op | I87: CMHC SCSS | J87: {=IFERROR(INDEX(df_cmhc_scss!$D$2:$AB$1000, MATCH(1, (cover!$C$4 = df_cmhc_scss!$A$2:$A$1000) * (df_cmhc_scss!$C$2:$C$1000 = "starts") * (df_cmhc_scss!$B$2:$B$1000 = federal_req!$J$71), 0), MATCH(federal_req!$F87, df_cmhc_scss!$D$1:$AB$1,0)),"x")} -> x
A88: 2608 | C88: Walked | D88: Census profile | E88: =IFERROR(INDEX(df_lf!$C$2:$C$1000, MATCH(1, (cover!$C$4 = df_lf!$A$2:$A$1000) * ($A88 = df_lf!$B$2:$B$1000), 0), 0),"x") -> x
A89: 2609 | C89: Bicycle | D89: Census profile | E89: =IFERROR(INDEX(df_lf!$C$2:$C$1000, MATCH(1, (cover!$C$4 = df_lf!$A$2:$A$1000) * ($A89 = df_lf!$B$2:$B$1000), 0), 0),"x") -> x
A90: 2610 | C90: Other method | D90: Census profile | E90: =IFERROR(INDEX(df_lf!$C$2:$C$1000, MATCH(1, (cover!$C$4 = df_lf!$A$2:$A$1000) * ($A90 = df_lf!$B$2:$B$1000), 0), 0),"x") -> x | G90: Table 3.6.4: Households in Core Housing Need
G91: Characteristic | H91: Data | I91: Source | J91: Value | L91: Total | M91: Owner | N91: Renter
G92: Affordability – owner / tenant HH | H92: Total | I92: Table 98-10-0624 | J92: =IFERROR(MROUND(J93*$O$96,5),"x") -> x | L92: =hh!D11 -> #N/A | M92: =hh!E11 -> #N/A | N92: =hh!F11 -> #N/A
H93: Percentage | I93: Table 98-10-0624 | J93: =need!C109 -> x
G94: Affordability – owner / tenant HH in core need | H94: Total | I94: HART | J94: =IFERROR(IF(O107=0,"x",O107),"x") -> x
H95: Percentage | I95: HART | J95: =IFERROR(IF(O107/O97=0,"x",O107/O97),"x") -> x | O95: total | P95: owner | Q95: renter
G96: Affordability – tenant HH | H96: Total | I96: Table 98-10-0624 | J96: =IFERROR(MROUND(J97*$Q$96,5),"x") -> x | L96: Total private households | O96: {=IFERROR(INDEX(df_chn_hart!$D$2:$M$1000, MATCH(1, (cover!$C$4 = df_chn_hart!$A$2:$A$1000) * ($L96 = df_chn_hart!$C$2:$C$1000) * (df_chn_hart!$B$2:$B$1000 = "Total private households"), 0), MATCH(O$95, df_chn_hart!$D$1:$M$1, 0)),"x")} -> x | P96: {=IFERROR(INDEX(df_chn_hart!$D$2:$M$1000, MATCH(1, (cover!$C$4 = df_chn_hart!$A$2:$A$1000) * ($L96 = df_chn_hart!$C$2:$C$1000) * (df_chn_hart!$B$2:$B$1000 = "Total private households"), 0), MATCH(P$95, df_chn_hart!$D$1:$M$1, 0)),"x")} -> x | Q96: {=IFERROR(INDEX(df_chn_hart!$D$2:$M$1000, MATCH(1, (cover!$C$4 = df_chn_hart!$A$2:$A$1000) * ($L96 = df_chn_hart!$C$2:$C$1000) * (df_chn_hart!$B$2:$B$1000 = "Total private households"), 0), MATCH(Q$95, df_chn_hart!$D$1:$M$1, 0)),"x")} -> x
H97: Percentage | I97: Table 98-10-0624 | J97: =need!E109 -> x | L97: Examined CHN | O97: {=IFERROR(INDEX(df_chn_hart!$D$2:$M$1000, MATCH(1, (cover!$C$4 = df_chn_hart!$A$2:$A$1000) * ($L97 = df_chn_hart!$C$2:$C$1000) * (df_chn_hart!$B$2:$B$1000 = "Total private households"), 0), MATCH(O$95, df_chn_hart!$D$1:$M$1, 0)),"x")} -> x | P97: {=IFERROR(INDEX(df_chn_hart!$D$2:$M$1000, MATCH(1, (cover!$C$4 = df_chn_hart!$A$2:$A$1000) * ($L97 = df_chn_hart!$C$2:$C$1000) * (df_chn_hart!$B$2:$B$1000 = "Total private households"), 0), MATCH(P$95, df_chn_hart!$D$1:$M$1, 0)),"x")} -> x | Q97: {=IFERROR(INDEX(df_chn_hart!$D$2:$M$1000, MATCH(1, (cover!$C$4 = df_chn_hart!$A$2:$A$1000) * ($L97 = df_chn_hart!$C$2:$C$1000) * (df_chn_hart!$B$2:$B$1000 = "Total private households"), 0), MATCH(Q$95, df_chn_hart!$D$1:$M$1, 0)),"x")} -> x
G98: Affordability – tenant HH in core need | H98: Total | I98: HART | J98: =IFERROR(IF(Q107=0,"x",Q107),"x") -> x | L98: In CHN | O98: {=IFERROR(INDEX(df_chn_hart!$D$2:$M$1000, MATCH(1, (cover!$C$4 = df_chn_hart!$A$2:$A$1000) * ($L98 = df_chn_hart!$C$2:$C$1000) * (df_chn_hart!$B$2:$B$1000 = "Total private households"), 0), MATCH(O$95, df_chn_hart!$D$1:$M$1, 0)),"x")} -> x | P98: {=IFERROR(INDEX(df_chn_hart!$D$2:$M$1000, MATCH(1, (cover!$C$4 = df_chn_hart!$A$2:$A$1000) * ($L98 = df_chn_hart!$C$2:$C$1000) * (df_chn_hart!$B$2:$B$1000 = "Total private households"), 0), MATCH(P$95, df_chn_hart!$D$1:$M$1, 0)),"x")} -> x | Q98: {=IFERROR(INDEX(df_chn_hart!$D$2:$M$1000, MATCH(1, (cover!$C$4 = df_chn_hart!$A$2:$A$1000) * ($L98 = df_chn_hart!$C$2:$C$1000) * (df_chn_hart!$B$2:$B$1000 = "Total private households"), 0), MATCH(Q$95, df_chn_hart!$D$1:$M$1, 0)),"x")} -> x
H99: Percentage | I99: HART | J99: =IFERROR(IF(Q107/Q97=0,"x",Q107/Q97),"x") -> x | L99: CHN: below one standard | O99: {=IFERROR(INDEX(df_chn_hart!$D$2:$M$1000, MATCH(1, (cover!$C$4 = df_chn_hart!$A$2:$A$1000) * ($L99 = df_chn_hart!$C$2:$C$1000) * (df_chn_hart!$B$2:$B$1000 = "Total private households"), 0), MATCH(O$95, df_chn_hart!$D$1:$M$1, 0)),"x")} -> x | P99: {=IFERROR(INDEX(df_chn_hart!$D$2:$M$1000, MATCH(1, (cover!$C$4 = df_chn_hart!$A$2:$A$1000) * ($L99 = df_chn_hart!$C$2:$C$1000) * (df_chn_hart!$B$2:$B$1000 = "Total private households"), 0), MATCH(P$95, df_chn_hart!$D$1:$M$1, 0)),"x")} -> x | Q99: {=IFERROR(INDEX(df_chn_hart!$D$2:$M$1000, MATCH(1, (cover!$C$4 = df_chn_hart!$A$2:$A$1000) * ($L99 = df_chn_hart!$C$2:$C$1000) * (df_chn_hart!$B$2:$B$1000 = "Total private households"), 0), MATCH(Q$95, df_chn_hart!$D$1:$M$1, 0)),"x")} -> x
G100: Affordability – owner HH | H100: Total | I100: Table 98-10-0624 | J100: =IFERROR(MROUND(J101*$P$96,5),"x") -> x | L100: CHN: below affordability standard only | O100: {=IFERROR(INDEX(df_chn_hart!$D$2:$M$1000, MATCH(1, (cover!$C$4 = df_chn_hart!$A$2:$A$1000) * ($L100 = df_chn_hart!$C$2:$C$1000) * (df_chn_hart!$B$2:$B$1000 = "Total private households"), 0), MATCH(O$95, df_chn_hart!$D$1:$M$1, 0)),"x")} -> x | P100: {=IFERROR(INDEX(df_chn_hart!$D$2:$M$1000, MATCH(1, (cover!$C$4 = df_chn_hart!$A$2:$A$1000) * ($L100 = df_chn_hart!$C$2:$C$1000) * (df_chn_hart!$B$2:$B$1000 = "Total private households"), 0), MATCH(P$95, df_chn_hart!$D$1:$M$1, 0)),"x")} -> x | Q100: {=IFERROR(INDEX(df_chn_hart!$D$2:$M$1000, MATCH(1, (cover!$C$4 = df_chn_hart!$A$2:$A$1000) * ($L100 = df_chn_hart!$C$2:$C$1000) * (df_chn_hart!$B$2:$B$1000 = "Total private households"), 0), MATCH(Q$95, df_chn_hart!$D$1:$M$1, 0)),"x")} -> x
H101: Percentage | I101: Table 98-10-0624 | J101: =need!D109 -> x | L101: CHN: below adequacy standard only | O101: {=IFERROR(INDEX(df_chn_hart!$D$2:$M$1000, MATCH(1, (cover!$C$4 = df_chn_hart!$A$2:$A$1000) * ($L101 = df_chn_hart!$C$2:$C$1000) * (df_chn_hart!$B$2:$B$1000 = "Total private households"), 0), MATCH(O$95, df_chn_hart!$D$1:$M$1, 0)),"x")} -> x | P101: {=IFERROR(INDEX(df_chn_hart!$D$2:$M$1000, MATCH(1, (cover!$C$4 = df_chn_hart!$A$2:$A$1000) * ($L101 = df_chn_hart!$C$2:$C$1000) * (df_chn_hart!$B$2:$B$1000 = "Total private households"), 0), MATCH(P$95, df_chn_hart!$D$1:$M$1, 0)),"x")} -> x | Q101: {=IFERROR(INDEX(df_chn_hart!$D$2:$M$1000, MATCH(1, (cover!$C$4 = df_chn_hart!$A$2:$A$1000) * ($L101 = df_chn_hart!$C$2:$C$1000) * (df_chn_hart!$B$2:$B$1000 = "Total private households"), 0), MATCH(Q$95, df_chn_hart!$D$1:$M$1, 0)),"x")} -> x
...

Sheet popn_now
A1: CSD | B1: CD | C1: PR | D1: Scenario
A2: =df_geo!A2 -> 1000000 | B2: =_xlfn.NUMBERVALUE(LEFT(A2,4)) -> 1000 | C2: =_xlfn.NUMBERVALUE(LEFT(B2,2)) -> 10 | D2: =popn_fut!D2 -> #N/A
B4: HISTORICAL POPULATION
B6: DATA COLLECTION
B8: Estimates + Census (unadjusted) | I8: Estimates + Census (adjusted)
C10: CSD | F10: CD | J10: CSD | M10: CD | O10: PR
B11: Age group | C11: 2016 | D11: 2021 | E11: 2025 | F11: 2016 | G11: 2021 | I11: Age group | J11: 2016 | K11: 2021 | L11: 2025 | M11: 2021 | N11: 2025 | O11: 2021 | P11: 2025
A12: 8 | B12: Total | C12: {=INDEX(df_pop!$C$2:$C$100, MATCH(1, (df_pop!$B$2:$B$100 = $A12) * (df_pop!$E$2:$E$100 = C$11) * (df_pop!$A$2:$A$100 = $A$2), 0), 0)} -> #N/A | D12: {=INDEX(df_pop!$C$2:$C$10000, MATCH(1, (df_pop!$B$2:$B$10000 = $A12) * (df_pop!$E$2:$E$10000 = D$11) * (df_pop!$A$2:$A$10000 = $A$2), 0), 0)} -> #N/A | E12: {=INDEX(df_proj!$E$2:$AD$1000, MATCH(1, ($A$2 = df_proj!$A$2:$A$1000) * (df_proj!$B$2:$B$1000 = $B12) * (df_proj!$C$2:$C$1000 = $D$2), 0), MATCH(TEXT(E$11, "####"), df_proj!$E$1:$AD$1,0))} -> #N/A | F12: {=INDEX(df_pop!$C$2:$C$10000, MATCH(1, (df_pop!$B$2:$B$10000 = $A12) * (df_pop!$E$2:$E$10000 = F$11) * (df_pop!$A$2:$A$10000 = $B$2), 0), 0)} -> #N/A | G12: {=INDEX(df_pop!$C$2:$C$10000, MATCH(1, (df_pop!$B$2:$B$10000 = $A12) * (df_pop!$E$2:$E$10000 = G$11) * (df_pop!$A$2:$A$10000 = $B$2), 0), 0)} -> #N/A | H12: 1 | I12: Total | J12: =INDEX(df_est_csd!$C$2:$BA$10, MATCH($A$2, df_est_csd!$B$2:$B$10, 0), MATCH(TEXT(C$11, "####"), df_est_csd!$C$1:$BA$1, 0)) -> #N/A | K12: =INDEX(df_est_csd!$C$2:$BA$10, MATCH($A$2, df_est_csd!$B$2:$B$10, 0), MATCH(TEXT(D$11, "####"), df_est_csd!$C$1:$BA$1, 0)) -> #N/A | L12: =IFERROR(INDEX(df_proj!$F$2:$AE$1000, MATCH(1, ($A$2 = df_proj!$B$2:$B$1000) * (df_proj!$E$2:$E$1000 = $H12) * (df_proj!$D$2:$D$1000 = $D$2), 0), MATCH(TEXT(E$11, "####"), df_proj!$F$1:$AE$1,0)),popn_fut!C81) -> #N/A | M12: =INDEX(df_est_cd!$D$2:$AB$100, MATCH("Total", df_est_cd!$C$2:$C$100, 0), MATCH(TEXT(M$11, "####"), df_est_cd!$D$1:$AB$1, 0)) -> 38239864 | N12: =INDEX(df_est_cd!$D$2:$AB$100, MATCH("Total", df_est_cd!$C$2:$C$100, 0), MATCH(TEXT(N$11, "####"), df_est_cd!$D$1:$AB$1, 0)) -> 41651653 | O12: =INDEX(df_est_pr!$D$2:$AB$100, MATCH("Total", df_est_pr!$C$2:$C$100, 0), MATCH(TEXT(O$11, "####"), df_est_pr!$D$1:$AB$1, 0)) -> #N/A | P12: =INDEX(df_est_pr!$D$2:$AB$100, MATCH("Total", df_est_pr!$C$2:$C$100, 0), MATCH(TEXT(P$11, "####"), df_est_pr!$D$1:$AB$1, 0)) -> #N/A
A13: 10 | B13: 0 to 4 | C13: {=INDEX(df_pop!$C$2:$C$100, MATCH(1, (df_pop!$B$2:$B$100 = $A13) * (df_pop!$E$2:$E$100 = C$11) * (df_pop!$A$2:$A$100 = $A$2), 0), 0)} -> #N/A | D13: {=INDEX(df_pop!$C$2:$C$1000, MATCH(1, (df_pop!$B$2:$B$1000 = $A13) * (df_pop!$E$2:$E$1000 = D$11) * (df_pop!$A$2:$A$1000 = $A$2), 0), 0)} -> #N/A | E13: {=INDEX(df_proj!$E$2:$AD$1000, MATCH(1, ($A$2 = df_proj!$A$2:$A$1000) * (df_proj!$B$2:$B$1000 = $B13) * (df_proj!$C$2:$C$1000 = $D$2), 0), MATCH(TEXT(E$11, "####"), df_proj!$E$1:$AD$1,0))} -> #N/A | F13: {=INDEX(df_pop!$C$2:$C$10000, MATCH(1, (df_pop!$B$2:$B$10000 = $A13) * (df_pop!$E$2:$E$10000 = F$11) * (df_pop!$A$2:$A$10000 = $B$2), 0), 0)} -> #N/A | G13: {=INDEX(df_pop!$C$2:$C$10000, MATCH(1, (df_pop!$B$2:$B$10000 = $A13) * (df_pop!$E$2:$E$10000 = G$11) * (df_pop!$A$2:$A$10000 = $B$2), 0), 0)} -> #N/A | H13: 2 | I13: 0 to 4 | J13: =ROUND(J$12/C$12*C13,0) -> #N/A | K13: =ROUND(K$12/D$12*D13,0) -> #N/A | L13: =IFERROR(INDEX(df_proj!$F$2:$AE$1000, MATCH(1, ($A$2 = df_proj!$B$2:$B$1000) * (df_proj!$E$2:$E$1000 = $H13) * (df_proj!$D$2:$D$1000 = $D$2), 0), MATCH(TEXT(E$11, "####"), df_proj!$F$1:$AE$1,0)),popn_fut!C82) -> #N/A | M13: =INDEX(df_est_cd!$D$2:$AB$100, MATCH(TEXT($Q13 * 5 + 4, "####"), df_est_cd!$C$2:$C$100, 0), MATCH(TEXT(M$11, "####"), df_est_cd!$D$1:$AB$1, 0)) + INDEX(df_est_cd!$D$2:$AB$100, MATCH(TEXT($Q13 * 5 + 3, "####"), df_est_cd!$C$2:$C$100, 0), MATCH(TEXT(M$11, "####"), df_est_cd!$D$1:$AB$1, 0)) + INDEX(df_est_cd!$D$2:$AB$100, MATCH(TEXT($Q13 * 5 + 2, "####"), df_est_cd!$C$2:$C$100, 0), MATCH(TEXT(M$11, "####"), df_est_cd!$D$1:$AB$1, 0)) + INDEX(df_est_cd!$D$2:$AB$100, MATCH(TEXT($Q13 * 5 + 1, "####"), df_est_cd!$C$2:$C$100, 0), MATCH(TEXT(M$11, "####"), df_est_cd!$D$1:$AB$1, 0)) + INDEX(df_est_cd!$D$2:$AB$100, MATCH("0", df_est_cd!$C$2:$C$100, 0), MATCH(TEXT(M$11, "####"), df_est_cd!$D$1:$AB$1, 0)) -> 1902883 | N13: =INDEX(df_est_cd!$D$2:$AB$100, MATCH(TEXT($Q13 * 5 + 4, "####"), df_est_cd!$C$2:$C$100, 0), MATCH(TEXT(N$11, "####"), df_est_cd!$D$1:$AB$1, 0)) + INDEX(df_est_cd!$D$2:$AB$100, MATCH(TEXT($Q13 * 5 + 3, "####"), df_est_cd!$C$2:$C$100, 0), MATCH(TEXT(N$11, "####"), df_est_cd!$D$1:$AB$1, 0)) + INDEX(df_est_cd!$D$2:$AB$100, MATCH(TEXT($Q13 * 5 + 2, "####"), df_est_cd!$C$2:$C$100, 0), MATCH(TEXT(N$11, "####"), df_est_cd!$D$1:$AB$1, 0)) + INDEX(df_est_cd!$D$2:$AB$100, MATCH(TEXT($Q13 * 5 + 1, "####"), df_est_cd!$C$2:$C$100, 0), MATCH(TEXT(N$11, "####"), df_est_cd!$D$1:$AB$1, 0)) + INDEX(df_est_cd!$D$2:$AB$100, MATCH("0", df_est_cd!$C$2:$C$100, 0), MATCH(TEXT(N$11, "####"), df_est_cd!$D$1:$AB$1, 0)) -> 1871184 | O13: =INDEX(df_est_pr!$D$2:$AB$100, MATCH(TEXT($Q13 * 5 + 4, "####"), df_est_pr!$C$2:$C$100, 0), MATCH(TEXT(O$11, "####"), df_est_pr!$D$1:$AB$1, 0)) + INDEX(df_est_pr!$D$2:$AB$100, MATCH(TEXT($Q13 * 5 + 3, "####"), df_est_pr!$C$2:$C$100, 0), MATCH(TEXT(O$11, "####"), df_est_pr!$D$1:$AB$1, 0)) + INDEX(df_est_pr!$D$2:$AB$100, MATCH(TEXT($Q13 * 5 + 2, "####"), df_est_pr!$C$2:$C$100, 0), MATCH(TEXT(O$11, "####"), df_est_pr!$D$1:$AB$1, 0)) + INDEX(df_est_pr!$D$2:$AB$100, MATCH(TEXT($Q13 * 5 + 1, "####"), df_est_pr!$C$2:$C$100, 0), MATCH(TEXT(O$11, "####"), df_est_pr!$D$1:$AB$1, 0)) + INDEX(df_est_pr!$D$2:$AB$100, MATCH("0", df_est_pr!$C$2:$C$100, 0), MATCH(TEXT(O$11, "####"), df_est_pr!$D$1:$AB$1, 0)) -> #N/A | P13: =INDEX(df_est_pr!$D$2:$AB$100, MATCH(TEXT($Q13 * 5 + 4, "####"), df_est_pr!$C$2:$C$100, 0), MATCH(TEXT(P$11, "####"), df_est_pr!$D$1:$AB$1, 0)) + INDEX(df_est_pr!$D$2:$AB$100, MATCH(TEXT($Q13 * 5 + 3, "####"), df_est_pr!$C$2:$C$100, 0), MATCH(TEXT(P$11, "####"), df_est_pr!$D$1:$AB$1, 0)) + INDEX(df_est_pr!$D$2:$AB$100, MATCH(TEXT($Q13 * 5 + 2, "####"), df_est_pr!$C$2:$C$100, 0), MATCH(TEXT(P$11, "####"), df_est_pr!$D$1:$AB$1, 0)) + INDEX(df_est_pr!$D$2:$AB$100, MATCH(TEXT($Q13 * 5 + 1, "####"), df_est_pr!$C$2:$C$100, 0), MATCH(TEXT(P$11, "####"), df_est_pr!$D$1:$AB$1, 0)) + INDEX(df_est_pr!$D$2:$AB$100, MATCH("0", df_est_pr!$C$2:$C$100, 0), MATCH(TEXT(P$11, "####"), df_est_pr!$D$1:$AB$1, 0)) -> #N/A | Q13: 0
A14: 11 | B14: 5 to 9 | C14: {=INDEX(df_pop!$C$2:$C$100, MATCH(1, (df_pop!$B$2:$B$100 = $A14) * (df_pop!$E$2:$E$100 = C$11) * (df_pop!$A$2:$A$100 = $A$2), 0), 0)} -> #N/A | D14: {=INDEX(df_pop!$C$2:$C$1000, MATCH(1, (df_pop!$B$2:$B$1000 = $A14) * (df_pop!$E$2:$E$1000 = D$11) * (df_pop!$A$2:$A$1000 = $A$2), 0), 0)} -> #N/A | E14: {=INDEX(df_proj!$E$2:$AD$1000, MATCH(1, ($A$2 = df_proj!$A$2:$A$1000) * (df_proj!$B$2:$B$1000 = $B14) * (df_proj!$C$2:$C$1000 = $D$2), 0), MATCH(TEXT(E$11, "####"), df_proj!$E$1:$AD$1,0))} -> #N/A | F14: {=INDEX(df_pop!$C$2:$C$10000, MATCH(1, (df_pop!$B$2:$B$10000 = $A14) * (df_pop!$E$2:$E$10000 = F$11) * (df_pop!$A$2:$A$10000 = $B$2), 0), 0)} -> #N/A | G14: {=INDEX(df_pop!$C$2:$C$10000, MATCH(1, (df_pop!$B$2:$B$10000 = $A14) * (df_pop!$E$2:$E$10000 = G$11) * (df_pop!$A$2:$A$10000 = $B$2), 0), 0)} -> #N/A | H14: 3 | I14: 5 to 9 | J14: =ROUND(J$12/C$12*C14,0) -> #N/A | K14: =ROUND(K$12/D$12*D14,0) -> #N/A | L14: =IFERROR(INDEX(df_proj!$F$2:$AE$1000, MATCH(1, ($A$2 = df_proj!$B$2:$B$1000) * (df_proj!$E$2:$E$1000 = $H14) * (df_proj!$D$2:$D$1000 = $D$2), 0), MATCH(TEXT(E$11, "####"), df_proj!$F$1:$AE$1,0)),popn_fut!C83) -> #N/A | M14: =INDEX(df_est_cd!$D$2:$AB$100, MATCH(TEXT($Q14 * 5 + 4, "####"), df_est_cd!$C$2:$C$100, 0), MATCH(TEXT(M$11, "####"), df_est_cd!$D$1:$AB$1, 0)) + INDEX(df_est_cd!$D$2:$AB$100, MATCH(TEXT($Q14 * 5 + 3, "####"), df_est_cd!$C$2:$C$100, 0), MATCH(TEXT(M$11, "####"), df_est_cd!$D$1:$AB$1, 0)) + INDEX(df_est_cd!$D$2:$AB$100, MATCH(TEXT($Q14 * 5 + 2, "####"), df_est_cd!$C$2:$C$100, 0), MATCH(TEXT(M$11, "####"), df_est_cd!$D$1:$AB$1, 0)) + INDEX(df_est_cd!$D$2:$AB$100, MATCH(TEXT($Q14 * 5 + 1, "####"), df_est_cd!$C$2:$C$100, 0), MATCH(TEXT(M$11, "####"), df_est_cd!$D$1:$AB$1, 0)) + INDEX(df_est_cd!$D$2:$AB$100, MATCH(TEXT($Q14 * 5, "####"), df_est_cd!$C$2:$C$100, 0), MATCH(TEXT(M$11, "####"), df_est_cd!$D$1:$AB$1, 0)) -> 2072565 | N14: =INDEX(df_est_cd!$D$2:$AB$100, MATCH(TEXT($Q14 * 5 + 4, "####"), df_est_cd!$C$2:$C$100, 0), MATCH(TEXT(N$11, "####"), df_est_cd!$D$1:$AB$1, 0)) + INDEX(df_est_cd!$D$2:$AB$100, MATCH(TEXT($Q14 * 5 + 3, "####"), df_est_cd!$C$2:$C$100, 0), MATCH(TEXT(N$11, "####"), df_est_cd!$D$1:$AB$1, 0)) + INDEX(df_est_cd!$D$2:$AB$100, MATCH(TEXT($Q14 * 5 + 2, "####"), df_est_cd!$C$2:$C$100, 0), MATCH(TEXT(N$11, "####"), df_est_cd!$D$1:$AB$1, 0)) + INDEX(df_est_cd!$D$2:$AB$100, MATCH(TEXT($Q14 * 5 + 1, "####"), df_est_cd!$C$2:$C$100, 0), MATCH(TEXT(N$11, "####"), df_est_cd!$D$1:$AB$1, 0)) + INDEX(df_est_cd!$D$2:$AB$100, MATCH(TEXT($Q14 * 5, "####"), df_est_cd!$C$2:$C$100, 0), MATCH(TEXT(N$11, "####"), df_est_cd!$D$1:$AB$1, 0)) -> 2138350 | O14: =INDEX(df_est_pr!$D$2:$AB$100, MATCH(TEXT($Q14 * 5 + 4, "####"), df_est_pr!$C$2:$C$100, 0), MATCH(TEXT(O$11, "####"), df_est_pr!$D$1:$AB$1, 0)) + INDEX(df_est_pr!$D$2:$AB$100, MATCH(TEXT($Q14 * 5 + 3, "####"), df_est_pr!$C$2:$C$100, 0), MATCH(TEXT(O$11, "####"), df_est_pr!$D$1:$AB$1, 0)) + INDEX(df_est_pr!$D$2:$AB$100, MATCH(TEXT($Q14 * 5 + 2, "####"), df_est_pr!$C$2:$C$100, 0), MATCH(TEXT(O$11, "####"), df_est_pr!$D$1:$AB$1, 0)) + INDEX(df_est_pr!$D$2:$AB$100, MATCH(TEXT($Q14 * 5 + 1, "####"), df_est_pr!$C$2:$C$100, 0), MATCH(TEXT(O$11, "####"), df_est_pr!$D$1:$AB$1, 0)) + INDEX(df_est_pr!$D$2:$AB$100, MATCH(TEXT($Q14 * 5, "####"), df_est_pr!$C$2:$C$100, 0), MATCH(TEXT(O$11, "####"), df_est_pr!$D$1:$AB$1, 0)) -> #N/A | P14: =INDEX(df_est_pr!$D$2:$AB$100, MATCH(TEXT($Q14 * 5 + 4, "####"), df_est_pr!$C$2:$C$100, 0), MATCH(TEXT(P$11, "####"), df_est_pr!$D$1:$AB$1, 0)) + INDEX(df_est_pr!$D$2:$AB$100, MATCH(TEXT($Q14 * 5 + 3, "####"), df_est_pr!$C$2:$C$100, 0), MATCH(TEXT(P$11, "####"), df_est_pr!$D$1:$AB$1, 0)) + INDEX(df_est_pr!$D$2:$AB$100, MATCH(TEXT($Q14 * 5 + 2, "####"), df_est_pr!$C$2:$C$100, 0), MATCH(TEXT(P$11, "####"), df_est_pr!$D$1:$AB$1, 0)) + INDEX(df_est_pr!$D$2:$AB$100, MATCH(TEXT($Q14 * 5 + 1, "####"), df_est_pr!$C$2:$C$100, 0), MATCH(TEXT(P$11, "####"), df_est_pr!$D$1:$AB$1, 0)) + INDEX(df_est_pr!$D$2:$AB$100, MATCH(TEXT($Q14 * 5, "####"), df_est_pr!$C$2:$C$100, 0), MATCH(TEXT(P$11, "####"), df_est_pr!$D$1:$AB$1, 0)) -> #N/A | Q14: 1
A15: 12 | B15: 10 to 14 | C15: {=INDEX(df_pop!$C$2:$C$100, MATCH(1, (df_pop!$B$2:$B$100 = $A15) * (df_pop!$E$2:$E$100 = C$11) * (df_pop!$A$2:$A$100 = $A$2), 0), 0)} -> #N/A | D15: {=INDEX(df_pop!$C$2:$C$1000, MATCH(1, (df_pop!$B$2:$B$1000 = $A15) * (df_pop!$E$2:$E$1000 = D$11) * (df_pop!$A$2:$A$1000 = $A$2), 0), 0)} -> #N/A | E15: {=INDEX(df_proj!$E$2:$AD$1000, MATCH(1, ($A$2 = df_proj!$A$2:$A$1000) * (df_proj!$B$2:$B$1000 = $B15) * (df_proj!$C$2:$C$1000 = $D$2), 0), MATCH(TEXT(E$11, "####"), df_proj!$E$1:$AD$1,0))} -> #N/A | F15: {=INDEX(df_pop!$C$2:$C$10000, MATCH(1, (df_pop!$B$2:$B$10000 = $A15) * (df_pop!$E$2:$E$10000 = F$11) * (df_pop!$A$2:$A$10000 = $B$2), 0), 0)} -> #N/A | G15: {=INDEX(df_pop!$C$2:$C$10000, MATCH(1, (df_pop!$B$2:$B$10000 = $A15) * (df_pop!$E$2:$E$10000 = G$11) * (df_pop!$A$2:$A$10000 = $B$2), 0), 0)} -> #N/A | H15: 4 | I15: 10 to 14 | J15: =ROUND(J$12/C$12*C15,0) -> #N/A | K15: =ROUND(K$12/D$12*D15,0) -> #N/A | L15: =IFERROR(INDEX(df_proj!$F$2:$AE$1000, MATCH(1, ($A$2 = df_proj!$B$2:$B$1000) * (df_proj!$E$2:$E$1000 = $H15) * (df_proj!$D$2:$D$1000 = $D$2), 0), MATCH(TEXT(E$11, "####"), df_proj!$F$1:$AE$1,0)),popn_fut!C84) -> #N/A | M15: =INDEX(df_est_cd!$D$2:$AB$100, MATCH(TEXT($Q15 * 5 + 4, "####"), df_est_cd!$C$2:$C$100, 0), MATCH(TEXT(M$11, "####"), df_est_cd!$D$1:$AB$1, 0)) + INDEX(df_est_cd!$D$2:$AB$100, MATCH(TEXT($Q15 * 5 + 3, "####"), df_est_cd!$C$2:$C$100, 0), MATCH(TEXT(M$11, "####"), df_est_cd!$D$1:$AB$1, 0)) + INDEX(df_est_cd!$D$2:$AB$100, MATCH(TEXT($Q15 * 5 + 2, "####"), df_est_cd!$C$2:$C$100, 0), MATCH(TEXT(M$11, "####"), df_est_cd!$D$1:$AB$1, 0)) + INDEX(df_est_cd!$D$2:$AB$100, MATCH(TEXT($Q15 * 5 + 1, "####"), df_est_cd!$C$2:$C$100, 0), MATCH(TEXT(M$11, "####"), df_est_cd!$D$1:$AB$1, 0)) + INDEX(df_est_cd!$D$2:$AB$100, MATCH(TEXT($Q15 * 5, "####"), df_est_cd!$C$2:$C$100, 0), MATCH(TEXT(M$11, "####"), df_est_cd!$D$1:$AB$1, 0)) -> 2114016 | N15: =INDEX(df_est_cd!$D$2:$AB$100, MATCH(TEXT($Q15 * 5 + 4, "####"), df_est_cd!$C$2:$C$100, 0), MATCH(TEXT(N$11, "####"), df_est_cd!$D$1:$AB$1, 0)) + INDEX(df_est_cd!$D$2:$AB$100, MATCH(TEXT($Q15 * 5 + 3, "####"), df_est_cd!$C$2:$C$100, 0), MATCH(TEXT(N$11, "####"), df_est_cd!$D$1:$AB$1, 0)) + INDEX(df_est_cd!$D$2:$AB$100, MATCH(TEXT($Q15 * 5 + 2, "####"), df_est_cd!$C$2:$C$100, 0), MATCH(TEXT(N$11, "####"), df_est_cd!$D$1:$AB$1, 0)) + INDEX(df_est_cd!$D$2:$AB$100, MATCH(TEXT($Q15 * 5 + 1, "####"), df_est_cd!$C$2:$C$100, 0), MATCH(TEXT(N$11, "####"), df_est_cd!$D$1:$AB$1, 0)) + INDEX(df_est_cd!$D$2:$AB$100, MATCH(TEXT($Q15 * 5, "####"), df_est_cd!$C$2:$C$100, 0), MATCH(TEXT(N$11, "####"), df_est_cd!$D$1:$AB$1, 0)) -> 2251628 | O15: =INDEX(df_est_pr!$D$2:$AB$100, MATCH(TEXT($Q15 * 5 + 4, "####"), df_est_pr!$C$2:$C$100, 0), MATCH(TEXT(O$11, "####"), df_est_pr!$D$1:$AB$1, 0)) + INDEX(df_est_pr!$D$2:$AB$100, MATCH(TEXT($Q15 * 5 + 3, "####"), df_est_pr!$C$2:$C$100, 0), MATCH(TEXT(O$11, "####"), df_est_pr!$D$1:$AB$1, 0)) + INDEX(df_est_pr!$D$2:$AB$100, MATCH(TEXT($Q15 * 5 + 2, "####"), df_est_pr!$C$2:$C$100, 0), MATCH(TEXT(O$11, "####"), df_est_pr!$D$1:$AB$1, 0)) + INDEX(df_est_pr!$D$2:$AB$100, MATCH(TEXT($Q15 * 5 + 1, "####"), df_est_pr!$C$2:$C$100, 0), MATCH(TEXT(O$11, "####"), df_est_pr!$D$1:$AB$1, 0)) + INDEX(df_est_pr!$D$2:$AB$100, MATCH(TEXT($Q15 * 5, "####"), df_est_pr!$C$2:$C$100, 0), MATCH(TEXT(O$11, "####"), df_est_pr!$D$1:$AB$1, 0)) -> #N/A | P15: =INDEX(df_est_pr!$D$2:$AB$100, MATCH(TEXT($Q15 * 5 + 4, "####"), df_est_pr!$C$2:$C$100, 0), MATCH(TEXT(P$11, "####"), df_est_pr!$D$1:$AB$1, 0)) + INDEX(df_est_pr!$D$2:$AB$100, MATCH(TEXT($Q15 * 5 + 3, "####"), df_est_pr!$C$2:$C$100, 0), MATCH(TEXT(P$11, "####"), df_est_pr!$D$1:$AB$1, 0)) + INDEX(df_est_pr!$D$2:$AB$100, MATCH(TEXT($Q15 * 5 + 2, "####"), df_est_pr!$C$2:$C$100, 0), MATCH(TEXT(P$11, "####"), df_est_pr!$D$1:$AB$1, 0)) + INDEX(df_est_pr!$D$2:$AB$100, MATCH(TEXT($Q15 * 5 + 1, "####"), df_est_pr!$C$2:$C$100, 0), MATCH(TEXT(P$11, "####"), df_est_pr!$D$1:$AB$1, 0)) + INDEX(df_est_pr!$D$2:$AB$100, MATCH(TEXT($Q15 * 5, "####"), df_est_pr!$C$2:$C$100, 0), MATCH(TEXT(P$11, "####"), df_est_pr!$D$1:$AB$1, 0)) -> #N/A | Q15: 2
A16: 14 | B16: 15 to 19 | C16: {=INDEX(df_pop!$C$2:$C$100, MATCH(1, (df_pop!$B$2:$B$100 = $A16) * (df_pop!$E$2:$E$100 = C$11) * (df_pop!$A$2:$A$100 = $A$2), 0), 0)} -> #N/A | D16: {=INDEX(df_pop!$C$2:$C$1000, MATCH(1, (df_pop!$B$2:$B$1000 = $A16) * (df_pop!$E$2:$E$1000 = D$11) * (df_pop!$A$2:$A$1000 = $A$2), 0), 0)} -> #N/A | E16: {=INDEX(df_proj!$E$2:$AD$1000, MATCH(1, ($A$2 = df_proj!$A$2:$A$1000) * (df_proj!$B$2:$B$1000 = $B16) * (df_proj!$C$2:$C$1000 = $D$2), 0), MATCH(TEXT(E$11, "####"), df_proj!$E$1:$AD$1,0))} -> #N/A | F16: {=INDEX(df_pop!$C$2:$C$10000, MATCH(1, (df_pop!$B$2:$B$10000 = $A16) * (df_pop!$E$2:$E$10000 = F$11) * (df_pop!$A$2:$A$10000 = $B$2), 0), 0)} -> #N/A | G16: {=INDEX(df_pop!$C$2:$C$10000, MATCH(1, (df_pop!$B$2:$B$10000 = $A16) * (df_pop!$E$2:$E$10000 = G$11) * (df_pop!$A$2:$A$10000 = $B$2), 0), 0)} -> #N/A | H16: 5 | I16: 15 to 19 | J16: =ROUND(J$12/C$12*C16,0) -> #N/A | K16: =ROUND(K$12/D$12*D16,0) -> #N/A | L16: =IFERROR(INDEX(df_proj!$F$2:$AE$1000, MATCH(1, ($A$2 = df_proj!$B$2:$B$1000) * (df_proj!$E$2:$E$1000 = $H16) * (df_proj!$D$2:$D$1000 = $D$2), 0), MATCH(TEXT(E$11, "####"), df_proj!$F$1:$AE$1,0)),popn_fut!C85) -> #N/A | M16: =INDEX(df_est_cd!$D$2:$AB$100, MATCH(TEXT($Q16 * 5 + 4, "####"), df_est_cd!$C$2:$C$100, 0), MATCH(TEXT(M$11, "####"), df_est_cd!$D$1:$AB$1, 0)) + INDEX(df_est_cd!$D$2:$AB$100, MATCH(TEXT($Q16 * 5 + 3, "####"), df_est_cd!$C$2:$C$100, 0), MATCH(TEXT(M$11, "####"), df_est_cd!$D$1:$AB$1, 0)) + INDEX(df_est_cd!$D$2:$AB$100, MATCH(TEXT($Q16 * 5 + 2, "####"), df_est_cd!$C$2:$C$100, 0), MATCH(TEXT(M$11, "####"), df_est_cd!$D$1:$AB$1, 0)) + INDEX(df_est_cd!$D$2:$AB$100, MATCH(TEXT($Q16 * 5 + 1, "####"), df_est_cd!$C$2:$C$100, 0), MATCH(TEXT(M$11, "####"), df_est_cd!$D$1:$AB$1, 0)) + INDEX(df_est_cd!$D$2:$AB$100, MATCH(TEXT($Q16 * 5, "####"), df_est_cd!$C$2:$C$100, 0), MATCH(TEXT(M$11, "####"), df_est_cd!$D$1:$AB$1, 0)) -> 2059975 | N16: =INDEX(df_est_cd!$D$2:$AB$100, MATCH(TEXT($Q16 * 5 + 4, "####"), df_est_cd!$C$2:$C$100, 0), MATCH(TEXT(N$11, "####"), df_est_cd!$D$1:$AB$1, 0)) + INDEX(df_est_cd!$D$2:$AB$100, MATCH(TEXT($Q16 * 5 + 3, "####"), df_est_cd!$C$2:$C$100, 0), MATCH(TEXT(N$11, "####"), df_est_cd!$D$1:$AB$1, 0)) + INDEX(df_est_cd!$D$2:$AB$100, MATCH(TEXT($Q16 * 5 + 2, "####"), df_est_cd!$C$2:$C$100, 0), MATCH(TEXT(N$11, "####"), df_est_cd!$D$1:$AB$1, 0)) + INDEX(df_est_cd!$D$2:$AB$100, MATCH(TEXT($Q16 * 5 + 1, "####"), df_est_cd!$C$2:$C$100, 0), MATCH(TEXT(N$11, "####"), df_est_cd!$D$1:$AB$1, 0)) + INDEX(df_est_cd!$D$2:$AB$100, MATCH(TEXT($Q16 * 5, "####"), df_est_cd!$C$2:$C$100, 0), MATCH(TEXT(N$11, "####"), df_est_cd!$D$1:$AB$1, 0)) -> 2319393 | O16: =INDEX(df_est_pr!$D$2:$AB$100, MATCH(TEXT($Q16 * 5 + 4, "####"), df_est_pr!$C$2:$C$100, 0), MATCH(TEXT(O$11, "####"), df_est_pr!$D$1:$AB$1, 0)) + INDEX(df_est_pr!$D$2:$AB$100, MATCH(TEXT($Q16 * 5 + 3, "####"), df_est_pr!$C$2:$C$100, 0), MATCH(TEXT(O$11, "####"), df_est_pr!$D$1:$AB$1, 0)) + INDEX(df_est_pr!$D$2:$AB$100, MATCH(TEXT($Q16 * 5 + 2, "####"), df_est_pr!$C$2:$C$100, 0), MATCH(TEXT(O$11, "####"), df_est_pr!$D$1:$AB$1, 0)) + INDEX(df_est_pr!$D$2:$AB$100, MATCH(TEXT($Q16 * 5 + 1, "####"), df_est_pr!$C$2:$C$100, 0), MATCH(TEXT(O$11, "####"), df_est_pr!$D$1:$AB$1, 0)) + INDEX(df_est_pr!$D$2:$AB$100, MATCH(TEXT($Q16 * 5, "####"), df_est_pr!$C$2:$C$100, 0), MATCH(TEXT(O$11, "####"), df_est_pr!$D$1:$AB$1, 0)) -> #N/A | P16: =INDEX(df_est_pr!$D$2:$AB$100, MATCH(TEXT($Q16 * 5 + 4, "####"), df_est_pr!$C$2:$C$100, 0), MATCH(TEXT(P$11, "####"), df_est_pr!$D$1:$AB$1, 0)) + INDEX(df_est_pr!$D$2:$AB$100, MATCH(TEXT($Q16 * 5 + 3, "####"), df_est_pr!$C$2:$C$100, 0), MATCH(TEXT(P$11, "####"), df_est_pr!$D$1:$AB$1, 0)) + INDEX(df_est_pr!$D$2:$AB$100, MATCH(TEXT($Q16 * 5 + 2, "####"), df_est_pr!$C$2:$C$100, 0), MATCH(TEXT(P$11, "####"), df_est_pr!$D$1:$AB$1, 0)) + INDEX(df_est_pr!$D$2:$AB$100, MATCH(TEXT($Q16 * 5 + 1, "####"), df_est_pr!$C$2:$C$100, 0), MATCH(TEXT(P$11, "####"), df_est_pr!$D$1:$AB$1, 0)) + INDEX(df_est_pr!$D$2:$AB$100, MATCH(TEXT($Q16 * 5, "####"), df_est_pr!$C$2:$C$100, 0), MATCH(TEXT(P$11, "####"), df_est_pr!$D$1:$AB$1, 0)) -> #N/A | Q16: 3
A17: 15 | B17: 20 to 24 | C17: {=INDEX(df_pop!$C$2:$C$100, MATCH(1, (df_pop!$B$2:$B$100 = $A17) * (df_pop!$E$2:$E$100 = C$11) * (df_pop!$A$2:$A$100 = $A$2), 0), 0)} -> #N/A | D17: {=INDEX(df_pop!$C$2:$C$1000, MATCH(1, (df_pop!$B$2:$B$1000 = $A17) * (df_pop!$E$2:$E$1000 = D$11) * (df_pop!$A$2:$A$1000 = $A$2), 0), 0)} -> #N/A | E17: {=INDEX(df_proj!$E$2:$AD$1000, MATCH(1, ($A$2 = df_proj!$A$2:$A$1000) * (df_proj!$B$2:$B$1000 = $B17) * (df_proj!$C$2:$C$1000 = $D$2), 0), MATCH(TEXT(E$11, "####"), df_proj!$E$1:$AD$1,0))} -> #N/A | F17: {=INDEX(df_pop!$C$2:$C$10000, MATCH(1, (df_pop!$B$2:$B$10000 = $A17) * (df_pop!$E$2:$E$10000 = F$11) * (df_pop!$A$2:$A$10000 = $B$2), 0), 0)} -> #N/A | G17: {=INDEX(df_pop!$C$2:$C$10000, MATCH(1, (df_pop!$B$2:$B$10000 = $A17) * (df_pop!$E$2:$E$10000 = G$11) * (df_pop!$A$2:$A$10000 = $B$2), 0), 0)} -> #N/A | H17: 6 | I17: 20 to 24 | J17: =ROUND(J$12/C$12*C17,0) -> #N/A | K17: =ROUND(K$12/D$12*D17,0) -> #N/A | L17: =IFERROR(INDEX(df_proj!$F$2:$AE$1000, MATCH(1, ($A$2 = df_proj!$B$2:$B$1000) * (df_proj!$E$2:$E$1000 = $H17) * (df_proj!$D$2:$D$1000 = $D$2), 0), MATCH(TEXT(E$11, "####"), df_proj!$F$1:$AE$1,0)),popn_fut!C86) -> #N/A | M17: =INDEX(df_est_cd!$D$2:$AB$100, MATCH(TEXT($Q17 * 5 + 4, "####"), df_est_cd!$C$2:$C$100, 0), MATCH(TEXT(M$11, "####"), df_est_cd!$D$1:$AB$1, 0)) + INDEX(df_est_cd!$D$2:$AB$100, MATCH(TEXT($Q17 * 5 + 3, "####"), df_est_cd!$C$2:$C$100, 0), MATCH(TEXT(M$11, "####"), df_est_cd!$D$1:$AB$1, 0)) + INDEX(df_est_cd!$D$2:$AB$100, MATCH(TEXT($Q17 * 5 + 2, "####"), df_est_cd!$C$2:$C$100, 0), MATCH(TEXT(M$11, "####"), df_est_cd!$D$1:$AB$1, 0)) + INDEX(df_est_cd!$D$2:$AB$100, MATCH(TEXT($Q17 * 5 + 1, "####"), df_est_cd!$C$2:$C$100, 0), MATCH(TEXT(M$11, "####"), df_est_cd!$D$1:$AB$1, 0)) + INDEX(df_est_cd!$D$2:$AB$100, MATCH(TEXT($Q17 * 5, "####"), df_est_cd!$C$2:$C$100, 0), MATCH(TEXT(M$11, "####"), df_est_cd!$D$1:$AB$1, 0)) -> 2404398 | N17: =INDEX(df_est_cd!$D$2:$AB$100, MATCH(TEXT($Q17 * 5 + 4, "####"), df_est_cd!$C$2:$C$100, 0), MATCH(TEXT(N$11, "####"), df_est_cd!$D$1:$AB$1, 0)) + INDEX(df_est_cd!$D$2:$AB$100, MATCH(TEXT($Q17 * 5 + 3, "####"), df_est_cd!$C$2:$C$100, 0), MATCH(TEXT(N$11, "####"), df_est_cd!$D$1:$AB$1, 0)) + INDEX(df_est_cd!$D$2:$AB$100, MATCH(TEXT($Q17 * 5 + 2, "####"), df_est_cd!$C$2:$C$100, 0), MATCH(TEXT(N$11, "####"), df_est_cd!$D$1:$AB$1, 0)) + INDEX(df_est_cd!$D$2:$AB$100, MATCH(TEXT($Q17 * 5 + 1, "####"), df_est_cd!$C$2:$C$100, 0), MATCH(TEXT(N$11, "####"), df_est_cd!$D$1:$AB$1, 0)) + INDEX(df_est_cd!$D$2:$AB$100, MATCH(TEXT($Q17 * 5, "####"), df_est_cd!$C$2:$C$100, 0), MATCH(TEXT(N$11, "####"), df_est_cd!$D$1:$AB$1, 0)) -> 2703780 | O17: =INDEX(df_est_pr!$D$2:$AB$100, MATCH(TEXT($Q17 * 5 + 4, "####"), df_est_pr!$C$2:$C$100, 0), MATCH(TEXT(O$11, "####"), df_est_pr!$D$1:$AB$1, 0)) + INDEX(df_est_pr!$D$2:$AB$100, MATCH(TEXT($Q17 * 5 + 3, "####"), df_est_pr!$C$2:$C$100, 0), MATCH(TEXT(O$11, "####"), df_est_pr!$D$1:$AB$1, 0)) + INDEX(df_est_pr!$D$2:$AB$100, MATCH(TEXT($Q17 * 5 + 2, "####"), df_est_pr!$C$2:$C$100, 0), MATCH(TEXT(O$11, "####"), df_est_pr!$D$1:$AB$1, 0)) + INDEX(df_est_pr!$D$2:$AB$100, MATCH(TEXT($Q17 * 5 + 1, "####"), df_est_pr!$C$2:$C$100, 0), MATCH(TEXT(O$11, "####"), df_est_pr!$D$1:$AB$1, 0)) + INDEX(df_est_pr!$D$2:$AB$100, MATCH(TEXT($Q17 * 5, "####"), df_est_pr!$C$2:$C$100, 0), MATCH(TEXT(O$11, "####"), df_est_pr!$D$1:$AB$1, 0)) -> #N/A | P17: =INDEX(df_est_pr!$D$2:$AB$100, MATCH(TEXT($Q17 * 5 + 4, "####"), df_est_pr!$C$2:$C$100, 0), MATCH(TEXT(P$11, "####"), df_est_pr!$D$1:$AB$1, 0)) + INDEX(df_est_pr!$D$2:$AB$100, MATCH(TEXT($Q17 * 5 + 3, "####"), df_est_pr!$C$2:$C$100, 0), MATCH(TEXT(P$11, "####"), df_est_pr!$D$1:$AB$1, 0)) + INDEX(df_est_pr!$D$2:$AB$100, MATCH(TEXT($Q17 * 5 + 2, "####"), df_est_pr!$C$2:$C$100, 0), MATCH(TEXT(P$11, "####"), df_est_pr!$D$1:$AB$1, 0)) + INDEX(df_est_pr!$D$2:$AB$100, MATCH(TEXT($Q17 * 5 + 1, "####"), df_est_pr!$C$2:$C$100, 0), MATCH(TEXT(P$11, "####"), df_est_pr!$D$1:$AB$1, 0)) + INDEX(df_est_pr!$D$2:$AB$100, MATCH(TEXT($Q17 * 5, "####"), df_est_pr!$C$2:$C$100, 0), MATCH(TEXT(P$11, "####"), df_est_pr!$D$1:$AB$1, 0)) -> #N/A | Q17: 4
A18: 16 | B18: 25 to 29 | C18: {=INDEX(df_pop!$C$2:$C$100, MATCH(1, (df_pop!$B$2:$B$100 = $A18) * (df_pop!$E$2:$E$100 = C$11) * (df_pop!$A$2:$A$100 = $A$2), 0), 0)} -> #N/A | D18: {=INDEX(df_pop!$C$2:$C$1000, MATCH(1, (df_pop!$B$2:$B$1000 = $A18) * (df_pop!$E$2:$E$1000 = D$11) * (df_pop!$A$2:$A$1000 = $A$2), 0), 0)} -> #N/A | E18: {=INDEX(df_proj!$E$2:$AD$1000, MATCH(1, ($A$2 = df_proj!$A$2:$A$1000) * (df_proj!$B$2:$B$1000 = $B18) * (df_proj!$C$2:$C$1000 = $D$2), 0), MATCH(TEXT(E$11, "####"), df_proj!$E$1:$AD$1,0))} -> #N/A | F18: {=INDEX(df_pop!$C$2:$C$10000, MATCH(1, (df_pop!$B$2:$B$10000 = $A18) * (df_pop!$E$2:$E$10000 = F$11) * (df_pop!$A$2:$A$10000 = $B$2), 0), 0)} -> #N/A | G18: {=INDEX(df_pop!$C$2:$C$10000, MATCH(1, (df_pop!$B$2:$B$10000 = $A18) * (df_pop!$E$2:$E$10000 = G$11) * (df_pop!$A$2:$A$10000 = $B$2), 0), 0)} -> #N/A | H18: 7 | I18: 25 to 29 | J18: =ROUND(J$12/C$12*C18,0) -> #N/A | K18: =ROUND(K$12/D$12*D18,0) -> #N/A | L18: =IFERROR(INDEX(df_proj!$F$2:$AE$1000, MATCH(1, ($A$2 = df_proj!$B$2:$B$1000) * (df_proj!$E$2:$E$1000 = $H18) * (df_proj!$D$2:$D$1000 = $D$2), 0), MATCH(TEXT(E$11, "####"), df_proj!$F$1:$AE$1,0)),popn_fut!C87) -> #N/A | M18: =INDEX(df_est_cd!$D$2:$AB$100, MATCH(TEXT($Q18 * 5 + 4, "####"), df_est_cd!$C$2:$C$100, 0), MATCH(TEXT(M$11, "####"), df_est_cd!$D$1:$AB$1, 0)) + INDEX(df_est_cd!$D$2:$AB$100, MATCH(TEXT($Q18 * 5 + 3, "####"), df_est_cd!$C$2:$C$100, 0), MATCH(TEXT(M$11, "####"), df_est_cd!$D$1:$AB$1, 0)) + INDEX(df_est_cd!$D$2:$AB$100, MATCH(TEXT($Q18 * 5 + 2, "####"), df_est_cd!$C$2:$C$100, 0), MATCH(TEXT(M$11, "####"), df_est_cd!$D$1:$AB$1, 0)) + INDEX(df_est_cd!$D$2:$AB$100, MATCH(TEXT($Q18 * 5 + 1, "####"), df_est_cd!$C$2:$C$100, 0), MATCH(TEXT(M$11, "####"), df_est_cd!$D$1:$AB$1, 0)) + INDEX(df_est_cd!$D$2:$AB$100, MATCH(TEXT($Q18 * 5, "####"), df_est_cd!$C$2:$C$100, 0), MATCH(TEXT(M$11, "####"), df_est_cd!$D$1:$AB$1, 0)) -> 2674655 | N18: =INDEX(df_est_cd!$D$2:$AB$100, MATCH(TEXT($Q18 * 5 + 4, "####"), df_est_cd!$C$2:$C$100, 0), MATCH(TEXT(N$11, "####"), df_est_cd!$D$1:$AB$1, 0)) + INDEX(df_est_cd!$D$2:$AB$100, MATCH(TEXT($Q18 * 5 + 3, "####"), df_est_cd!$C$2:$C$100, 0), MATCH(TEXT(N$11, "####"), df_est_cd!$D$1:$AB$1, 0)) + INDEX(df_est_cd!$D$2:$AB$100, MATCH(TEXT($Q18 * 5 + 2, "####"), df_est_cd!$C$2:$C$100, 0), MATCH(TEXT(N$11, "####"), df_est_cd!$D$1:$AB$1, 0)) + INDEX(df_est_cd!$D$2:$AB$100, MATCH(TEXT($Q18 * 5 + 1, "####"), df_est_cd!$C$2:$C$100, 0), MATCH(TEXT(N$11, "####"), df_est_cd!$D$1:$AB$1, 0)) + INDEX(df_est_cd!$D$2:$AB$100, MATCH(TEXT($Q18 * 5, "####"), df_est_cd!$C$2:$C$100, 0), MATCH(TEXT(N$11, "####"), df_est_cd!$D$1:$AB$1, 0)) -> 2995647 | O18: =INDEX(df_est_pr!$D$2:$AB$100, MATCH(TEXT($Q18 * 5 + 4, "####"), df_est_pr!$C$2:$C$100, 0), MATCH(TEXT(O$11, "####"), df_est_pr!$D$1:$AB$1, 0)) + INDEX(df_est_pr!$D$2:$AB$100, MATCH(TEXT($Q18 * 5 + 3, "####"), df_est_pr!$C$2:$C$100, 0), MATCH(TEXT(O$11, "####"), df_est_pr!$D$1:$AB$1, 0)) + INDEX(df_est_pr!$D$2:$AB$100, MATCH(TEXT($Q18 * 5 + 2, "####"), df_est_pr!$C$2:$C$100, 0), MATCH(TEXT(O$11, "####"), df_est_pr!$D$1:$AB$1, 0)) + INDEX(df_est_pr!$D$2:$AB$100, MATCH(TEXT($Q18 * 5 + 1, "####"), df_est_pr!$C$2:$C$100, 0), MATCH(TEXT(O$11, "####"), df_est_pr!$D$1:$AB$1, 0)) + INDEX(df_est_pr!$D$2:$AB$100, MATCH(TEXT($Q18 * 5, "####"), df_est_pr!$C$2:$C$100, 0), MATCH(TEXT(O$11, "####"), df_est_pr!$D$1:$AB$1, 0)) -> #N/A | P18: =INDEX(df_est_pr!$D$2:$AB$100, MATCH(TEXT($Q18 * 5 + 4, "####"), df_est_pr!$C$2:$C$100, 0), MATCH(TEXT(P$11, "####"), df_est_pr!$D$1:$AB$1, 0)) + INDEX(df_est_pr!$D$2:$AB$100, MATCH(TEXT($Q18 * 5 + 3, "####"), df_est_pr!$C$2:$C$100, 0), MATCH(TEXT(P$11, "####"), df_est_pr!$D$1:$AB$1, 0)) + INDEX(df_est_pr!$D$2:$AB$100, MATCH(TEXT($Q18 * 5 + 2, "####"), df_est_pr!$C$2:$C$100, 0), MATCH(TEXT(P$11, "####"), df_est_pr!$D$1:$AB$1, 0)) + INDEX(df_est_pr!$D$2:$AB$100, MATCH(TEXT($Q18 * 5 + 1, "####"), df_est_pr!$C$2:$C$100, 0), MATCH(TEXT(P$11, "####"), df_est_pr!$D$1:$AB$1, 0)) + INDEX(df_est_pr!$D$2:$AB$100, MATCH(TEXT($Q18 * 5, "####"), df_est_pr!$C$2:$C$100, 0), MATCH(TEXT(P$11, "####"), df_est_pr!$D$1:$AB$1, 0)) -> #N/A | Q18: 5
A19: 17 | B19: 30 to 34 | C19: {=INDEX(df_pop!$C$2:$C$100, MATCH(1, (df_pop!$B$2:$B$100 = $A19) * (df_pop!$E$2:$E$100 = C$11) * (df_pop!$A$2:$A$100 = $A$2), 0), 0)} -> #N/A | D19: {=INDEX(df_pop!$C$2:$C$1000, MATCH(1, (df_pop!$B$2:$B$1000 = $A19) * (df_pop!$E$2:$E$1000 = D$11) * (df_pop!$A$2:$A$1000 = $A$2), 0), 0)} -> #N/A | E19: {=INDEX(df_proj!$E$2:$AD$1000, MATCH(1, ($A$2 = df_proj!$A$2:$A$1000) * (df_proj!$B$2:$B$1000 = $B19) * (df_proj!$C$2:$C$1000 = $D$2), 0), MATCH(TEXT(E$11, "####"), df_proj!$E$1:$AD$1,0))} -> #N/A | F19: {=INDEX(df_pop!$C$2:$C$10000, MATCH(1, (df_pop!$B$2:$B$10000 = $A19) * (df_pop!$E$2:$E$10000 = F$11) * (df_pop!$A$2:$A$10000 = $B$2), 0), 0)} -> #N/A | G19: {=INDEX(df_pop!$C$2:$C$10000, MATCH(1, (df_pop!$B$2:$B$10000 = $A19) * (df_pop!$E$2:$E$10000 = G$11) * (df_pop!$A$2:$A$10000 = $B$2), 0), 0)} -> #N/A | H19: 8 | I19: 30 to 34 | J19: =ROUND(J$12/C$12*C19,0) -> #N/A | K19: =ROUND(K$12/D$12*D19,0) -> #N/A | L19: =IFERROR(INDEX(df_proj!$F$2:$AE$1000, MATCH(1, ($A$2 = df_proj!$B$2:$B$1000) * (df_proj!$E$2:$E$1000 = $H19) * (df_proj!$D$2:$D$1000 = $D$2), 0), MATCH(TEXT(E$11, "####"), df_proj!$F$1:$AE$1,0)),popn_fut!C88) -> #N/A | M19: =INDEX(df_est_cd!$D$2:$AB$100, MATCH(TEXT($Q19 * 5 + 4, "####"), df_est_cd!$C$2:$C$100, 0), MATCH(TEXT(M$11, "####"), df_est_cd!$D$1:$AB$1, 0)) + INDEX(df_est_cd!$D$2:$AB$100, MATCH(TEXT($Q19 * 5 + 3, "####"), df_est_cd!$C$2:$C$100, 0), MATCH(TEXT(M$11, "####"), df_est_cd!$D$1:$AB$1, 0)) + INDEX(df_est_cd!$D$2:$AB$100, MATCH(TEXT($Q19 * 5 + 2, "####"), df_est_cd!$C$2:$C$100, 0), MATCH(TEXT(M$11, "####"), df_est_cd!$D$1:$AB$1, 0)) + INDEX(df_est_cd!$D$2:$AB$100, MATCH(TEXT($Q19 * 5 + 1, "####"), df_est_cd!$C$2:$C$100, 0), MATCH(TEXT(M$11, "####"), df_est_cd!$D$1:$AB$1, 0)) + INDEX(df_est_cd!$D$2:$AB$100, MATCH(TEXT($Q19 * 5, "####"), df_est_cd!$C$2:$C$100, 0), MATCH(TEXT(M$11, "####"), df_est_cd!$D$1:$AB$1, 0)) -> 2704004 | N19: =INDEX(df_est_cd!$D$2:$AB$100, MATCH(TEXT($Q19 * 5 + 4, "####"), df_est_cd!$C$2:$C$100, 0), MATCH(TEXT(N$11, "####"), df_est_cd!$D$1:$AB$1, 0)) + INDEX(df_est_cd!$D$2:$AB$100, MATCH(TEXT($Q19 * 5 + 3, "####"), df_est_cd!$C$2:$C$100, 0), MATCH(TEXT(N$11, "####"), df_est_cd!$D$1:$AB$1, 0)) + INDEX(df_est_cd!$D$2:$AB$100, MATCH(TEXT($Q19 * 5 + 2, "####"), df_est_cd!$C$2:$C$100, 0), MATCH(TEXT(N$11, "####"), df_est_cd!$D$1:$AB$1, 0)) + INDEX(df_est_cd!$D$2:$AB$100, MATCH(TEXT($Q19 * 5 + 1, "####"), df_est_cd!$C$2:$C$100, 0), MATCH(TEXT(N$11, "####"), df_est_cd!$D$1:$AB$1, 0)) + INDEX(df_est_cd!$D$2:$AB$100, MATCH(TEXT($Q19 * 5, "####"), df_est_cd!$C$2:$C$100, 0), MATCH(TEXT(N$11, "####"), df_est_cd!$D$1:$AB$1, 0)) -> 3175724 | O19: =INDEX(df_est_pr!$D$2:$AB$100, MATCH(TEXT($Q19 * 5 + 4, "####"), df_est_pr!$C$2:$C$100, 0), MATCH(TEXT(O$11, "####"), df_est_pr!$D$1:$AB$1, 0)) + INDEX(df_est_pr!$D$2:$AB$100, MATCH(TEXT($Q19 * 5 + 3, "####"), df_est_pr!$C$2:$C$100, 0), MATCH(TEXT(O$11, "####"), df_est_pr!$D$1:$AB$1, 0)) + INDEX(df_est_pr!$D$2:$AB$100, MATCH(TEXT($Q19 * 5 + 2, "####"), df_est_pr!$C$2:$C$100, 0), MATCH(TEXT(O$11, "####"), df_est_pr!$D$1:$AB$1, 0)) + INDEX(df_est_pr!$D$2:$AB$100, MATCH(TEXT($Q19 * 5 + 1, "####"), df_est_pr!$C$2:$C$100, 0), MATCH(TEXT(O$11, "####"), df_est_pr!$D$1:$AB$1, 0)) + INDEX(df_est_pr!$D$2:$AB$100, MATCH(TEXT($Q19 * 5, "####"), df_est_pr!$C$2:$C$100, 0), MATCH(TEXT(O$11, "####"), df_est_pr!$D$1:$AB$1, 0)) -> #N/A | P19: =INDEX(df_est_pr!$D$2:$AB$100, MATCH(TEXT($Q19 * 5 + 4, "####"), df_est_pr!$C$2:$C$100, 0), MATCH(TEXT(P$11, "####"), df_est_pr!$D$1:$AB$1, 0)) + INDEX(df_est_pr!$D$2:$AB$100, MATCH(TEXT($Q19 * 5 + 3, "####"), df_est_pr!$C$2:$C$100, 0), MATCH(TEXT(P$11, "####"), df_est_pr!$D$1:$AB$1, 0)) + INDEX(df_est_pr!$D$2:$AB$100, MATCH(TEXT($Q19 * 5 + 2, "####"), df_est_pr!$C$2:$C$100, 0), MATCH(TEXT(P$11, "####"), df_est_pr!$D$1:$AB$1, 0)) + INDEX(df_est_pr!$D$2:$AB$100, MATCH(TEXT($Q19 * 5 + 1, "####"), df_est_pr!$C$2:$C$100, 0), MATCH(TEXT(P$11, "####"), df_est_pr!$D$1:$AB$1, 0)) + INDEX(df_est_pr!$D$2:$AB$100, MATCH(TEXT($Q19 * 5, "####"), df_est_pr!$C$2:$C$100, 0), MATCH(TEXT(P$11, "####"), df_est_pr!$D$1:$AB$1, 0)) -> #N/A | Q19: 6
